{"__type__":"sp.SkeletonData","_name":"Effect","skeletonJsonStr":"{\"skeleton\":{\"hash\":\"SN2G/Yig/pRl4AKRXB0e1rndcUI\",\"spine\":\"3.7.94\",\"width\":1196.06,\"height\":1191.33,\"images\":\"./images/\",\"audio\":\"F:/GAMEBAI/DOING/THANQUAY2/EFFECT VICTORY/Thuycung\"},\"bones\":[{\"name\":\"root\",\"y\":6.05},{\"name\":\"effect03\",\"parent\":\"root\",\"y\":146.6,\"scaleX\":1.505,\"scaleY\":1.505},{\"name\":\"bone3\",\"parent\":\"root\",\"length\":142.22,\"rotation\":0.44,\"x\":-65.25,\"y\":580.9},{\"name\":\"Fire2\",\"parent\":\"bone3\",\"rotation\":-0.69,\"x\":290.18,\"y\":23.33,\"scaleX\":0.622,\"scaleY\":0.622,\"color\":\"00f6ffff\"},{\"name\":\"Fire3\",\"parent\":\"bone3\",\"rotation\":-0.69,\"x\":174.62,\"y\":22.75,\"scaleX\":0.501,\"scaleY\":0.501,\"color\":\"00f6ffff\"},{\"name\":\"Fire4\",\"parent\":\"bone3\",\"rotation\":-0.69,\"x\":115.7,\"y\":23.46,\"scaleX\":0.423,\"scaleY\":0.423,\"color\":\"00f6ffff\"},{\"name\":\"Fire5\",\"parent\":\"bone3\",\"rotation\":-0.69,\"x\":58.08,\"y\":24.15,\"scaleX\":0.761,\"scaleY\":0.761,\"color\":\"00f6ffff\"},{\"name\":\"Fire7\",\"parent\":\"bone3\",\"rotation\":-0.69,\"x\":-62.89,\"y\":25.6,\"scaleX\":0.465,\"scaleY\":0.465,\"color\":\"00f6ffff\"},{\"name\":\"Fire8\",\"parent\":\"bone3\",\"rotation\":-0.69,\"x\":-108.92,\"y\":26.15,\"scaleX\":0.289,\"scaleY\":0.289,\"color\":\"00f6ffff\"},{\"name\":\"Fire9\",\"parent\":\"bone3\",\"rotation\":-0.69,\"x\":-108.25,\"y\":81.94,\"scaleX\":0.609,\"scaleY\":0.609,\"color\":\"00f6ffff\"},{\"name\":\"Fire10\",\"parent\":\"bone3\",\"rotation\":-0.69,\"x\":231.29,\"y\":84.01,\"scaleX\":0.502,\"scaleY\":0.502,\"color\":\"00f6ffff\"},{\"name\":\"Fire11\",\"parent\":\"bone3\",\"rotation\":-0.69,\"x\":118.27,\"y\":84.19,\"scaleX\":0.67,\"scaleY\":0.67,\"color\":\"00f6ffff\"},{\"name\":\"Fire12\",\"parent\":\"bone3\",\"rotation\":-0.69,\"x\":-1.41,\"y\":78.91,\"scaleX\":0.352,\"scaleY\":0.352,\"color\":\"00f6ffff\"},{\"name\":\"Fire13\",\"parent\":\"bone3\",\"rotation\":-0.69,\"x\":173.55,\"y\":81.56,\"scaleX\":0.684,\"scaleY\":0.684,\"color\":\"00f6ffff\"},{\"name\":\"Fire14\",\"parent\":\"bone3\",\"rotation\":-0.69,\"x\":294.98,\"y\":86.4,\"scaleX\":0.44,\"scaleY\":0.44,\"color\":\"00f6ffff\"},{\"name\":\"Fire15\",\"parent\":\"bone3\",\"rotation\":-0.69,\"x\":-57.96,\"y\":81.21,\"scaleX\":0.289,\"scaleY\":0.289,\"color\":\"00f6ffff\"},{\"name\":\"Fire16\",\"parent\":\"bone3\",\"rotation\":-0.69,\"x\":57.8,\"y\":81.36,\"scaleX\":0.423,\"scaleY\":0.423,\"color\":\"00f6ffff\"},{\"name\":\"Fire30\",\"parent\":\"bone3\",\"rotation\":-0.69,\"x\":290.18,\"y\":23.33,\"scaleX\":0.622,\"scaleY\":0.622,\"color\":\"00f6ffff\"},{\"name\":\"Fire31\",\"parent\":\"bone3\",\"rotation\":-0.69,\"x\":174.62,\"y\":22.75,\"scaleX\":0.501,\"scaleY\":0.501,\"color\":\"00f6ffff\"},{\"name\":\"Fire32\",\"parent\":\"bone3\",\"rotation\":-0.69,\"x\":115.7,\"y\":23.46,\"scaleX\":0.423,\"scaleY\":0.423,\"color\":\"00f6ffff\"},{\"name\":\"Fire33\",\"parent\":\"bone3\",\"rotation\":-0.69,\"x\":58.08,\"y\":24.15,\"scaleX\":0.761,\"scaleY\":0.761,\"color\":\"00f6ffff\"},{\"name\":\"Fire34\",\"parent\":\"bone3\",\"rotation\":-0.69,\"x\":-62.89,\"y\":25.6,\"scaleX\":0.465,\"scaleY\":0.465,\"color\":\"00f6ffff\"},{\"name\":\"Fire35\",\"parent\":\"bone3\",\"rotation\":-0.69,\"x\":-108.92,\"y\":26.15,\"scaleX\":0.289,\"scaleY\":0.289,\"color\":\"00f6ffff\"},{\"name\":\"Fire36\",\"parent\":\"bone3\",\"rotation\":-0.69,\"x\":-108.25,\"y\":81.94,\"scaleX\":0.609,\"scaleY\":0.609,\"color\":\"00f6ffff\"},{\"name\":\"Fire37\",\"parent\":\"bone3\",\"rotation\":-0.69,\"x\":231.29,\"y\":84.01,\"scaleX\":0.502,\"scaleY\":0.502,\"color\":\"00f6ffff\"},{\"name\":\"Fire38\",\"parent\":\"bone3\",\"rotation\":-0.69,\"x\":118.27,\"y\":84.19,\"scaleX\":0.67,\"scaleY\":0.67,\"color\":\"00f6ffff\"},{\"name\":\"Fire39\",\"parent\":\"bone3\",\"rotation\":-0.69,\"x\":-1.41,\"y\":78.91,\"scaleX\":0.352,\"scaleY\":0.352,\"color\":\"00f6ffff\"},{\"name\":\"Fire40\",\"parent\":\"bone3\",\"rotation\":-0.69,\"x\":173.55,\"y\":81.56,\"scaleX\":0.684,\"scaleY\":0.684,\"color\":\"00f6ffff\"},{\"name\":\"Fire41\",\"parent\":\"bone3\",\"rotation\":-0.69,\"x\":294.98,\"y\":86.4,\"scaleX\":0.44,\"scaleY\":0.44,\"color\":\"00f6ffff\"},{\"name\":\"Fire42\",\"parent\":\"bone3\",\"rotation\":-0.69,\"x\":-57.96,\"y\":81.21,\"scaleX\":0.289,\"scaleY\":0.289,\"color\":\"00f6ffff\"},{\"name\":\"Fire43\",\"parent\":\"bone3\",\"rotation\":-0.69,\"x\":57.8,\"y\":81.36,\"scaleX\":0.423,\"scaleY\":0.423,\"color\":\"00f6ffff\"},{\"name\":\"Fire6\",\"parent\":\"bone3\",\"rotation\":-0.69,\"x\":290.18,\"y\":23.33,\"scaleX\":0.622,\"scaleY\":0.622,\"color\":\"00f6ffff\"},{\"name\":\"Fire17\",\"parent\":\"bone3\",\"rotation\":-0.69,\"x\":174.62,\"y\":22.75,\"scaleX\":0.501,\"scaleY\":0.501,\"color\":\"00f6ffff\"},{\"name\":\"Fire18\",\"parent\":\"bone3\",\"rotation\":-0.69,\"x\":115.7,\"y\":23.46,\"scaleX\":0.423,\"scaleY\":0.423,\"color\":\"00f6ffff\"},{\"name\":\"Fire19\",\"parent\":\"bone3\",\"rotation\":-0.69,\"x\":58.08,\"y\":24.15,\"scaleX\":0.761,\"scaleY\":0.761,\"color\":\"00f6ffff\"},{\"name\":\"Fire20\",\"parent\":\"bone3\",\"rotation\":-0.69,\"x\":-62.89,\"y\":25.6,\"scaleX\":0.465,\"scaleY\":0.465,\"color\":\"00f6ffff\"},{\"name\":\"Fire21\",\"parent\":\"bone3\",\"rotation\":-0.69,\"x\":-108.92,\"y\":26.15,\"scaleX\":0.289,\"scaleY\":0.289,\"color\":\"00f6ffff\"},{\"name\":\"Fire22\",\"parent\":\"bone3\",\"rotation\":-0.69,\"x\":-108.25,\"y\":81.94,\"scaleX\":0.609,\"scaleY\":0.609,\"color\":\"00f6ffff\"},{\"name\":\"Fire23\",\"parent\":\"bone3\",\"rotation\":-0.69,\"x\":231.29,\"y\":84.01,\"scaleX\":0.502,\"scaleY\":0.502,\"color\":\"00f6ffff\"},{\"name\":\"Fire24\",\"parent\":\"bone3\",\"rotation\":-0.69,\"x\":118.27,\"y\":84.19,\"scaleX\":0.67,\"scaleY\":0.67,\"color\":\"00f6ffff\"},{\"name\":\"Fire25\",\"parent\":\"bone3\",\"rotation\":-0.69,\"x\":-1.41,\"y\":78.91,\"scaleX\":0.352,\"scaleY\":0.352,\"color\":\"00f6ffff\"},{\"name\":\"Fire26\",\"parent\":\"bone3\",\"rotation\":-0.69,\"x\":173.55,\"y\":81.56,\"scaleX\":0.684,\"scaleY\":0.684,\"color\":\"00f6ffff\"},{\"name\":\"Fire27\",\"parent\":\"bone3\",\"rotation\":-0.69,\"x\":294.98,\"y\":86.4,\"scaleX\":0.44,\"scaleY\":0.44,\"color\":\"00f6ffff\"},{\"name\":\"Fire28\",\"parent\":\"bone3\",\"rotation\":-0.69,\"x\":-57.96,\"y\":81.21,\"scaleX\":0.289,\"scaleY\":0.289,\"color\":\"00f6ffff\"},{\"name\":\"Fire29\",\"parent\":\"bone3\",\"rotation\":-0.69,\"x\":57.8,\"y\":81.36,\"scaleX\":0.423,\"scaleY\":0.423,\"color\":\"00f6ffff\"},{\"name\":\"Fire44\",\"parent\":\"bone3\",\"rotation\":-0.69,\"x\":290.18,\"y\":23.33,\"scaleX\":0.622,\"scaleY\":0.622,\"color\":\"00f6ffff\"},{\"name\":\"Fire45\",\"parent\":\"bone3\",\"rotation\":-0.69,\"x\":174.62,\"y\":22.75,\"scaleX\":0.501,\"scaleY\":0.501,\"color\":\"00f6ffff\"},{\"name\":\"Fire46\",\"parent\":\"bone3\",\"rotation\":-0.69,\"x\":115.7,\"y\":23.46,\"scaleX\":0.423,\"scaleY\":0.423,\"color\":\"00f6ffff\"},{\"name\":\"Fire47\",\"parent\":\"bone3\",\"rotation\":-0.69,\"x\":58.08,\"y\":24.15,\"scaleX\":0.761,\"scaleY\":0.761,\"color\":\"00f6ffff\"},{\"name\":\"Fire48\",\"parent\":\"bone3\",\"rotation\":-0.69,\"x\":-62.89,\"y\":25.6,\"scaleX\":0.465,\"scaleY\":0.465,\"color\":\"00f6ffff\"},{\"name\":\"Fire49\",\"parent\":\"bone3\",\"rotation\":-0.69,\"x\":-108.92,\"y\":26.15,\"scaleX\":0.289,\"scaleY\":0.289,\"color\":\"00f6ffff\"},{\"name\":\"Fire50\",\"parent\":\"bone3\",\"rotation\":-0.69,\"x\":-108.25,\"y\":81.94,\"scaleX\":0.609,\"scaleY\":0.609,\"color\":\"00f6ffff\"},{\"name\":\"Fire51\",\"parent\":\"bone3\",\"rotation\":-0.69,\"x\":231.29,\"y\":84.01,\"scaleX\":0.502,\"scaleY\":0.502,\"color\":\"00f6ffff\"},{\"name\":\"Fire52\",\"parent\":\"bone3\",\"rotation\":-0.69,\"x\":118.27,\"y\":84.19,\"scaleX\":0.67,\"scaleY\":0.67,\"color\":\"00f6ffff\"},{\"name\":\"bone\",\"parent\":\"root\",\"y\":268.81,\"scaleX\":1.574,\"scaleY\":1.574}],\"slots\":[{\"name\":\"Light\",\"bone\":\"bone\",\"attachment\":\"Light\"},{\"name\":\"attack2_02\",\"bone\":\"effect03\",\"attachment\":\"attack2_02\",\"blend\":\"additive\"},{\"name\":\"Fire7\",\"bone\":\"Fire7\"},{\"name\":\"Fire20\",\"bone\":\"Fire20\"},{\"name\":\"Fire48\",\"bone\":\"Fire48\"},{\"name\":\"Fire34\",\"bone\":\"Fire34\"},{\"name\":\"Fire49\",\"bone\":\"Fire49\"},{\"name\":\"Fire21\",\"bone\":\"Fire21\"},{\"name\":\"Fire28\",\"bone\":\"Fire28\"},{\"name\":\"Fire50\",\"bone\":\"Fire50\"},{\"name\":\"Fire8\",\"bone\":\"Fire8\"},{\"name\":\"Fire52\",\"bone\":\"Fire52\"},{\"name\":\"Fire35\",\"bone\":\"Fire35\"},{\"name\":\"Fire29\",\"bone\":\"Fire29\"},{\"name\":\"Fire22\",\"bone\":\"Fire22\"},{\"name\":\"Fire45\",\"bone\":\"Fire45\"},{\"name\":\"Fire15\",\"bone\":\"Fire15\"},{\"name\":\"Fire24\",\"bone\":\"Fire24\"},{\"name\":\"Fire51\",\"bone\":\"Fire51\"},{\"name\":\"Fire42\",\"bone\":\"Fire42\"},{\"name\":\"Fire46\",\"bone\":\"Fire46\"},{\"name\":\"Fire27\",\"bone\":\"Fire27\"},{\"name\":\"Fire47\",\"bone\":\"Fire47\"},{\"name\":\"Fire44\",\"bone\":\"Fire44\"},{\"name\":\"Fire26\",\"bone\":\"Fire26\"},{\"name\":\"Fire16\",\"bone\":\"Fire16\"},{\"name\":\"Fire43\",\"bone\":\"Fire43\"},{\"name\":\"Fire17\",\"bone\":\"Fire17\"},{\"name\":\"Fire25\",\"bone\":\"Fire25\"},{\"name\":\"Fire9\",\"bone\":\"Fire9\"},{\"name\":\"Fire23\",\"bone\":\"Fire23\"},{\"name\":\"Fire36\",\"bone\":\"Fire36\"},{\"name\":\"Fire18\",\"bone\":\"Fire18\"},{\"name\":\"Fire19\",\"bone\":\"Fire19\"},{\"name\":\"Fire11\",\"bone\":\"Fire11\"},{\"name\":\"Fire38\",\"bone\":\"Fire38\"},{\"name\":\"Fire6\",\"bone\":\"Fire6\"},{\"name\":\"Fire14\",\"bone\":\"Fire14\"},{\"name\":\"Fire41\",\"bone\":\"Fire41\"},{\"name\":\"Fire13\",\"bone\":\"Fire13\"},{\"name\":\"Fire40\",\"bone\":\"Fire40\"},{\"name\":\"Fire3\",\"bone\":\"Fire3\"},{\"name\":\"Fire31\",\"bone\":\"Fire31\"},{\"name\":\"Fire12\",\"bone\":\"Fire12\"},{\"name\":\"Fire39\",\"bone\":\"Fire39\"},{\"name\":\"Fire10\",\"bone\":\"Fire10\"},{\"name\":\"Fire37\",\"bone\":\"Fire37\"},{\"name\":\"Fire4\",\"bone\":\"Fire4\"},{\"name\":\"Fire32\",\"bone\":\"Fire32\"},{\"name\":\"Fire5\",\"bone\":\"Fire5\"},{\"name\":\"Fire33\",\"bone\":\"Fire33\"},{\"name\":\"Fire2\",\"bone\":\"Fire2\"},{\"name\":\"Fire30\",\"bone\":\"Fire30\"}],\"skins\":{\"default\":{\"Fire10\":{\"phaogiay1\":{\"x\":-2.49,\"y\":-1.65,\"width\":600,\"height\":600},\"phaogiay2\":{\"x\":4.91,\"y\":-1.21,\"width\":600,\"height\":600},\"phaogiay3\":{\"x\":3.4,\"y\":1.85,\"width\":600,\"height\":600}},\"Fire11\":{\"phaogiay1\":{\"x\":-2.49,\"y\":-1.65,\"width\":600,\"height\":600},\"phaogiay2\":{\"x\":4.91,\"y\":-1.2,\"width\":600,\"height\":600},\"phaogiay3\":{\"x\":3.4,\"y\":1.85,\"width\":600,\"height\":600}},\"Fire12\":{\"phaogiay1\":{\"x\":-2.49,\"y\":-1.65,\"width\":600,\"height\":600},\"phaogiay2\":{\"x\":4.91,\"y\":-1.21,\"width\":600,\"height\":600},\"phaogiay3\":{\"x\":3.4,\"y\":1.85,\"width\":600,\"height\":600}},\"Fire13\":{\"phaogiay1\":{\"x\":-2.49,\"y\":-1.65,\"width\":600,\"height\":600},\"phaogiay2\":{\"x\":4.91,\"y\":-1.2,\"width\":600,\"height\":600},\"phaogiay3\":{\"x\":3.4,\"y\":1.85,\"width\":600,\"height\":600}},\"Fire14\":{\"phaogiay1\":{\"x\":-2.49,\"y\":-1.65,\"width\":600,\"height\":600},\"phaogiay2\":{\"x\":4.91,\"y\":-1.2,\"width\":600,\"height\":600},\"phaogiay3\":{\"x\":3.4,\"y\":1.85,\"width\":600,\"height\":600}},\"Fire15\":{\"phaogiay1\":{\"x\":-2.49,\"y\":-1.65,\"width\":600,\"height\":600},\"phaogiay2\":{\"x\":4.91,\"y\":-1.2,\"width\":600,\"height\":600},\"phaogiay3\":{\"x\":3.4,\"y\":1.85,\"width\":600,\"height\":600}},\"Fire16\":{\"phaogiay1\":{\"x\":-2.49,\"y\":-1.65,\"width\":600,\"height\":600},\"phaogiay2\":{\"x\":4.91,\"y\":-1.2,\"width\":600,\"height\":600},\"phaogiay3\":{\"x\":3.4,\"y\":1.85,\"width\":600,\"height\":600}},\"Fire17\":{\"phaogiay1\":{\"x\":-2.49,\"y\":-1.65,\"width\":600,\"height\":600},\"phaogiay2\":{\"x\":4.91,\"y\":-1.21,\"width\":600,\"height\":600},\"phaogiay3\":{\"x\":3.4,\"y\":1.85,\"width\":600,\"height\":600}},\"Fire18\":{\"phaogiay1\":{\"x\":-2.49,\"y\":-1.65,\"width\":600,\"height\":600},\"phaogiay2\":{\"x\":4.91,\"y\":-1.21,\"width\":600,\"height\":600},\"phaogiay3\":{\"x\":3.4,\"y\":1.85,\"width\":600,\"height\":600}},\"Fire19\":{\"phaogiay1\":{\"x\":-2.49,\"y\":-1.65,\"width\":600,\"height\":600},\"phaogiay2\":{\"x\":4.91,\"y\":-1.2,\"width\":600,\"height\":600},\"phaogiay3\":{\"x\":3.4,\"y\":1.85,\"width\":600,\"height\":600}},\"Fire2\":{\"phaogiay1\":{\"x\":-2.49,\"y\":-1.65,\"width\":600,\"height\":600},\"phaogiay2\":{\"x\":4.91,\"y\":-1.2,\"width\":600,\"height\":600},\"phaogiay3\":{\"x\":3.4,\"y\":1.85,\"width\":600,\"height\":600}},\"Fire20\":{\"phaogiay1\":{\"x\":-2.49,\"y\":-1.65,\"width\":600,\"height\":600},\"phaogiay2\":{\"x\":4.91,\"y\":-1.21,\"width\":600,\"height\":600},\"phaogiay3\":{\"x\":3.4,\"y\":1.85,\"width\":600,\"height\":600}},\"Fire21\":{\"phaogiay1\":{\"x\":-2.49,\"y\":-1.65,\"width\":600,\"height\":600},\"phaogiay2\":{\"x\":4.91,\"y\":-1.2,\"width\":600,\"height\":600},\"phaogiay3\":{\"x\":3.4,\"y\":1.85,\"width\":600,\"height\":600}},\"Fire22\":{\"phaogiay1\":{\"x\":-2.49,\"y\":-1.65,\"width\":600,\"height\":600},\"phaogiay2\":{\"x\":4.91,\"y\":-1.2,\"width\":600,\"height\":600},\"phaogiay3\":{\"x\":3.4,\"y\":1.85,\"width\":600,\"height\":600}},\"Fire23\":{\"phaogiay1\":{\"x\":-2.49,\"y\":-1.65,\"width\":600,\"height\":600},\"phaogiay2\":{\"x\":4.91,\"y\":-1.21,\"width\":600,\"height\":600},\"phaogiay3\":{\"x\":3.4,\"y\":1.85,\"width\":600,\"height\":600}},\"Fire24\":{\"phaogiay1\":{\"x\":-2.49,\"y\":-1.65,\"width\":600,\"height\":600},\"phaogiay2\":{\"x\":4.91,\"y\":-1.2,\"width\":600,\"height\":600},\"phaogiay3\":{\"x\":3.4,\"y\":1.85,\"width\":600,\"height\":600}},\"Fire25\":{\"phaogiay1\":{\"x\":-2.49,\"y\":-1.65,\"width\":600,\"height\":600},\"phaogiay2\":{\"x\":4.91,\"y\":-1.21,\"width\":600,\"height\":600},\"phaogiay3\":{\"x\":3.4,\"y\":1.85,\"width\":600,\"height\":600}},\"Fire26\":{\"phaogiay1\":{\"x\":-2.49,\"y\":-1.65,\"width\":600,\"height\":600},\"phaogiay2\":{\"x\":4.91,\"y\":-1.2,\"width\":600,\"height\":600},\"phaogiay3\":{\"x\":3.4,\"y\":1.85,\"width\":600,\"height\":600}},\"Fire27\":{\"phaogiay1\":{\"x\":-2.49,\"y\":-1.65,\"width\":600,\"height\":600},\"phaogiay2\":{\"x\":4.91,\"y\":-1.2,\"width\":600,\"height\":600},\"phaogiay3\":{\"x\":3.4,\"y\":1.85,\"width\":600,\"height\":600}},\"Fire28\":{\"phaogiay1\":{\"x\":-2.49,\"y\":-1.65,\"width\":600,\"height\":600},\"phaogiay2\":{\"x\":4.91,\"y\":-1.2,\"width\":600,\"height\":600},\"phaogiay3\":{\"x\":3.4,\"y\":1.85,\"width\":600,\"height\":600}},\"Fire29\":{\"phaogiay1\":{\"x\":-2.49,\"y\":-1.65,\"width\":600,\"height\":600},\"phaogiay2\":{\"x\":4.91,\"y\":-1.2,\"width\":600,\"height\":600},\"phaogiay3\":{\"x\":3.4,\"y\":1.85,\"width\":600,\"height\":600}},\"Fire3\":{\"phaogiay1\":{\"x\":-2.49,\"y\":-1.65,\"width\":600,\"height\":600},\"phaogiay2\":{\"x\":4.91,\"y\":-1.21,\"width\":600,\"height\":600},\"phaogiay3\":{\"x\":3.4,\"y\":1.85,\"width\":600,\"height\":600}},\"Fire30\":{\"phaogiay1\":{\"x\":-2.49,\"y\":-1.65,\"width\":600,\"height\":600},\"phaogiay2\":{\"x\":4.91,\"y\":-1.2,\"width\":600,\"height\":600},\"phaogiay3\":{\"x\":3.4,\"y\":1.85,\"width\":600,\"height\":600}},\"Fire31\":{\"phaogiay1\":{\"x\":-2.49,\"y\":-1.65,\"width\":600,\"height\":600},\"phaogiay2\":{\"x\":4.91,\"y\":-1.21,\"width\":600,\"height\":600},\"phaogiay3\":{\"x\":3.4,\"y\":1.85,\"width\":600,\"height\":600}},\"Fire32\":{\"phaogiay1\":{\"x\":-2.49,\"y\":-1.65,\"width\":600,\"height\":600},\"phaogiay2\":{\"x\":4.91,\"y\":-1.21,\"width\":600,\"height\":600},\"phaogiay3\":{\"x\":3.4,\"y\":1.85,\"width\":600,\"height\":600}},\"Fire33\":{\"phaogiay1\":{\"x\":-2.49,\"y\":-1.65,\"width\":600,\"height\":600},\"phaogiay2\":{\"x\":4.91,\"y\":-1.2,\"width\":600,\"height\":600},\"phaogiay3\":{\"x\":3.4,\"y\":1.85,\"width\":600,\"height\":600}},\"Fire34\":{\"phaogiay1\":{\"x\":-2.49,\"y\":-1.65,\"width\":600,\"height\":600},\"phaogiay2\":{\"x\":4.91,\"y\":-1.21,\"width\":600,\"height\":600},\"phaogiay3\":{\"x\":3.4,\"y\":1.85,\"width\":600,\"height\":600}},\"Fire35\":{\"phaogiay1\":{\"x\":-2.49,\"y\":-1.65,\"width\":600,\"height\":600},\"phaogiay2\":{\"x\":4.91,\"y\":-1.2,\"width\":600,\"height\":600},\"phaogiay3\":{\"x\":3.4,\"y\":1.85,\"width\":600,\"height\":600}},\"Fire36\":{\"phaogiay1\":{\"x\":-2.49,\"y\":-1.65,\"width\":600,\"height\":600},\"phaogiay2\":{\"x\":4.91,\"y\":-1.2,\"width\":600,\"height\":600},\"phaogiay3\":{\"x\":3.4,\"y\":1.85,\"width\":600,\"height\":600}},\"Fire37\":{\"phaogiay1\":{\"x\":-2.49,\"y\":-1.65,\"width\":600,\"height\":600},\"phaogiay2\":{\"x\":4.91,\"y\":-1.21,\"width\":600,\"height\":600},\"phaogiay3\":{\"x\":3.4,\"y\":1.85,\"width\":600,\"height\":600}},\"Fire38\":{\"phaogiay1\":{\"x\":-2.49,\"y\":-1.65,\"width\":600,\"height\":600},\"phaogiay2\":{\"x\":4.91,\"y\":-1.2,\"width\":600,\"height\":600},\"phaogiay3\":{\"x\":3.4,\"y\":1.85,\"width\":600,\"height\":600}},\"Fire39\":{\"phaogiay1\":{\"x\":-2.49,\"y\":-1.65,\"width\":600,\"height\":600},\"phaogiay2\":{\"x\":4.91,\"y\":-1.21,\"width\":600,\"height\":600},\"phaogiay3\":{\"x\":3.4,\"y\":1.85,\"width\":600,\"height\":600}},\"Fire4\":{\"phaogiay1\":{\"x\":-2.49,\"y\":-1.65,\"width\":600,\"height\":600},\"phaogiay2\":{\"x\":4.91,\"y\":-1.21,\"width\":600,\"height\":600},\"phaogiay3\":{\"x\":3.4,\"y\":1.85,\"width\":600,\"height\":600}},\"Fire40\":{\"phaogiay1\":{\"x\":-2.49,\"y\":-1.65,\"width\":600,\"height\":600},\"phaogiay2\":{\"x\":4.91,\"y\":-1.2,\"width\":600,\"height\":600},\"phaogiay3\":{\"x\":3.4,\"y\":1.85,\"width\":600,\"height\":600}},\"Fire41\":{\"phaogiay1\":{\"x\":-2.49,\"y\":-1.65,\"width\":600,\"height\":600},\"phaogiay2\":{\"x\":4.91,\"y\":-1.2,\"width\":600,\"height\":600},\"phaogiay3\":{\"x\":3.4,\"y\":1.85,\"width\":600,\"height\":600}},\"Fire42\":{\"phaogiay1\":{\"x\":-2.49,\"y\":-1.65,\"width\":600,\"height\":600},\"phaogiay2\":{\"x\":4.91,\"y\":-1.2,\"width\":600,\"height\":600},\"phaogiay3\":{\"x\":3.4,\"y\":1.85,\"width\":600,\"height\":600}},\"Fire43\":{\"phaogiay1\":{\"x\":-2.49,\"y\":-1.65,\"width\":600,\"height\":600},\"phaogiay2\":{\"x\":4.91,\"y\":-1.2,\"width\":600,\"height\":600},\"phaogiay3\":{\"x\":3.4,\"y\":1.85,\"width\":600,\"height\":600}},\"Fire44\":{\"phaogiay1\":{\"x\":-2.49,\"y\":-1.65,\"width\":600,\"height\":600},\"phaogiay2\":{\"x\":4.91,\"y\":-1.2,\"width\":600,\"height\":600},\"phaogiay3\":{\"x\":3.4,\"y\":1.85,\"width\":600,\"height\":600}},\"Fire45\":{\"phaogiay1\":{\"x\":-2.49,\"y\":-1.65,\"width\":600,\"height\":600},\"phaogiay2\":{\"x\":4.91,\"y\":-1.21,\"width\":600,\"height\":600},\"phaogiay3\":{\"x\":3.4,\"y\":1.85,\"width\":600,\"height\":600}},\"Fire46\":{\"phaogiay1\":{\"x\":-2.49,\"y\":-1.65,\"width\":600,\"height\":600},\"phaogiay2\":{\"x\":4.91,\"y\":-1.21,\"width\":600,\"height\":600},\"phaogiay3\":{\"x\":3.4,\"y\":1.85,\"width\":600,\"height\":600}},\"Fire47\":{\"phaogiay1\":{\"x\":-2.49,\"y\":-1.65,\"width\":600,\"height\":600},\"phaogiay2\":{\"x\":4.91,\"y\":-1.2,\"width\":600,\"height\":600},\"phaogiay3\":{\"x\":3.4,\"y\":1.85,\"width\":600,\"height\":600}},\"Fire48\":{\"phaogiay1\":{\"x\":-2.49,\"y\":-1.65,\"width\":600,\"height\":600},\"phaogiay2\":{\"x\":4.91,\"y\":-1.21,\"width\":600,\"height\":600},\"phaogiay3\":{\"x\":3.4,\"y\":1.85,\"width\":600,\"height\":600}},\"Fire49\":{\"phaogiay1\":{\"x\":-2.49,\"y\":-1.65,\"width\":600,\"height\":600},\"phaogiay2\":{\"x\":4.91,\"y\":-1.2,\"width\":600,\"height\":600},\"phaogiay3\":{\"x\":3.4,\"y\":1.85,\"width\":600,\"height\":600}},\"Fire5\":{\"phaogiay1\":{\"x\":-2.49,\"y\":-1.65,\"width\":600,\"height\":600},\"phaogiay2\":{\"x\":4.91,\"y\":-1.2,\"width\":600,\"height\":600},\"phaogiay3\":{\"x\":3.4,\"y\":1.85,\"width\":600,\"height\":600}},\"Fire50\":{\"phaogiay1\":{\"x\":-2.49,\"y\":-1.65,\"width\":600,\"height\":600},\"phaogiay2\":{\"x\":4.91,\"y\":-1.2,\"width\":600,\"height\":600},\"phaogiay3\":{\"x\":3.4,\"y\":1.85,\"width\":600,\"height\":600}},\"Fire51\":{\"phaogiay1\":{\"x\":-2.49,\"y\":-1.65,\"width\":600,\"height\":600},\"phaogiay2\":{\"x\":4.91,\"y\":-1.21,\"width\":600,\"height\":600},\"phaogiay3\":{\"x\":3.4,\"y\":1.85,\"width\":600,\"height\":600}},\"Fire52\":{\"phaogiay1\":{\"x\":-2.49,\"y\":-1.65,\"width\":600,\"height\":600},\"phaogiay2\":{\"x\":4.91,\"y\":-1.2,\"width\":600,\"height\":600},\"phaogiay3\":{\"x\":3.4,\"y\":1.85,\"width\":600,\"height\":600}},\"Fire6\":{\"phaogiay1\":{\"x\":-2.49,\"y\":-1.65,\"width\":600,\"height\":600},\"phaogiay2\":{\"x\":4.91,\"y\":-1.2,\"width\":600,\"height\":600},\"phaogiay3\":{\"x\":3.4,\"y\":1.85,\"width\":600,\"height\":600}},\"Fire7\":{\"phaogiay1\":{\"x\":-2.49,\"y\":-1.65,\"width\":600,\"height\":600},\"phaogiay2\":{\"x\":4.91,\"y\":-1.21,\"width\":600,\"height\":600},\"phaogiay3\":{\"x\":3.4,\"y\":1.85,\"width\":600,\"height\":600}},\"Fire8\":{\"phaogiay1\":{\"x\":-2.49,\"y\":-1.65,\"width\":600,\"height\":600},\"phaogiay2\":{\"x\":4.91,\"y\":-1.2,\"width\":600,\"height\":600},\"phaogiay3\":{\"x\":3.4,\"y\":1.85,\"width\":600,\"height\":600}},\"Fire9\":{\"phaogiay1\":{\"x\":-2.49,\"y\":-1.65,\"width\":600,\"height\":600},\"phaogiay2\":{\"x\":4.91,\"y\":-1.2,\"width\":600,\"height\":600},\"phaogiay3\":{\"x\":3.4,\"y\":1.85,\"width\":600,\"height\":600}},\"Light\":{\"Light\":{\"width\":760,\"height\":757}},\"attack2_02\":{\"attack2_02\":{\"type\":\"mesh\",\"uvs\":[1,1,0,1,0,0,1,0],\"triangles\":[1,2,3,1,3,0],\"vertices\":[60,-60,-60,-60,-60,60,60,60],\"hull\":4,\"edges\":[0,2,2,4,4,6,0,6],\"width\":120,\"height\":120}}}},\"animations\":{\"Lop ngoai\":{\"slots\":{\"Fire2\":{\"color\":[{\"time\":0.4,\"color\":\"ffffff00\"},{\"time\":0.4333,\"color\":\"ffffffff\",\"curve\":\"stepped\"},{\"time\":0.9667,\"color\":\"ffffffff\"},{\"time\":1.0667,\"color\":\"ffffff00\"}],\"attachment\":[{\"time\":0.6,\"name\":\"phaogiay2\"}]},\"Fire3\":{\"color\":[{\"time\":0.4,\"color\":\"ffffff00\"},{\"time\":0.4333,\"color\":\"ffffffff\",\"curve\":\"stepped\"},{\"time\":0.9667,\"color\":\"ffffffff\"},{\"time\":1.0667,\"color\":\"ffffff00\"}],\"attachment\":[{\"time\":0.4,\"name\":\"phaogiay1\"}]},\"Fire4\":{\"color\":[{\"time\":0.4,\"color\":\"ffffff00\"},{\"time\":0.4333,\"color\":\"ffffffff\",\"curve\":\"stepped\"},{\"time\":0.9667,\"color\":\"ffffffff\"},{\"time\":1.0667,\"color\":\"ffffff00\"}],\"attachment\":[{\"time\":0.5667,\"name\":\"phaogiay1\"}]},\"Fire5\":{\"color\":[{\"time\":0.4,\"color\":\"ffffff00\"},{\"time\":0.4333,\"color\":\"ffffffff\",\"curve\":\"stepped\"},{\"time\":0.9667,\"color\":\"ffffffff\"},{\"time\":1.0667,\"color\":\"ffffff00\"}],\"attachment\":[{\"time\":0.4667,\"name\":\"phaogiay3\"}]},\"Fire6\":{\"color\":[{\"time\":0.4,\"color\":\"ffffff00\"},{\"time\":0.4333,\"color\":\"ffffffff\",\"curve\":\"stepped\"},{\"time\":0.9667,\"color\":\"ffffffff\"},{\"time\":1.0667,\"color\":\"ffffff00\"}],\"attachment\":[{\"time\":0.6,\"name\":\"phaogiay2\"}]},\"Fire7\":{\"color\":[{\"time\":0.4,\"color\":\"ffffff00\"},{\"time\":0.4667,\"color\":\"ffffffff\"},{\"time\":1.0667,\"color\":\"ffffff00\"}],\"attachment\":[{\"time\":0.4667,\"name\":\"phaogiay1\"}]},\"Fire8\":{\"color\":[{\"time\":1.0667,\"color\":\"ffffff00\"}],\"attachment\":[{\"time\":0.6,\"name\":\"phaogiay3\"}]},\"Fire9\":{\"color\":[{\"time\":0.4,\"color\":\"ffffff00\"},{\"time\":0.4333,\"color\":\"ffffffff\",\"curve\":\"stepped\"},{\"time\":0.9667,\"color\":\"ffffffff\"},{\"time\":1.0667,\"color\":\"ffffff00\"}],\"attachment\":[{\"time\":0.6333,\"name\":\"phaogiay3\"}]},\"Fire10\":{\"color\":[{\"time\":0.4,\"color\":\"ffffff00\"},{\"time\":0.4333,\"color\":\"ffffffff\",\"curve\":\"stepped\"},{\"time\":0.9667,\"color\":\"ffffffff\"},{\"time\":1.0667,\"color\":\"ffffff00\"}],\"attachment\":[{\"time\":0.4667,\"name\":\"phaogiay2\"}]},\"Fire11\":{\"color\":[{\"time\":0.4,\"color\":\"ffffff00\"},{\"time\":0.4333,\"color\":\"ffffffff\",\"curve\":\"stepped\"},{\"time\":0.9667,\"color\":\"ffffffff\"},{\"time\":1.0667,\"color\":\"ffffff00\"}],\"attachment\":[{\"time\":0.8333,\"name\":\"phaogiay3\"}]},\"Fire12\":{\"color\":[{\"time\":0.4,\"color\":\"ffffff00\"},{\"time\":0.4333,\"color\":\"ffffffff\",\"curve\":\"stepped\"},{\"time\":0.9667,\"color\":\"ffffffff\"},{\"time\":1.0667,\"color\":\"ffffff00\"}],\"attachment\":[{\"time\":0.5333,\"name\":\"phaogiay2\"}]},\"Fire13\":{\"color\":[{\"time\":0.4,\"color\":\"ffffff00\"},{\"time\":0.4333,\"color\":\"ffffffff\",\"curve\":\"stepped\"},{\"time\":0.9667,\"color\":\"ffffffff\"},{\"time\":1.0667,\"color\":\"ffffff00\"}],\"attachment\":[{\"time\":0.6333,\"name\":\"phaogiay1\"}]},\"Fire14\":{\"color\":[{\"time\":0.4,\"color\":\"ffffff00\"},{\"time\":0.4333,\"color\":\"ffffffff\",\"curve\":\"stepped\"},{\"time\":0.9667,\"color\":\"ffffffff\"},{\"time\":1.0667,\"color\":\"ffffff00\"}],\"attachment\":[{\"time\":0.7,\"name\":\"phaogiay1\"}]},\"Fire15\":{\"color\":[{\"time\":0.4,\"color\":\"ffffff00\"},{\"time\":0.4333,\"color\":\"ffffffff\",\"curve\":\"stepped\"},{\"time\":0.9667,\"color\":\"ffffffff\"},{\"time\":1.0667,\"color\":\"ffffff00\"}],\"attachment\":[{\"time\":0.5333,\"name\":\"phaogiay2\"},{\"time\":1.0667,\"name\":\"phaogiay3\"}]},\"Fire16\":{\"color\":[{\"time\":0.4,\"color\":\"ffffff00\"},{\"time\":0.4333,\"color\":\"ffffffff\",\"curve\":\"stepped\"},{\"time\":0.9667,\"color\":\"ffffffff\"},{\"time\":1.0667,\"color\":\"ffffff00\"}],\"attachment\":[{\"time\":0.5667,\"name\":\"phaogiay1\"}]},\"Fire17\":{\"color\":[{\"time\":0.4,\"color\":\"ffffff00\"},{\"time\":0.4333,\"color\":\"ffffffff\",\"curve\":\"stepped\"},{\"time\":0.9667,\"color\":\"ffffffff\"},{\"time\":1.0667,\"color\":\"ffffff00\"}],\"attachment\":[{\"time\":0.4,\"name\":\"phaogiay1\"}]},\"Fire18\":{\"color\":[{\"time\":0.4,\"color\":\"ffffff00\"},{\"time\":0.4333,\"color\":\"ffffffff\",\"curve\":\"stepped\"},{\"time\":0.9667,\"color\":\"ffffffff\"},{\"time\":1.0667,\"color\":\"ffffff00\"}],\"attachment\":[{\"time\":0.5667,\"name\":\"phaogiay1\"}]},\"Fire19\":{\"color\":[{\"time\":0.4,\"color\":\"ffffff00\"},{\"time\":0.4333,\"color\":\"ffffffff\",\"curve\":\"stepped\"},{\"time\":0.9667,\"color\":\"ffffffff\"},{\"time\":1.0667,\"color\":\"ffffff00\"}],\"attachment\":[{\"time\":0.4667,\"name\":\"phaogiay3\"}]},\"Fire20\":{\"color\":[{\"time\":0.4,\"color\":\"ffffff00\"},{\"time\":0.4667,\"color\":\"ffffffff\"},{\"time\":1.0667,\"color\":\"ffffff00\"}],\"attachment\":[{\"time\":0.4667,\"name\":\"phaogiay1\"}]},\"Fire21\":{\"color\":[{\"time\":1.0667,\"color\":\"ffffff00\"}],\"attachment\":[{\"time\":0.6,\"name\":\"phaogiay3\"}]},\"Fire22\":{\"color\":[{\"time\":0.4,\"color\":\"ffffff00\"},{\"time\":0.4333,\"color\":\"ffffffff\",\"curve\":\"stepped\"},{\"time\":0.9667,\"color\":\"ffffffff\"},{\"time\":1.0667,\"color\":\"ffffff00\"}],\"attachment\":[{\"time\":0.6333,\"name\":\"phaogiay3\"}]},\"Fire23\":{\"color\":[{\"time\":0.4,\"color\":\"ffffff00\"},{\"time\":0.4333,\"color\":\"ffffffff\",\"curve\":\"stepped\"},{\"time\":0.9667,\"color\":\"ffffffff\"},{\"time\":1.0667,\"color\":\"ffffff00\"}],\"attachment\":[{\"time\":0.4667,\"name\":\"phaogiay2\"}]},\"Fire24\":{\"color\":[{\"time\":0.4,\"color\":\"ffffff00\"},{\"time\":0.4333,\"color\":\"ffffffff\",\"curve\":\"stepped\"},{\"time\":0.9667,\"color\":\"ffffffff\"},{\"time\":1.0667,\"color\":\"ffffff00\"}],\"attachment\":[{\"time\":0.8333,\"name\":\"phaogiay3\"}]},\"Fire25\":{\"color\":[{\"time\":0.4,\"color\":\"ffffff00\"},{\"time\":0.4333,\"color\":\"ffffffff\",\"curve\":\"stepped\"},{\"time\":0.9667,\"color\":\"ffffffff\"},{\"time\":1.0667,\"color\":\"ffffff00\"}],\"attachment\":[{\"time\":0.5333,\"name\":\"phaogiay2\"}]},\"Fire26\":{\"color\":[{\"time\":0.4,\"color\":\"ffffff00\"},{\"time\":0.4333,\"color\":\"ffffffff\",\"curve\":\"stepped\"},{\"time\":0.9667,\"color\":\"ffffffff\"},{\"time\":1.0667,\"color\":\"ffffff00\"}],\"attachment\":[{\"time\":0.6333,\"name\":\"phaogiay1\"}]},\"Fire27\":{\"color\":[{\"time\":0.4,\"color\":\"ffffff00\"},{\"time\":0.4333,\"color\":\"ffffffff\",\"curve\":\"stepped\"},{\"time\":0.9667,\"color\":\"ffffffff\"},{\"time\":1.0667,\"color\":\"ffffff00\"}],\"attachment\":[{\"time\":0.7,\"name\":\"phaogiay1\"}]},\"Fire28\":{\"color\":[{\"time\":0.4,\"color\":\"ffffff00\"},{\"time\":0.4333,\"color\":\"ffffffff\",\"curve\":\"stepped\"},{\"time\":0.9667,\"color\":\"ffffffff\"},{\"time\":1.0667,\"color\":\"ffffff00\"}],\"attachment\":[{\"time\":0.5333,\"name\":\"phaogiay2\"},{\"time\":1.0667,\"name\":\"phaogiay3\"}]},\"Fire29\":{\"color\":[{\"time\":0.4,\"color\":\"ffffff00\"},{\"time\":0.4333,\"color\":\"ffffffff\",\"curve\":\"stepped\"},{\"time\":0.9667,\"color\":\"ffffffff\"},{\"time\":1.0667,\"color\":\"ffffff00\"}],\"attachment\":[{\"time\":0.5667,\"name\":\"phaogiay1\"}]},\"Fire30\":{\"color\":[{\"time\":0.8667,\"color\":\"ffffff00\"},{\"time\":0.9,\"color\":\"ffffffff\",\"curve\":\"stepped\"},{\"time\":1.4333,\"color\":\"ffffffff\"},{\"time\":1.5333,\"color\":\"ffffff00\"}],\"attachment\":[{\"time\":1.0667,\"name\":\"phaogiay2\"}]},\"Fire31\":{\"color\":[{\"time\":0.8667,\"color\":\"ffffff00\"},{\"time\":0.9,\"color\":\"ffffffff\",\"curve\":\"stepped\"},{\"time\":1.4333,\"color\":\"ffffffff\"},{\"time\":1.5333,\"color\":\"ffffff00\"}],\"attachment\":[{\"time\":0.8667,\"name\":\"phaogiay1\"}]},\"Fire32\":{\"color\":[{\"time\":0.8667,\"color\":\"ffffff00\"},{\"time\":0.9,\"color\":\"ffffffff\",\"curve\":\"stepped\"},{\"time\":1.4333,\"color\":\"ffffffff\"},{\"time\":1.5333,\"color\":\"ffffff00\"}],\"attachment\":[{\"time\":1.0333,\"name\":\"phaogiay1\"}]},\"Fire33\":{\"color\":[{\"time\":0.8667,\"color\":\"ffffff00\"},{\"time\":0.9,\"color\":\"ffffffff\",\"curve\":\"stepped\"},{\"time\":1.4333,\"color\":\"ffffffff\"},{\"time\":1.5333,\"color\":\"ffffff00\"}],\"attachment\":[{\"time\":0.9333,\"name\":\"phaogiay3\"}]},\"Fire34\":{\"color\":[{\"time\":0.8667,\"color\":\"ffffff00\"},{\"time\":0.9333,\"color\":\"ffffffff\"},{\"time\":1.5333,\"color\":\"ffffff00\"}],\"attachment\":[{\"time\":0.9333,\"name\":\"phaogiay1\"}]},\"Fire35\":{\"color\":[{\"time\":1.5333,\"color\":\"ffffff00\"}],\"attachment\":[{\"time\":1.0667,\"name\":\"phaogiay3\"}]},\"Fire36\":{\"color\":[{\"time\":0.8667,\"color\":\"ffffff00\"},{\"time\":0.9,\"color\":\"ffffffff\",\"curve\":\"stepped\"},{\"time\":1.4333,\"color\":\"ffffffff\"},{\"time\":1.5333,\"color\":\"ffffff00\"}],\"attachment\":[{\"time\":1.1,\"name\":\"phaogiay3\"}]},\"Fire37\":{\"color\":[{\"time\":0.8667,\"color\":\"ffffff00\"},{\"time\":0.9,\"color\":\"ffffffff\",\"curve\":\"stepped\"},{\"time\":1.4333,\"color\":\"ffffffff\"},{\"time\":1.5333,\"color\":\"ffffff00\"}],\"attachment\":[{\"time\":0.9333,\"name\":\"phaogiay2\"}]},\"Fire38\":{\"color\":[{\"time\":0.8667,\"color\":\"ffffff00\"},{\"time\":0.9,\"color\":\"ffffffff\",\"curve\":\"stepped\"},{\"time\":1.4333,\"color\":\"ffffffff\"},{\"time\":1.5333,\"color\":\"ffffff00\"}],\"attachment\":[{\"time\":1.3,\"name\":\"phaogiay3\"}]},\"Fire39\":{\"color\":[{\"time\":0.8667,\"color\":\"ffffff00\"},{\"time\":0.9,\"color\":\"ffffffff\",\"curve\":\"stepped\"},{\"time\":1.4333,\"color\":\"ffffffff\"},{\"time\":1.5333,\"color\":\"ffffff00\"}],\"attachment\":[{\"time\":1,\"name\":\"phaogiay2\"}]},\"Fire40\":{\"color\":[{\"time\":0.8667,\"color\":\"ffffff00\"},{\"time\":0.9,\"color\":\"ffffffff\",\"curve\":\"stepped\"},{\"time\":1.4333,\"color\":\"ffffffff\"},{\"time\":1.5333,\"color\":\"ffffff00\"}],\"attachment\":[{\"time\":1.1,\"name\":\"phaogiay1\"}]},\"Fire41\":{\"color\":[{\"time\":0.8667,\"color\":\"ffffff00\"},{\"time\":0.9,\"color\":\"ffffffff\",\"curve\":\"stepped\"},{\"time\":1.4333,\"color\":\"ffffffff\"},{\"time\":1.5333,\"color\":\"ffffff00\"}],\"attachment\":[{\"time\":1.1667,\"name\":\"phaogiay1\"}]},\"Fire42\":{\"color\":[{\"time\":0.8667,\"color\":\"ffffff00\"},{\"time\":0.9,\"color\":\"ffffffff\",\"curve\":\"stepped\"},{\"time\":1.4333,\"color\":\"ffffffff\"},{\"time\":1.5333,\"color\":\"ffffff00\"}],\"attachment\":[{\"time\":1,\"name\":\"phaogiay2\"},{\"time\":1.5333,\"name\":\"phaogiay3\"}]},\"Fire43\":{\"color\":[{\"time\":0.8667,\"color\":\"ffffff00\"},{\"time\":0.9,\"color\":\"ffffffff\",\"curve\":\"stepped\"},{\"time\":1.4333,\"color\":\"ffffffff\"},{\"time\":1.5333,\"color\":\"ffffff00\"}],\"attachment\":[{\"time\":1.0333,\"name\":\"phaogiay1\"}]},\"Fire44\":{\"color\":[{\"time\":0.4,\"color\":\"ffffff00\"},{\"time\":0.4333,\"color\":\"ffffffff\",\"curve\":\"stepped\"},{\"time\":0.9667,\"color\":\"ffffffff\"},{\"time\":1.0667,\"color\":\"ffffff00\"}],\"attachment\":[{\"time\":0.6,\"name\":\"phaogiay2\"}]},\"Fire45\":{\"color\":[{\"time\":0.4,\"color\":\"ffffff00\"},{\"time\":0.4333,\"color\":\"ffffffff\",\"curve\":\"stepped\"},{\"time\":0.9667,\"color\":\"ffffffff\"},{\"time\":1.0667,\"color\":\"ffffff00\"}],\"attachment\":[{\"time\":0.4,\"name\":\"phaogiay1\"}]},\"Fire46\":{\"color\":[{\"time\":0.4,\"color\":\"ffffff00\"},{\"time\":0.4333,\"color\":\"ffffffff\",\"curve\":\"stepped\"},{\"time\":0.9667,\"color\":\"ffffffff\"},{\"time\":1.0667,\"color\":\"ffffff00\"}],\"attachment\":[{\"time\":0.5667,\"name\":\"phaogiay1\"}]},\"Fire47\":{\"color\":[{\"time\":0.4,\"color\":\"ffffff00\"},{\"time\":0.4333,\"color\":\"ffffffff\",\"curve\":\"stepped\"},{\"time\":0.9667,\"color\":\"ffffffff\"},{\"time\":1.0667,\"color\":\"ffffff00\"}],\"attachment\":[{\"time\":0.4667,\"name\":\"phaogiay3\"}]},\"Fire48\":{\"color\":[{\"time\":0.4,\"color\":\"ffffff00\"},{\"time\":0.4667,\"color\":\"ffffffff\"},{\"time\":1.0667,\"color\":\"ffffff00\"}],\"attachment\":[{\"time\":0.4667,\"name\":\"phaogiay1\"}]},\"Fire49\":{\"color\":[{\"time\":1.0667,\"color\":\"ffffff00\"}],\"attachment\":[{\"time\":0.6,\"name\":\"phaogiay3\"}]},\"Fire50\":{\"color\":[{\"time\":0.4,\"color\":\"ffffff00\"},{\"time\":0.4333,\"color\":\"ffffffff\",\"curve\":\"stepped\"},{\"time\":0.9667,\"color\":\"ffffffff\"},{\"time\":1.0667,\"color\":\"ffffff00\"}],\"attachment\":[{\"time\":0.6333,\"name\":\"phaogiay3\"}]},\"Fire51\":{\"color\":[{\"time\":0.4,\"color\":\"ffffff00\"},{\"time\":0.4333,\"color\":\"ffffffff\",\"curve\":\"stepped\"},{\"time\":0.9667,\"color\":\"ffffffff\"},{\"time\":1.0667,\"color\":\"ffffff00\"}],\"attachment\":[{\"time\":0.4667,\"name\":\"phaogiay2\"}]},\"Fire52\":{\"color\":[{\"time\":0.4,\"color\":\"ffffff00\"},{\"time\":0.4333,\"color\":\"ffffffff\",\"curve\":\"stepped\"},{\"time\":0.9667,\"color\":\"ffffffff\"},{\"time\":1.0667,\"color\":\"ffffff00\"}],\"attachment\":[{\"time\":0.8333,\"name\":\"phaogiay3\"}]},\"Light\":{\"attachment\":[{\"time\":0,\"name\":null}]},\"attack2_02\":{\"attachment\":[{\"time\":0,\"name\":null}]}},\"bones\":{\"bone3\":{\"translate\":[{\"time\":0,\"x\":100.09,\"y\":-28.1}],\"scale\":[{\"time\":0,\"x\":0.255,\"y\":0.255}]},\"Fire51\":{\"rotate\":[{\"time\":0.4,\"angle\":12.86},{\"time\":0.9,\"angle\":29.8},{\"time\":1.0667,\"angle\":19.54}],\"translate\":[{\"time\":0.4,\"x\":-617.28,\"y\":-660.48},{\"time\":0.4667,\"x\":-1724.03,\"y\":37.89},{\"time\":0.9,\"x\":-1550.71,\"y\":-1117.62},{\"time\":1.0667,\"x\":-1871.37,\"y\":-1426.88}],\"shear\":[{\"time\":0.4,\"x\":0,\"y\":0},{\"time\":0.9,\"x\":-30.91,\"y\":-64.34}]},\"Fire7\":{\"rotate\":[{\"time\":0.4,\"angle\":12.86},{\"time\":0.8667,\"angle\":116.51}],\"translate\":[{\"time\":0.4,\"x\":918,\"y\":387},{\"time\":0.8667,\"x\":1404,\"y\":-801},{\"time\":1.0667,\"x\":1707.43,\"y\":-1382.14}],\"shear\":[{\"time\":0.4,\"x\":0,\"y\":0},{\"time\":0.8667,\"x\":59.5,\"y\":42.75}]},\"Fire13\":{\"rotate\":[{\"time\":0.4,\"angle\":0},{\"time\":0.4667,\"angle\":12.86},{\"time\":0.5667,\"angle\":20.76},{\"time\":1.0667,\"angle\":-4.87}],\"translate\":[{\"time\":0.4,\"x\":0,\"y\":0},{\"time\":0.4667,\"x\":-576,\"y\":0},{\"time\":0.5667,\"x\":978.58,\"y\":245.38},{\"time\":1.0667,\"x\":639.3,\"y\":-1993.36}]},\"Fire8\":{\"rotate\":[{\"time\":0.4,\"angle\":12.86,\"curve\":\"stepped\"},{\"time\":0.5667,\"angle\":12.86},{\"time\":1.0667,\"angle\":60.18}],\"translate\":[{\"time\":0.4,\"x\":918,\"y\":387,\"curve\":\"stepped\"},{\"time\":0.5667,\"x\":918,\"y\":387},{\"time\":1.0667,\"x\":127.82,\"y\":-576.02}],\"shear\":[{\"time\":0.5667,\"x\":0,\"y\":0},{\"time\":1.0667,\"x\":-30.38,\"y\":0}]},\"Fire14\":{\"rotate\":[{\"time\":0.4,\"angle\":0},{\"time\":0.5667,\"angle\":-63.11},{\"time\":0.6333,\"angle\":-95.98},{\"time\":1.0667,\"angle\":-141.27}],\"translate\":[{\"time\":0.4,\"x\":0,\"y\":0},{\"time\":0.5667,\"x\":-1529.69,\"y\":417.98},{\"time\":1.0667,\"x\":-1710.66,\"y\":-791.27}]},\"Fire15\":{\"rotate\":[{\"time\":0.4,\"angle\":12.86,\"curve\":\"stepped\"},{\"time\":0.5333,\"angle\":12.86},{\"time\":1.0667,\"angle\":60.18}],\"translate\":[{\"time\":0.4,\"x\":918,\"y\":387},{\"time\":0.5333,\"x\":1471.45,\"y\":-324.61},{\"time\":1.0667,\"x\":1929.08,\"y\":-1445.68}],\"scale\":[{\"time\":0.4,\"x\":1.382,\"y\":1.382}],\"shear\":[{\"time\":0.5333,\"x\":0,\"y\":0},{\"time\":1.0667,\"x\":-30.38,\"y\":0}]},\"Fire3\":{\"rotate\":[{\"time\":0.4,\"angle\":12.86},{\"time\":0.8667,\"angle\":51.85},{\"time\":1.0667,\"angle\":-19.22}],\"translate\":[{\"time\":0.4,\"x\":-576,\"y\":0},{\"time\":0.8667,\"x\":-1179,\"y\":-1962},{\"time\":1.0667,\"x\":-1589.4,\"y\":-2682}],\"shear\":[{\"time\":0.4,\"x\":0,\"y\":0},{\"time\":0.8667,\"x\":-30.91,\"y\":-10.99}]},\"Fire9\":{\"rotate\":[{\"time\":0.4,\"angle\":12.86,\"curve\":\"stepped\"},{\"time\":0.5667,\"angle\":12.86},{\"time\":1.0667,\"angle\":60.2}],\"translate\":[{\"time\":0.4,\"x\":918,\"y\":387},{\"time\":0.5667,\"x\":360,\"y\":387},{\"time\":0.7667,\"x\":737.9,\"y\":-259.34},{\"time\":1.0667,\"x\":1197.63,\"y\":-1089.94}],\"shear\":[{\"time\":0.4,\"x\":0,\"y\":0},{\"time\":0.7667,\"x\":-19.22,\"y\":0}]},\"Fire4\":{\"rotate\":[{\"time\":0.4,\"angle\":12.86,\"curve\":\"stepped\"},{\"time\":0.5,\"angle\":12.86},{\"time\":1.0667,\"angle\":138.04}],\"translate\":[{\"time\":0.4,\"x\":-576,\"y\":0,\"curve\":\"stepped\"},{\"time\":0.5,\"x\":-576,\"y\":0},{\"time\":1.0667,\"x\":-1459.93,\"y\":-1796.14}],\"shear\":[{\"time\":0.5,\"x\":0,\"y\":0},{\"time\":0.9667,\"x\":-30.91,\"y\":-64.34}]},\"Fire5\":{\"rotate\":[{\"time\":0.4,\"angle\":12.86},{\"time\":0.7667,\"angle\":-37.68},{\"time\":1.0667,\"angle\":-2.51}],\"translate\":[{\"time\":0.4,\"x\":-617.28,\"y\":-660.48},{\"time\":0.7667,\"x\":-1004.84,\"y\":-1821.04},{\"time\":1.0667,\"x\":-636.33,\"y\":-2373.88}],\"shear\":[{\"time\":0.4,\"x\":0,\"y\":0},{\"time\":0.7667,\"x\":-14.04,\"y\":-50.91}]},\"Fire2\":{\"rotate\":[{\"time\":0.4,\"angle\":34.4},{\"time\":1.0667,\"angle\":165.74}],\"translate\":[{\"time\":0.4,\"x\":-477,\"y\":855},{\"time\":1.0667,\"x\":-176.14,\"y\":-1957.78}],\"shear\":[{\"time\":0.5667,\"x\":0,\"y\":0},{\"time\":0.7667,\"x\":0,\"y\":12.44},{\"time\":0.9667,\"x\":0,\"y\":-17.81}]},\"Fire10\":{\"rotate\":[{\"time\":0.4,\"angle\":12.86},{\"time\":0.9,\"angle\":29.8},{\"time\":1.0667,\"angle\":19.54}],\"translate\":[{\"time\":0.4,\"x\":-617.28,\"y\":-660.48},{\"time\":0.4667,\"x\":-1724.03,\"y\":37.89},{\"time\":0.9,\"x\":-1550.71,\"y\":-1117.62},{\"time\":1.0667,\"x\":-1871.37,\"y\":-1426.88}],\"shear\":[{\"time\":0.4,\"x\":0,\"y\":0},{\"time\":0.9,\"x\":-30.91,\"y\":-64.34}]},\"Fire11\":{\"rotate\":[{\"time\":0.4,\"angle\":0},{\"time\":0.7667,\"angle\":-63.11},{\"time\":1.0667,\"angle\":-35.53}],\"translate\":[{\"time\":0.4,\"x\":0,\"y\":0},{\"time\":0.7667,\"x\":594.31,\"y\":93.98},{\"time\":1.0667,\"x\":565.25,\"y\":-457.01}]},\"Fire12\":{\"rotate\":[{\"time\":0.4,\"angle\":0},{\"time\":0.5,\"angle\":34.4},{\"time\":1.0667,\"angle\":164.06}],\"translate\":[{\"time\":0.4,\"x\":0,\"y\":0},{\"time\":0.5,\"x\":214.53,\"y\":-408.78},{\"time\":1.0667,\"x\":121.75,\"y\":-1990.05}],\"shear\":[{\"time\":0.5,\"x\":0,\"y\":0},{\"time\":0.7667,\"x\":0,\"y\":12.44},{\"time\":0.9667,\"x\":0,\"y\":-17.81}]},\"Fire16\":{\"rotate\":[{\"time\":0.4,\"angle\":12.86,\"curve\":\"stepped\"},{\"time\":0.5,\"angle\":12.86},{\"time\":1.0667,\"angle\":138.04}],\"translate\":[{\"time\":0.4,\"x\":-576,\"y\":0},{\"time\":0.5,\"x\":479.54,\"y\":-488.35},{\"time\":1.0667,\"x\":1137.85,\"y\":-2876.83}],\"shear\":[{\"time\":0.5,\"x\":0,\"y\":0},{\"time\":0.9667,\"x\":-30.91,\"y\":-64.34}]},\"Fire6\":{\"rotate\":[{\"time\":0.4,\"angle\":34.4},{\"time\":1.0667,\"angle\":165.74}],\"translate\":[{\"time\":0.4,\"x\":-477,\"y\":855},{\"time\":1.0667,\"x\":-176.14,\"y\":-1957.78}],\"shear\":[{\"time\":0.5667,\"x\":0,\"y\":0},{\"time\":0.7667,\"x\":0,\"y\":12.44},{\"time\":0.9667,\"x\":0,\"y\":-17.81}]},\"Fire17\":{\"rotate\":[{\"time\":0.4,\"angle\":12.86},{\"time\":0.8667,\"angle\":51.85},{\"time\":1.0667,\"angle\":-19.22}],\"translate\":[{\"time\":0.4,\"x\":-576,\"y\":0},{\"time\":0.8667,\"x\":-1179,\"y\":-1962},{\"time\":1.0667,\"x\":-1589.4,\"y\":-2682}],\"shear\":[{\"time\":0.4,\"x\":0,\"y\":0},{\"time\":0.8667,\"x\":-30.91,\"y\":-10.99}]},\"Fire18\":{\"rotate\":[{\"time\":0.4,\"angle\":12.86,\"curve\":\"stepped\"},{\"time\":0.5,\"angle\":12.86},{\"time\":1.0667,\"angle\":138.04}],\"translate\":[{\"time\":0.4,\"x\":-576,\"y\":0,\"curve\":\"stepped\"},{\"time\":0.5,\"x\":-576,\"y\":0},{\"time\":1.0667,\"x\":-1459.93,\"y\":-1796.14}],\"shear\":[{\"time\":0.5,\"x\":0,\"y\":0},{\"time\":0.9667,\"x\":-30.91,\"y\":-64.34}]},\"Fire19\":{\"rotate\":[{\"time\":0.4,\"angle\":12.86},{\"time\":0.7667,\"angle\":-37.68},{\"time\":1.0667,\"angle\":-2.51}],\"translate\":[{\"time\":0.4,\"x\":-617.28,\"y\":-660.48},{\"time\":0.7667,\"x\":-1004.84,\"y\":-1821.04},{\"time\":1.0667,\"x\":-636.33,\"y\":-2373.88}],\"shear\":[{\"time\":0.4,\"x\":0,\"y\":0},{\"time\":0.7667,\"x\":-14.04,\"y\":-50.91}]},\"Fire20\":{\"rotate\":[{\"time\":0.4,\"angle\":12.86},{\"time\":0.8667,\"angle\":116.51}],\"translate\":[{\"time\":0.4,\"x\":918,\"y\":387},{\"time\":0.8667,\"x\":1404,\"y\":-801},{\"time\":1.0667,\"x\":1707.43,\"y\":-1382.14}],\"shear\":[{\"time\":0.4,\"x\":0,\"y\":0},{\"time\":0.8667,\"x\":59.5,\"y\":42.75}]},\"Fire21\":{\"rotate\":[{\"time\":0.4,\"angle\":12.86,\"curve\":\"stepped\"},{\"time\":0.5667,\"angle\":12.86},{\"time\":1.0667,\"angle\":60.18}],\"translate\":[{\"time\":0.4,\"x\":918,\"y\":387,\"curve\":\"stepped\"},{\"time\":0.5667,\"x\":918,\"y\":387},{\"time\":1.0667,\"x\":127.82,\"y\":-576.02}],\"shear\":[{\"time\":0.5667,\"x\":0,\"y\":0},{\"time\":1.0667,\"x\":-30.38,\"y\":0}]},\"Fire22\":{\"rotate\":[{\"time\":0.4,\"angle\":12.86,\"curve\":\"stepped\"},{\"time\":0.5667,\"angle\":12.86},{\"time\":1.0667,\"angle\":60.2}],\"translate\":[{\"time\":0.4,\"x\":918,\"y\":387},{\"time\":0.5667,\"x\":360,\"y\":387},{\"time\":0.7667,\"x\":737.9,\"y\":-259.34},{\"time\":1.0667,\"x\":1197.63,\"y\":-1089.94}],\"shear\":[{\"time\":0.4,\"x\":0,\"y\":0},{\"time\":0.7667,\"x\":-19.22,\"y\":0}]},\"Fire23\":{\"rotate\":[{\"time\":0.4,\"angle\":12.86},{\"time\":0.9,\"angle\":29.8},{\"time\":1.0667,\"angle\":19.54}],\"translate\":[{\"time\":0.4,\"x\":-617.28,\"y\":-660.48},{\"time\":0.4667,\"x\":-1724.03,\"y\":37.89},{\"time\":0.9,\"x\":-1550.71,\"y\":-1117.62},{\"time\":1.0667,\"x\":-1871.37,\"y\":-1426.88}],\"shear\":[{\"time\":0.4,\"x\":0,\"y\":0},{\"time\":0.9,\"x\":-30.91,\"y\":-64.34}]},\"Fire24\":{\"rotate\":[{\"time\":0.4,\"angle\":0},{\"time\":0.7667,\"angle\":-63.11},{\"time\":1.0667,\"angle\":-35.53}],\"translate\":[{\"time\":0.4,\"x\":0,\"y\":0},{\"time\":0.7667,\"x\":594.31,\"y\":93.98},{\"time\":1.0667,\"x\":565.25,\"y\":-457.01}]},\"Fire25\":{\"rotate\":[{\"time\":0.4,\"angle\":0},{\"time\":0.5,\"angle\":34.4},{\"time\":1.0667,\"angle\":164.06}],\"translate\":[{\"time\":0.4,\"x\":0,\"y\":0},{\"time\":0.5,\"x\":214.53,\"y\":-408.78},{\"time\":1.0667,\"x\":121.75,\"y\":-1990.05}],\"shear\":[{\"time\":0.5,\"x\":0,\"y\":0},{\"time\":0.7667,\"x\":0,\"y\":12.44},{\"time\":0.9667,\"x\":0,\"y\":-17.81}]},\"Fire26\":{\"rotate\":[{\"time\":0.4,\"angle\":0},{\"time\":0.4667,\"angle\":12.86},{\"time\":0.5667,\"angle\":20.76},{\"time\":1.0667,\"angle\":-4.87}],\"translate\":[{\"time\":0.4,\"x\":0,\"y\":0},{\"time\":0.4667,\"x\":-576,\"y\":0},{\"time\":0.5667,\"x\":978.58,\"y\":245.38},{\"time\":1.0667,\"x\":639.3,\"y\":-1993.36}]},\"Fire27\":{\"rotate\":[{\"time\":0.4,\"angle\":0},{\"time\":0.5667,\"angle\":-63.11},{\"time\":0.6333,\"angle\":-95.98},{\"time\":1.0667,\"angle\":-141.27}],\"translate\":[{\"time\":0.4,\"x\":0,\"y\":0},{\"time\":0.5667,\"x\":-1529.69,\"y\":417.98},{\"time\":1.0667,\"x\":-1710.66,\"y\":-791.27}]},\"Fire28\":{\"rotate\":[{\"time\":0.4,\"angle\":12.86,\"curve\":\"stepped\"},{\"time\":0.5333,\"angle\":12.86},{\"time\":1.0667,\"angle\":60.18}],\"translate\":[{\"time\":0.4,\"x\":918,\"y\":387},{\"time\":0.5333,\"x\":1471.45,\"y\":-324.61},{\"time\":1.0667,\"x\":1929.08,\"y\":-1445.68}],\"scale\":[{\"time\":0.4,\"x\":1.382,\"y\":1.382}],\"shear\":[{\"time\":0.5333,\"x\":0,\"y\":0},{\"time\":1.0667,\"x\":-30.38,\"y\":0}]},\"Fire29\":{\"rotate\":[{\"time\":0.4,\"angle\":12.86,\"curve\":\"stepped\"},{\"time\":0.5,\"angle\":12.86},{\"time\":1.0667,\"angle\":138.04}],\"translate\":[{\"time\":0.4,\"x\":-576,\"y\":0},{\"time\":0.5,\"x\":479.54,\"y\":-488.35},{\"time\":1.0667,\"x\":1137.85,\"y\":-2876.83}],\"shear\":[{\"time\":0.5,\"x\":0,\"y\":0},{\"time\":0.9667,\"x\":-30.91,\"y\":-64.34}]},\"Fire44\":{\"rotate\":[{\"time\":0.4,\"angle\":34.4},{\"time\":1.0667,\"angle\":165.74}],\"translate\":[{\"time\":0.4,\"x\":-477,\"y\":855},{\"time\":1.0667,\"x\":-176.14,\"y\":-1957.78}],\"shear\":[{\"time\":0.5667,\"x\":0,\"y\":0},{\"time\":0.7667,\"x\":0,\"y\":12.44},{\"time\":0.9667,\"x\":0,\"y\":-17.81}]},\"Fire45\":{\"rotate\":[{\"time\":0.4,\"angle\":12.86},{\"time\":0.8667,\"angle\":51.85},{\"time\":1.0667,\"angle\":-19.22}],\"translate\":[{\"time\":0.4,\"x\":-576,\"y\":0},{\"time\":0.8667,\"x\":-1179,\"y\":-1962},{\"time\":1.0667,\"x\":-1589.4,\"y\":-2682}],\"shear\":[{\"time\":0.4,\"x\":0,\"y\":0},{\"time\":0.8667,\"x\":-30.91,\"y\":-10.99}]},\"Fire46\":{\"rotate\":[{\"time\":0.4,\"angle\":12.86,\"curve\":\"stepped\"},{\"time\":0.5,\"angle\":12.86},{\"time\":1.0667,\"angle\":138.04}],\"translate\":[{\"time\":0.4,\"x\":-576,\"y\":0,\"curve\":\"stepped\"},{\"time\":0.5,\"x\":-576,\"y\":0},{\"time\":1.0667,\"x\":-1459.93,\"y\":-1796.14}],\"shear\":[{\"time\":0.5,\"x\":0,\"y\":0},{\"time\":0.9667,\"x\":-30.91,\"y\":-64.34}]},\"Fire47\":{\"rotate\":[{\"time\":0.4,\"angle\":12.86},{\"time\":0.7667,\"angle\":-37.68},{\"time\":1.0667,\"angle\":-2.51}],\"translate\":[{\"time\":0.4,\"x\":-617.28,\"y\":-660.48},{\"time\":0.7667,\"x\":-1004.84,\"y\":-1821.04},{\"time\":1.0667,\"x\":-636.33,\"y\":-2373.88}],\"shear\":[{\"time\":0.4,\"x\":0,\"y\":0},{\"time\":0.7667,\"x\":-14.04,\"y\":-50.91}]},\"Fire48\":{\"rotate\":[{\"time\":0.4,\"angle\":12.86},{\"time\":0.8667,\"angle\":116.51}],\"translate\":[{\"time\":0.4,\"x\":918,\"y\":387},{\"time\":0.8667,\"x\":1404,\"y\":-801},{\"time\":1.0667,\"x\":1707.43,\"y\":-1382.14}],\"shear\":[{\"time\":0.4,\"x\":0,\"y\":0},{\"time\":0.8667,\"x\":59.5,\"y\":42.75}]},\"Fire49\":{\"rotate\":[{\"time\":0.4,\"angle\":12.86,\"curve\":\"stepped\"},{\"time\":0.5667,\"angle\":12.86},{\"time\":1.0667,\"angle\":60.18}],\"translate\":[{\"time\":0.4,\"x\":918,\"y\":387,\"curve\":\"stepped\"},{\"time\":0.5667,\"x\":918,\"y\":387},{\"time\":1.0667,\"x\":127.82,\"y\":-576.02}],\"shear\":[{\"time\":0.5667,\"x\":0,\"y\":0},{\"time\":1.0667,\"x\":-30.38,\"y\":0}]},\"Fire50\":{\"rotate\":[{\"time\":0.4,\"angle\":12.86,\"curve\":\"stepped\"},{\"time\":0.5667,\"angle\":12.86},{\"time\":1.0667,\"angle\":60.2}],\"translate\":[{\"time\":0.4,\"x\":918,\"y\":387},{\"time\":0.5667,\"x\":360,\"y\":387},{\"time\":0.7667,\"x\":737.9,\"y\":-259.34},{\"time\":1.0667,\"x\":1197.63,\"y\":-1089.94}],\"shear\":[{\"time\":0.4,\"x\":0,\"y\":0},{\"time\":0.7667,\"x\":-19.22,\"y\":0}]},\"Fire52\":{\"rotate\":[{\"time\":0.4,\"angle\":0},{\"time\":0.7667,\"angle\":-63.11},{\"time\":1.0667,\"angle\":-35.53}],\"translate\":[{\"time\":0.4,\"x\":0,\"y\":0},{\"time\":0.7667,\"x\":594.31,\"y\":93.98},{\"time\":1.0667,\"x\":565.25,\"y\":-457.01}]},\"Fire43\":{\"rotate\":[{\"time\":0.8667,\"angle\":12.86,\"curve\":\"stepped\"},{\"time\":0.9667,\"angle\":12.86},{\"time\":1.5333,\"angle\":138.04}],\"translate\":[{\"time\":0.8667,\"x\":-576,\"y\":0},{\"time\":0.9667,\"x\":479.54,\"y\":-488.35},{\"time\":1.5333,\"x\":1137.85,\"y\":-2876.83}],\"shear\":[{\"time\":0.9667,\"x\":0,\"y\":0},{\"time\":1.4333,\"x\":-30.91,\"y\":-64.34}]},\"Fire30\":{\"rotate\":[{\"time\":0.8667,\"angle\":34.4},{\"time\":1.5333,\"angle\":165.74}],\"translate\":[{\"time\":0.8667,\"x\":-477,\"y\":855},{\"time\":1.5333,\"x\":-176.14,\"y\":-1957.78}],\"shear\":[{\"time\":1.0333,\"x\":0,\"y\":0},{\"time\":1.2333,\"x\":0,\"y\":12.44},{\"time\":1.4333,\"x\":0,\"y\":-17.81}]},\"Fire31\":{\"rotate\":[{\"time\":0.8667,\"angle\":12.86},{\"time\":1.3333,\"angle\":51.85},{\"time\":1.5333,\"angle\":-19.22}],\"translate\":[{\"time\":0.8667,\"x\":-576,\"y\":0},{\"time\":1.3333,\"x\":-1179,\"y\":-1962},{\"time\":1.5333,\"x\":-1589.4,\"y\":-2682}],\"shear\":[{\"time\":0.8667,\"x\":0,\"y\":0},{\"time\":1.3333,\"x\":-30.91,\"y\":-10.99}]},\"Fire32\":{\"rotate\":[{\"time\":0.8667,\"angle\":12.86,\"curve\":\"stepped\"},{\"time\":0.9667,\"angle\":12.86},{\"time\":1.5333,\"angle\":138.04}],\"translate\":[{\"time\":0.8667,\"x\":-576,\"y\":0,\"curve\":\"stepped\"},{\"time\":0.9667,\"x\":-576,\"y\":0},{\"time\":1.5333,\"x\":-1459.93,\"y\":-1796.14}],\"shear\":[{\"time\":0.9667,\"x\":0,\"y\":0},{\"time\":1.4333,\"x\":-30.91,\"y\":-64.34}]},\"Fire33\":{\"rotate\":[{\"time\":0.8667,\"angle\":12.86},{\"time\":1.2333,\"angle\":-37.68},{\"time\":1.5333,\"angle\":-2.51}],\"translate\":[{\"time\":0.8667,\"x\":-617.28,\"y\":-660.48},{\"time\":1.2333,\"x\":-1004.84,\"y\":-1821.04},{\"time\":1.5333,\"x\":-636.33,\"y\":-2373.88}],\"shear\":[{\"time\":0.8667,\"x\":0,\"y\":0},{\"time\":1.2333,\"x\":-14.04,\"y\":-50.91}]},\"Fire34\":{\"rotate\":[{\"time\":0.8667,\"angle\":12.86},{\"time\":1.3333,\"angle\":116.51}],\"translate\":[{\"time\":0.8667,\"x\":918,\"y\":387},{\"time\":1.3333,\"x\":1404,\"y\":-801},{\"time\":1.5333,\"x\":1707.43,\"y\":-1382.14}],\"shear\":[{\"time\":0.8667,\"x\":0,\"y\":0},{\"time\":1.3333,\"x\":59.5,\"y\":42.75}]},\"Fire35\":{\"rotate\":[{\"time\":0.8667,\"angle\":12.86,\"curve\":\"stepped\"},{\"time\":1.0333,\"angle\":12.86},{\"time\":1.5333,\"angle\":60.18}],\"translate\":[{\"time\":0.8667,\"x\":918,\"y\":387,\"curve\":\"stepped\"},{\"time\":1.0333,\"x\":918,\"y\":387},{\"time\":1.5333,\"x\":127.82,\"y\":-576.02}],\"shear\":[{\"time\":1.0333,\"x\":0,\"y\":0},{\"time\":1.5333,\"x\":-30.38,\"y\":0}]},\"Fire36\":{\"rotate\":[{\"time\":0.8667,\"angle\":12.86,\"curve\":\"stepped\"},{\"time\":1.0333,\"angle\":12.86},{\"time\":1.5333,\"angle\":60.2}],\"translate\":[{\"time\":0.8667,\"x\":918,\"y\":387},{\"time\":1.0333,\"x\":360,\"y\":387},{\"time\":1.2333,\"x\":737.9,\"y\":-259.34},{\"time\":1.5333,\"x\":1197.63,\"y\":-1089.94}],\"shear\":[{\"time\":0.8667,\"x\":0,\"y\":0},{\"time\":1.2333,\"x\":-19.22,\"y\":0}]},\"Fire37\":{\"rotate\":[{\"time\":0.8667,\"angle\":12.86},{\"time\":1.3667,\"angle\":29.8},{\"time\":1.5333,\"angle\":19.54}],\"translate\":[{\"time\":0.8667,\"x\":-617.28,\"y\":-660.48},{\"time\":0.9333,\"x\":-1724.03,\"y\":37.89},{\"time\":1.3667,\"x\":-1550.71,\"y\":-1117.62},{\"time\":1.5333,\"x\":-1871.37,\"y\":-1426.88}],\"shear\":[{\"time\":0.8667,\"x\":0,\"y\":0},{\"time\":1.3667,\"x\":-30.91,\"y\":-64.34}]},\"Fire38\":{\"rotate\":[{\"time\":0.8667,\"angle\":0},{\"time\":1.2333,\"angle\":-63.11},{\"time\":1.5333,\"angle\":-35.53}],\"translate\":[{\"time\":0.8667,\"x\":0,\"y\":0},{\"time\":1.2333,\"x\":594.31,\"y\":93.98},{\"time\":1.5333,\"x\":565.25,\"y\":-457.01}]},\"Fire39\":{\"rotate\":[{\"time\":0.8667,\"angle\":0},{\"time\":0.9667,\"angle\":34.4},{\"time\":1.5333,\"angle\":164.06}],\"translate\":[{\"time\":0.8667,\"x\":0,\"y\":0},{\"time\":0.9667,\"x\":214.53,\"y\":-408.78},{\"time\":1.5333,\"x\":121.75,\"y\":-1990.05}],\"shear\":[{\"time\":0.9667,\"x\":0,\"y\":0},{\"time\":1.2333,\"x\":0,\"y\":12.44},{\"time\":1.4333,\"x\":0,\"y\":-17.81}]},\"Fire40\":{\"rotate\":[{\"time\":0.8667,\"angle\":0},{\"time\":0.9333,\"angle\":12.86},{\"time\":1.0333,\"angle\":20.76},{\"time\":1.5333,\"angle\":-4.87}],\"translate\":[{\"time\":0.8667,\"x\":0,\"y\":0},{\"time\":0.9333,\"x\":-576,\"y\":0},{\"time\":1.0333,\"x\":978.58,\"y\":245.38},{\"time\":1.5333,\"x\":639.3,\"y\":-1993.36}]},\"Fire41\":{\"rotate\":[{\"time\":0.8667,\"angle\":0},{\"time\":1.0333,\"angle\":-63.11},{\"time\":1.1,\"angle\":-95.98},{\"time\":1.5333,\"angle\":-141.27}],\"translate\":[{\"time\":0.8667,\"x\":0,\"y\":0},{\"time\":1.0333,\"x\":-1529.69,\"y\":417.98},{\"time\":1.5333,\"x\":-1710.66,\"y\":-791.27}]},\"Fire42\":{\"rotate\":[{\"time\":0.8667,\"angle\":12.86,\"curve\":\"stepped\"},{\"time\":1,\"angle\":12.86},{\"time\":1.5333,\"angle\":60.18}],\"translate\":[{\"time\":0.8667,\"x\":918,\"y\":387},{\"time\":1,\"x\":1471.45,\"y\":-324.61},{\"time\":1.5333,\"x\":1929.08,\"y\":-1445.68}],\"scale\":[{\"time\":0.8667,\"x\":1.382,\"y\":1.382}],\"shear\":[{\"time\":1,\"x\":0,\"y\":0},{\"time\":1.5333,\"x\":-30.38,\"y\":0}]}}},\"Lop trong\":{\"slots\":{\"attack2_02\":{\"color\":[{\"time\":0.7333,\"color\":\"ffffffff\"},{\"time\":1.2,\"color\":\"ffffff0d\"}],\"attachment\":[{\"time\":0,\"name\":null},{\"time\":0.5,\"name\":\"attack2_02\"},{\"time\":1.2667,\"name\":null}]}},\"bones\":{\"effect03\":{\"translate\":[{\"time\":0.5,\"x\":0,\"y\":0},{\"time\":0.7333,\"x\":0,\"y\":283.22},{\"time\":1.4,\"x\":0,\"y\":156.68}],\"scale\":[{\"time\":0,\"x\":5.791,\"y\":3.776,\"curve\":\"stepped\"},{\"time\":0.0667,\"x\":5.791,\"y\":3.776},{\"time\":0.5,\"x\":2.551,\"y\":2.551},{\"time\":1.2,\"x\":4,\"y\":4}]},\"bone3\":{\"translate\":[{\"time\":0,\"x\":100.09,\"y\":-28.1}],\"scale\":[{\"time\":0,\"x\":0.255,\"y\":0.255}]},\"bone\":{\"rotate\":[{\"time\":0,\"angle\":0},{\"time\":0.7667,\"angle\":180},{\"time\":1.5333,\"angle\":0}]}}}}}","_skeletonJson":{"skeleton":{"hash":"SN2G/Yig/pRl4AKRXB0e1rndcUI","spine":"3.7.94","width":1196.06,"height":1191.33,"images":"./images/","audio":"F:/GAMEBAI/DOING/THANQUAY2/EFFECT VICTORY/Thuycung"},"bones":[{"name":"root","y":6.05},{"name":"effect03","parent":"root","y":146.6,"scaleX":1.505,"scaleY":1.505},{"name":"bone3","parent":"root","length":142.22,"rotation":0.44,"x":-65.25,"y":580.9},{"name":"Fire2","parent":"bone3","rotation":-0.69,"x":290.18,"y":23.33,"scaleX":0.622,"scaleY":0.622,"color":"00f6ffff"},{"name":"Fire3","parent":"bone3","rotation":-0.69,"x":174.62,"y":22.75,"scaleX":0.501,"scaleY":0.501,"color":"00f6ffff"},{"name":"Fire4","parent":"bone3","rotation":-0.69,"x":115.7,"y":23.46,"scaleX":0.423,"scaleY":0.423,"color":"00f6ffff"},{"name":"Fire5","parent":"bone3","rotation":-0.69,"x":58.08,"y":24.15,"scaleX":0.761,"scaleY":0.761,"color":"00f6ffff"},{"name":"Fire7","parent":"bone3","rotation":-0.69,"x":-62.89,"y":25.6,"scaleX":0.465,"scaleY":0.465,"color":"00f6ffff"},{"name":"Fire8","parent":"bone3","rotation":-0.69,"x":-108.92,"y":26.15,"scaleX":0.289,"scaleY":0.289,"color":"00f6ffff"},{"name":"Fire9","parent":"bone3","rotation":-0.69,"x":-108.25,"y":81.94,"scaleX":0.609,"scaleY":0.609,"color":"00f6ffff"},{"name":"Fire10","parent":"bone3","rotation":-0.69,"x":231.29,"y":84.01,"scaleX":0.502,"scaleY":0.502,"color":"00f6ffff"},{"name":"Fire11","parent":"bone3","rotation":-0.69,"x":118.27,"y":84.19,"scaleX":0.67,"scaleY":0.67,"color":"00f6ffff"},{"name":"Fire12","parent":"bone3","rotation":-0.69,"x":-1.41,"y":78.91,"scaleX":0.352,"scaleY":0.352,"color":"00f6ffff"},{"name":"Fire13","parent":"bone3","rotation":-0.69,"x":173.55,"y":81.56,"scaleX":0.684,"scaleY":0.684,"color":"00f6ffff"},{"name":"Fire14","parent":"bone3","rotation":-0.69,"x":294.98,"y":86.4,"scaleX":0.44,"scaleY":0.44,"color":"00f6ffff"},{"name":"Fire15","parent":"bone3","rotation":-0.69,"x":-57.96,"y":81.21,"scaleX":0.289,"scaleY":0.289,"color":"00f6ffff"},{"name":"Fire16","parent":"bone3","rotation":-0.69,"x":57.8,"y":81.36,"scaleX":0.423,"scaleY":0.423,"color":"00f6ffff"},{"name":"Fire30","parent":"bone3","rotation":-0.69,"x":290.18,"y":23.33,"scaleX":0.622,"scaleY":0.622,"color":"00f6ffff"},{"name":"Fire31","parent":"bone3","rotation":-0.69,"x":174.62,"y":22.75,"scaleX":0.501,"scaleY":0.501,"color":"00f6ffff"},{"name":"Fire32","parent":"bone3","rotation":-0.69,"x":115.7,"y":23.46,"scaleX":0.423,"scaleY":0.423,"color":"00f6ffff"},{"name":"Fire33","parent":"bone3","rotation":-0.69,"x":58.08,"y":24.15,"scaleX":0.761,"scaleY":0.761,"color":"00f6ffff"},{"name":"Fire34","parent":"bone3","rotation":-0.69,"x":-62.89,"y":25.6,"scaleX":0.465,"scaleY":0.465,"color":"00f6ffff"},{"name":"Fire35","parent":"bone3","rotation":-0.69,"x":-108.92,"y":26.15,"scaleX":0.289,"scaleY":0.289,"color":"00f6ffff"},{"name":"Fire36","parent":"bone3","rotation":-0.69,"x":-108.25,"y":81.94,"scaleX":0.609,"scaleY":0.609,"color":"00f6ffff"},{"name":"Fire37","parent":"bone3","rotation":-0.69,"x":231.29,"y":84.01,"scaleX":0.502,"scaleY":0.502,"color":"00f6ffff"},{"name":"Fire38","parent":"bone3","rotation":-0.69,"x":118.27,"y":84.19,"scaleX":0.67,"scaleY":0.67,"color":"00f6ffff"},{"name":"Fire39","parent":"bone3","rotation":-0.69,"x":-1.41,"y":78.91,"scaleX":0.352,"scaleY":0.352,"color":"00f6ffff"},{"name":"Fire40","parent":"bone3","rotation":-0.69,"x":173.55,"y":81.56,"scaleX":0.684,"scaleY":0.684,"color":"00f6ffff"},{"name":"Fire41","parent":"bone3","rotation":-0.69,"x":294.98,"y":86.4,"scaleX":0.44,"scaleY":0.44,"color":"00f6ffff"},{"name":"Fire42","parent":"bone3","rotation":-0.69,"x":-57.96,"y":81.21,"scaleX":0.289,"scaleY":0.289,"color":"00f6ffff"},{"name":"Fire43","parent":"bone3","rotation":-0.69,"x":57.8,"y":81.36,"scaleX":0.423,"scaleY":0.423,"color":"00f6ffff"},{"name":"Fire6","parent":"bone3","rotation":-0.69,"x":290.18,"y":23.33,"scaleX":0.622,"scaleY":0.622,"color":"00f6ffff"},{"name":"Fire17","parent":"bone3","rotation":-0.69,"x":174.62,"y":22.75,"scaleX":0.501,"scaleY":0.501,"color":"00f6ffff"},{"name":"Fire18","parent":"bone3","rotation":-0.69,"x":115.7,"y":23.46,"scaleX":0.423,"scaleY":0.423,"color":"00f6ffff"},{"name":"Fire19","parent":"bone3","rotation":-0.69,"x":58.08,"y":24.15,"scaleX":0.761,"scaleY":0.761,"color":"00f6ffff"},{"name":"Fire20","parent":"bone3","rotation":-0.69,"x":-62.89,"y":25.6,"scaleX":0.465,"scaleY":0.465,"color":"00f6ffff"},{"name":"Fire21","parent":"bone3","rotation":-0.69,"x":-108.92,"y":26.15,"scaleX":0.289,"scaleY":0.289,"color":"00f6ffff"},{"name":"Fire22","parent":"bone3","rotation":-0.69,"x":-108.25,"y":81.94,"scaleX":0.609,"scaleY":0.609,"color":"00f6ffff"},{"name":"Fire23","parent":"bone3","rotation":-0.69,"x":231.29,"y":84.01,"scaleX":0.502,"scaleY":0.502,"color":"00f6ffff"},{"name":"Fire24","parent":"bone3","rotation":-0.69,"x":118.27,"y":84.19,"scaleX":0.67,"scaleY":0.67,"color":"00f6ffff"},{"name":"Fire25","parent":"bone3","rotation":-0.69,"x":-1.41,"y":78.91,"scaleX":0.352,"scaleY":0.352,"color":"00f6ffff"},{"name":"Fire26","parent":"bone3","rotation":-0.69,"x":173.55,"y":81.56,"scaleX":0.684,"scaleY":0.684,"color":"00f6ffff"},{"name":"Fire27","parent":"bone3","rotation":-0.69,"x":294.98,"y":86.4,"scaleX":0.44,"scaleY":0.44,"color":"00f6ffff"},{"name":"Fire28","parent":"bone3","rotation":-0.69,"x":-57.96,"y":81.21,"scaleX":0.289,"scaleY":0.289,"color":"00f6ffff"},{"name":"Fire29","parent":"bone3","rotation":-0.69,"x":57.8,"y":81.36,"scaleX":0.423,"scaleY":0.423,"color":"00f6ffff"},{"name":"Fire44","parent":"bone3","rotation":-0.69,"x":290.18,"y":23.33,"scaleX":0.622,"scaleY":0.622,"color":"00f6ffff"},{"name":"Fire45","parent":"bone3","rotation":-0.69,"x":174.62,"y":22.75,"scaleX":0.501,"scaleY":0.501,"color":"00f6ffff"},{"name":"Fire46","parent":"bone3","rotation":-0.69,"x":115.7,"y":23.46,"scaleX":0.423,"scaleY":0.423,"color":"00f6ffff"},{"name":"Fire47","parent":"bone3","rotation":-0.69,"x":58.08,"y":24.15,"scaleX":0.761,"scaleY":0.761,"color":"00f6ffff"},{"name":"Fire48","parent":"bone3","rotation":-0.69,"x":-62.89,"y":25.6,"scaleX":0.465,"scaleY":0.465,"color":"00f6ffff"},{"name":"Fire49","parent":"bone3","rotation":-0.69,"x":-108.92,"y":26.15,"scaleX":0.289,"scaleY":0.289,"color":"00f6ffff"},{"name":"Fire50","parent":"bone3","rotation":-0.69,"x":-108.25,"y":81.94,"scaleX":0.609,"scaleY":0.609,"color":"00f6ffff"},{"name":"Fire51","parent":"bone3","rotation":-0.69,"x":231.29,"y":84.01,"scaleX":0.502,"scaleY":0.502,"color":"00f6ffff"},{"name":"Fire52","parent":"bone3","rotation":-0.69,"x":118.27,"y":84.19,"scaleX":0.67,"scaleY":0.67,"color":"00f6ffff"},{"name":"bone","parent":"root","y":268.81,"scaleX":1.574,"scaleY":1.574}],"slots":[{"name":"Light","bone":"bone","attachment":"Light"},{"name":"attack2_02","bone":"effect03","attachment":"attack2_02","blend":"additive"},{"name":"Fire7","bone":"Fire7"},{"name":"Fire20","bone":"Fire20"},{"name":"Fire48","bone":"Fire48"},{"name":"Fire34","bone":"Fire34"},{"name":"Fire49","bone":"Fire49"},{"name":"Fire21","bone":"Fire21"},{"name":"Fire28","bone":"Fire28"},{"name":"Fire50","bone":"Fire50"},{"name":"Fire8","bone":"Fire8"},{"name":"Fire52","bone":"Fire52"},{"name":"Fire35","bone":"Fire35"},{"name":"Fire29","bone":"Fire29"},{"name":"Fire22","bone":"Fire22"},{"name":"Fire45","bone":"Fire45"},{"name":"Fire15","bone":"Fire15"},{"name":"Fire24","bone":"Fire24"},{"name":"Fire51","bone":"Fire51"},{"name":"Fire42","bone":"Fire42"},{"name":"Fire46","bone":"Fire46"},{"name":"Fire27","bone":"Fire27"},{"name":"Fire47","bone":"Fire47"},{"name":"Fire44","bone":"Fire44"},{"name":"Fire26","bone":"Fire26"},{"name":"Fire16","bone":"Fire16"},{"name":"Fire43","bone":"Fire43"},{"name":"Fire17","bone":"Fire17"},{"name":"Fire25","bone":"Fire25"},{"name":"Fire9","bone":"Fire9"},{"name":"Fire23","bone":"Fire23"},{"name":"Fire36","bone":"Fire36"},{"name":"Fire18","bone":"Fire18"},{"name":"Fire19","bone":"Fire19"},{"name":"Fire11","bone":"Fire11"},{"name":"Fire38","bone":"Fire38"},{"name":"Fire6","bone":"Fire6"},{"name":"Fire14","bone":"Fire14"},{"name":"Fire41","bone":"Fire41"},{"name":"Fire13","bone":"Fire13"},{"name":"Fire40","bone":"Fire40"},{"name":"Fire3","bone":"Fire3"},{"name":"Fire31","bone":"Fire31"},{"name":"Fire12","bone":"Fire12"},{"name":"Fire39","bone":"Fire39"},{"name":"Fire10","bone":"Fire10"},{"name":"Fire37","bone":"Fire37"},{"name":"Fire4","bone":"Fire4"},{"name":"Fire32","bone":"Fire32"},{"name":"Fire5","bone":"Fire5"},{"name":"Fire33","bone":"Fire33"},{"name":"Fire2","bone":"Fire2"},{"name":"Fire30","bone":"Fire30"}],"skins":{"default":{"Fire10":{"phaogiay1":{"x":-2.49,"y":-1.65,"width":600,"height":600},"phaogiay2":{"x":4.91,"y":-1.21,"width":600,"height":600},"phaogiay3":{"x":3.4,"y":1.85,"width":600,"height":600}},"Fire11":{"phaogiay1":{"x":-2.49,"y":-1.65,"width":600,"height":600},"phaogiay2":{"x":4.91,"y":-1.2,"width":600,"height":600},"phaogiay3":{"x":3.4,"y":1.85,"width":600,"height":600}},"Fire12":{"phaogiay1":{"x":-2.49,"y":-1.65,"width":600,"height":600},"phaogiay2":{"x":4.91,"y":-1.21,"width":600,"height":600},"phaogiay3":{"x":3.4,"y":1.85,"width":600,"height":600}},"Fire13":{"phaogiay1":{"x":-2.49,"y":-1.65,"width":600,"height":600},"phaogiay2":{"x":4.91,"y":-1.2,"width":600,"height":600},"phaogiay3":{"x":3.4,"y":1.85,"width":600,"height":600}},"Fire14":{"phaogiay1":{"x":-2.49,"y":-1.65,"width":600,"height":600},"phaogiay2":{"x":4.91,"y":-1.2,"width":600,"height":600},"phaogiay3":{"x":3.4,"y":1.85,"width":600,"height":600}},"Fire15":{"phaogiay1":{"x":-2.49,"y":-1.65,"width":600,"height":600},"phaogiay2":{"x":4.91,"y":-1.2,"width":600,"height":600},"phaogiay3":{"x":3.4,"y":1.85,"width":600,"height":600}},"Fire16":{"phaogiay1":{"x":-2.49,"y":-1.65,"width":600,"height":600},"phaogiay2":{"x":4.91,"y":-1.2,"width":600,"height":600},"phaogiay3":{"x":3.4,"y":1.85,"width":600,"height":600}},"Fire17":{"phaogiay1":{"x":-2.49,"y":-1.65,"width":600,"height":600},"phaogiay2":{"x":4.91,"y":-1.21,"width":600,"height":600},"phaogiay3":{"x":3.4,"y":1.85,"width":600,"height":600}},"Fire18":{"phaogiay1":{"x":-2.49,"y":-1.65,"width":600,"height":600},"phaogiay2":{"x":4.91,"y":-1.21,"width":600,"height":600},"phaogiay3":{"x":3.4,"y":1.85,"width":600,"height":600}},"Fire19":{"phaogiay1":{"x":-2.49,"y":-1.65,"width":600,"height":600},"phaogiay2":{"x":4.91,"y":-1.2,"width":600,"height":600},"phaogiay3":{"x":3.4,"y":1.85,"width":600,"height":600}},"Fire2":{"phaogiay1":{"x":-2.49,"y":-1.65,"width":600,"height":600},"phaogiay2":{"x":4.91,"y":-1.2,"width":600,"height":600},"phaogiay3":{"x":3.4,"y":1.85,"width":600,"height":600}},"Fire20":{"phaogiay1":{"x":-2.49,"y":-1.65,"width":600,"height":600},"phaogiay2":{"x":4.91,"y":-1.21,"width":600,"height":600},"phaogiay3":{"x":3.4,"y":1.85,"width":600,"height":600}},"Fire21":{"phaogiay1":{"x":-2.49,"y":-1.65,"width":600,"height":600},"phaogiay2":{"x":4.91,"y":-1.2,"width":600,"height":600},"phaogiay3":{"x":3.4,"y":1.85,"width":600,"height":600}},"Fire22":{"phaogiay1":{"x":-2.49,"y":-1.65,"width":600,"height":600},"phaogiay2":{"x":4.91,"y":-1.2,"width":600,"height":600},"phaogiay3":{"x":3.4,"y":1.85,"width":600,"height":600}},"Fire23":{"phaogiay1":{"x":-2.49,"y":-1.65,"width":600,"height":600},"phaogiay2":{"x":4.91,"y":-1.21,"width":600,"height":600},"phaogiay3":{"x":3.4,"y":1.85,"width":600,"height":600}},"Fire24":{"phaogiay1":{"x":-2.49,"y":-1.65,"width":600,"height":600},"phaogiay2":{"x":4.91,"y":-1.2,"width":600,"height":600},"phaogiay3":{"x":3.4,"y":1.85,"width":600,"height":600}},"Fire25":{"phaogiay1":{"x":-2.49,"y":-1.65,"width":600,"height":600},"phaogiay2":{"x":4.91,"y":-1.21,"width":600,"height":600},"phaogiay3":{"x":3.4,"y":1.85,"width":600,"height":600}},"Fire26":{"phaogiay1":{"x":-2.49,"y":-1.65,"width":600,"height":600},"phaogiay2":{"x":4.91,"y":-1.2,"width":600,"height":600},"phaogiay3":{"x":3.4,"y":1.85,"width":600,"height":600}},"Fire27":{"phaogiay1":{"x":-2.49,"y":-1.65,"width":600,"height":600},"phaogiay2":{"x":4.91,"y":-1.2,"width":600,"height":600},"phaogiay3":{"x":3.4,"y":1.85,"width":600,"height":600}},"Fire28":{"phaogiay1":{"x":-2.49,"y":-1.65,"width":600,"height":600},"phaogiay2":{"x":4.91,"y":-1.2,"width":600,"height":600},"phaogiay3":{"x":3.4,"y":1.85,"width":600,"height":600}},"Fire29":{"phaogiay1":{"x":-2.49,"y":-1.65,"width":600,"height":600},"phaogiay2":{"x":4.91,"y":-1.2,"width":600,"height":600},"phaogiay3":{"x":3.4,"y":1.85,"width":600,"height":600}},"Fire3":{"phaogiay1":{"x":-2.49,"y":-1.65,"width":600,"height":600},"phaogiay2":{"x":4.91,"y":-1.21,"width":600,"height":600},"phaogiay3":{"x":3.4,"y":1.85,"width":600,"height":600}},"Fire30":{"phaogiay1":{"x":-2.49,"y":-1.65,"width":600,"height":600},"phaogiay2":{"x":4.91,"y":-1.2,"width":600,"height":600},"phaogiay3":{"x":3.4,"y":1.85,"width":600,"height":600}},"Fire31":{"phaogiay1":{"x":-2.49,"y":-1.65,"width":600,"height":600},"phaogiay2":{"x":4.91,"y":-1.21,"width":600,"height":600},"phaogiay3":{"x":3.4,"y":1.85,"width":600,"height":600}},"Fire32":{"phaogiay1":{"x":-2.49,"y":-1.65,"width":600,"height":600},"phaogiay2":{"x":4.91,"y":-1.21,"width":600,"height":600},"phaogiay3":{"x":3.4,"y":1.85,"width":600,"height":600}},"Fire33":{"phaogiay1":{"x":-2.49,"y":-1.65,"width":600,"height":600},"phaogiay2":{"x":4.91,"y":-1.2,"width":600,"height":600},"phaogiay3":{"x":3.4,"y":1.85,"width":600,"height":600}},"Fire34":{"phaogiay1":{"x":-2.49,"y":-1.65,"width":600,"height":600},"phaogiay2":{"x":4.91,"y":-1.21,"width":600,"height":600},"phaogiay3":{"x":3.4,"y":1.85,"width":600,"height":600}},"Fire35":{"phaogiay1":{"x":-2.49,"y":-1.65,"width":600,"height":600},"phaogiay2":{"x":4.91,"y":-1.2,"width":600,"height":600},"phaogiay3":{"x":3.4,"y":1.85,"width":600,"height":600}},"Fire36":{"phaogiay1":{"x":-2.49,"y":-1.65,"width":600,"height":600},"phaogiay2":{"x":4.91,"y":-1.2,"width":600,"height":600},"phaogiay3":{"x":3.4,"y":1.85,"width":600,"height":600}},"Fire37":{"phaogiay1":{"x":-2.49,"y":-1.65,"width":600,"height":600},"phaogiay2":{"x":4.91,"y":-1.21,"width":600,"height":600},"phaogiay3":{"x":3.4,"y":1.85,"width":600,"height":600}},"Fire38":{"phaogiay1":{"x":-2.49,"y":-1.65,"width":600,"height":600},"phaogiay2":{"x":4.91,"y":-1.2,"width":600,"height":600},"phaogiay3":{"x":3.4,"y":1.85,"width":600,"height":600}},"Fire39":{"phaogiay1":{"x":-2.49,"y":-1.65,"width":600,"height":600},"phaogiay2":{"x":4.91,"y":-1.21,"width":600,"height":600},"phaogiay3":{"x":3.4,"y":1.85,"width":600,"height":600}},"Fire4":{"phaogiay1":{"x":-2.49,"y":-1.65,"width":600,"height":600},"phaogiay2":{"x":4.91,"y":-1.21,"width":600,"height":600},"phaogiay3":{"x":3.4,"y":1.85,"width":600,"height":600}},"Fire40":{"phaogiay1":{"x":-2.49,"y":-1.65,"width":600,"height":600},"phaogiay2":{"x":4.91,"y":-1.2,"width":600,"height":600},"phaogiay3":{"x":3.4,"y":1.85,"width":600,"height":600}},"Fire41":{"phaogiay1":{"x":-2.49,"y":-1.65,"width":600,"height":600},"phaogiay2":{"x":4.91,"y":-1.2,"width":600,"height":600},"phaogiay3":{"x":3.4,"y":1.85,"width":600,"height":600}},"Fire42":{"phaogiay1":{"x":-2.49,"y":-1.65,"width":600,"height":600},"phaogiay2":{"x":4.91,"y":-1.2,"width":600,"height":600},"phaogiay3":{"x":3.4,"y":1.85,"width":600,"height":600}},"Fire43":{"phaogiay1":{"x":-2.49,"y":-1.65,"width":600,"height":600},"phaogiay2":{"x":4.91,"y":-1.2,"width":600,"height":600},"phaogiay3":{"x":3.4,"y":1.85,"width":600,"height":600}},"Fire44":{"phaogiay1":{"x":-2.49,"y":-1.65,"width":600,"height":600},"phaogiay2":{"x":4.91,"y":-1.2,"width":600,"height":600},"phaogiay3":{"x":3.4,"y":1.85,"width":600,"height":600}},"Fire45":{"phaogiay1":{"x":-2.49,"y":-1.65,"width":600,"height":600},"phaogiay2":{"x":4.91,"y":-1.21,"width":600,"height":600},"phaogiay3":{"x":3.4,"y":1.85,"width":600,"height":600}},"Fire46":{"phaogiay1":{"x":-2.49,"y":-1.65,"width":600,"height":600},"phaogiay2":{"x":4.91,"y":-1.21,"width":600,"height":600},"phaogiay3":{"x":3.4,"y":1.85,"width":600,"height":600}},"Fire47":{"phaogiay1":{"x":-2.49,"y":-1.65,"width":600,"height":600},"phaogiay2":{"x":4.91,"y":-1.2,"width":600,"height":600},"phaogiay3":{"x":3.4,"y":1.85,"width":600,"height":600}},"Fire48":{"phaogiay1":{"x":-2.49,"y":-1.65,"width":600,"height":600},"phaogiay2":{"x":4.91,"y":-1.21,"width":600,"height":600},"phaogiay3":{"x":3.4,"y":1.85,"width":600,"height":600}},"Fire49":{"phaogiay1":{"x":-2.49,"y":-1.65,"width":600,"height":600},"phaogiay2":{"x":4.91,"y":-1.2,"width":600,"height":600},"phaogiay3":{"x":3.4,"y":1.85,"width":600,"height":600}},"Fire5":{"phaogiay1":{"x":-2.49,"y":-1.65,"width":600,"height":600},"phaogiay2":{"x":4.91,"y":-1.2,"width":600,"height":600},"phaogiay3":{"x":3.4,"y":1.85,"width":600,"height":600}},"Fire50":{"phaogiay1":{"x":-2.49,"y":-1.65,"width":600,"height":600},"phaogiay2":{"x":4.91,"y":-1.2,"width":600,"height":600},"phaogiay3":{"x":3.4,"y":1.85,"width":600,"height":600}},"Fire51":{"phaogiay1":{"x":-2.49,"y":-1.65,"width":600,"height":600},"phaogiay2":{"x":4.91,"y":-1.21,"width":600,"height":600},"phaogiay3":{"x":3.4,"y":1.85,"width":600,"height":600}},"Fire52":{"phaogiay1":{"x":-2.49,"y":-1.65,"width":600,"height":600},"phaogiay2":{"x":4.91,"y":-1.2,"width":600,"height":600},"phaogiay3":{"x":3.4,"y":1.85,"width":600,"height":600}},"Fire6":{"phaogiay1":{"x":-2.49,"y":-1.65,"width":600,"height":600},"phaogiay2":{"x":4.91,"y":-1.2,"width":600,"height":600},"phaogiay3":{"x":3.4,"y":1.85,"width":600,"height":600}},"Fire7":{"phaogiay1":{"x":-2.49,"y":-1.65,"width":600,"height":600},"phaogiay2":{"x":4.91,"y":-1.21,"width":600,"height":600},"phaogiay3":{"x":3.4,"y":1.85,"width":600,"height":600}},"Fire8":{"phaogiay1":{"x":-2.49,"y":-1.65,"width":600,"height":600},"phaogiay2":{"x":4.91,"y":-1.2,"width":600,"height":600},"phaogiay3":{"x":3.4,"y":1.85,"width":600,"height":600}},"Fire9":{"phaogiay1":{"x":-2.49,"y":-1.65,"width":600,"height":600},"phaogiay2":{"x":4.91,"y":-1.2,"width":600,"height":600},"phaogiay3":{"x":3.4,"y":1.85,"width":600,"height":600}},"Light":{"Light":{"width":760,"height":757}},"attack2_02":{"attack2_02":{"type":"mesh","uvs":[1,1,0,1,0,0,1,0],"triangles":[1,2,3,1,3,0],"vertices":[60,-60,-60,-60,-60,60,60,60],"hull":4,"edges":[0,2,2,4,4,6,0,6],"width":120,"height":120}}}},"animations":{"Lop ngoai":{"slots":{"Fire2":{"color":[{"time":0.4,"color":"ffffff00"},{"time":0.4333,"color":"ffffffff","curve":"stepped"},{"time":0.9667,"color":"ffffffff"},{"time":1.0667,"color":"ffffff00"}],"attachment":[{"time":0.6,"name":"phaogiay2"}]},"Fire3":{"color":[{"time":0.4,"color":"ffffff00"},{"time":0.4333,"color":"ffffffff","curve":"stepped"},{"time":0.9667,"color":"ffffffff"},{"time":1.0667,"color":"ffffff00"}],"attachment":[{"time":0.4,"name":"phaogiay1"}]},"Fire4":{"color":[{"time":0.4,"color":"ffffff00"},{"time":0.4333,"color":"ffffffff","curve":"stepped"},{"time":0.9667,"color":"ffffffff"},{"time":1.0667,"color":"ffffff00"}],"attachment":[{"time":0.5667,"name":"phaogiay1"}]},"Fire5":{"color":[{"time":0.4,"color":"ffffff00"},{"time":0.4333,"color":"ffffffff","curve":"stepped"},{"time":0.9667,"color":"ffffffff"},{"time":1.0667,"color":"ffffff00"}],"attachment":[{"time":0.4667,"name":"phaogiay3"}]},"Fire6":{"color":[{"time":0.4,"color":"ffffff00"},{"time":0.4333,"color":"ffffffff","curve":"stepped"},{"time":0.9667,"color":"ffffffff"},{"time":1.0667,"color":"ffffff00"}],"attachment":[{"time":0.6,"name":"phaogiay2"}]},"Fire7":{"color":[{"time":0.4,"color":"ffffff00"},{"time":0.4667,"color":"ffffffff"},{"time":1.0667,"color":"ffffff00"}],"attachment":[{"time":0.4667,"name":"phaogiay1"}]},"Fire8":{"color":[{"time":1.0667,"color":"ffffff00"}],"attachment":[{"time":0.6,"name":"phaogiay3"}]},"Fire9":{"color":[{"time":0.4,"color":"ffffff00"},{"time":0.4333,"color":"ffffffff","curve":"stepped"},{"time":0.9667,"color":"ffffffff"},{"time":1.0667,"color":"ffffff00"}],"attachment":[{"time":0.6333,"name":"phaogiay3"}]},"Fire10":{"color":[{"time":0.4,"color":"ffffff00"},{"time":0.4333,"color":"ffffffff","curve":"stepped"},{"time":0.9667,"color":"ffffffff"},{"time":1.0667,"color":"ffffff00"}],"attachment":[{"time":0.4667,"name":"phaogiay2"}]},"Fire11":{"color":[{"time":0.4,"color":"ffffff00"},{"time":0.4333,"color":"ffffffff","curve":"stepped"},{"time":0.9667,"color":"ffffffff"},{"time":1.0667,"color":"ffffff00"}],"attachment":[{"time":0.8333,"name":"phaogiay3"}]},"Fire12":{"color":[{"time":0.4,"color":"ffffff00"},{"time":0.4333,"color":"ffffffff","curve":"stepped"},{"time":0.9667,"color":"ffffffff"},{"time":1.0667,"color":"ffffff00"}],"attachment":[{"time":0.5333,"name":"phaogiay2"}]},"Fire13":{"color":[{"time":0.4,"color":"ffffff00"},{"time":0.4333,"color":"ffffffff","curve":"stepped"},{"time":0.9667,"color":"ffffffff"},{"time":1.0667,"color":"ffffff00"}],"attachment":[{"time":0.6333,"name":"phaogiay1"}]},"Fire14":{"color":[{"time":0.4,"color":"ffffff00"},{"time":0.4333,"color":"ffffffff","curve":"stepped"},{"time":0.9667,"color":"ffffffff"},{"time":1.0667,"color":"ffffff00"}],"attachment":[{"time":0.7,"name":"phaogiay1"}]},"Fire15":{"color":[{"time":0.4,"color":"ffffff00"},{"time":0.4333,"color":"ffffffff","curve":"stepped"},{"time":0.9667,"color":"ffffffff"},{"time":1.0667,"color":"ffffff00"}],"attachment":[{"time":0.5333,"name":"phaogiay2"},{"time":1.0667,"name":"phaogiay3"}]},"Fire16":{"color":[{"time":0.4,"color":"ffffff00"},{"time":0.4333,"color":"ffffffff","curve":"stepped"},{"time":0.9667,"color":"ffffffff"},{"time":1.0667,"color":"ffffff00"}],"attachment":[{"time":0.5667,"name":"phaogiay1"}]},"Fire17":{"color":[{"time":0.4,"color":"ffffff00"},{"time":0.4333,"color":"ffffffff","curve":"stepped"},{"time":0.9667,"color":"ffffffff"},{"time":1.0667,"color":"ffffff00"}],"attachment":[{"time":0.4,"name":"phaogiay1"}]},"Fire18":{"color":[{"time":0.4,"color":"ffffff00"},{"time":0.4333,"color":"ffffffff","curve":"stepped"},{"time":0.9667,"color":"ffffffff"},{"time":1.0667,"color":"ffffff00"}],"attachment":[{"time":0.5667,"name":"phaogiay1"}]},"Fire19":{"color":[{"time":0.4,"color":"ffffff00"},{"time":0.4333,"color":"ffffffff","curve":"stepped"},{"time":0.9667,"color":"ffffffff"},{"time":1.0667,"color":"ffffff00"}],"attachment":[{"time":0.4667,"name":"phaogiay3"}]},"Fire20":{"color":[{"time":0.4,"color":"ffffff00"},{"time":0.4667,"color":"ffffffff"},{"time":1.0667,"color":"ffffff00"}],"attachment":[{"time":0.4667,"name":"phaogiay1"}]},"Fire21":{"color":[{"time":1.0667,"color":"ffffff00"}],"attachment":[{"time":0.6,"name":"phaogiay3"}]},"Fire22":{"color":[{"time":0.4,"color":"ffffff00"},{"time":0.4333,"color":"ffffffff","curve":"stepped"},{"time":0.9667,"color":"ffffffff"},{"time":1.0667,"color":"ffffff00"}],"attachment":[{"time":0.6333,"name":"phaogiay3"}]},"Fire23":{"color":[{"time":0.4,"color":"ffffff00"},{"time":0.4333,"color":"ffffffff","curve":"stepped"},{"time":0.9667,"color":"ffffffff"},{"time":1.0667,"color":"ffffff00"}],"attachment":[{"time":0.4667,"name":"phaogiay2"}]},"Fire24":{"color":[{"time":0.4,"color":"ffffff00"},{"time":0.4333,"color":"ffffffff","curve":"stepped"},{"time":0.9667,"color":"ffffffff"},{"time":1.0667,"color":"ffffff00"}],"attachment":[{"time":0.8333,"name":"phaogiay3"}]},"Fire25":{"color":[{"time":0.4,"color":"ffffff00"},{"time":0.4333,"color":"ffffffff","curve":"stepped"},{"time":0.9667,"color":"ffffffff"},{"time":1.0667,"color":"ffffff00"}],"attachment":[{"time":0.5333,"name":"phaogiay2"}]},"Fire26":{"color":[{"time":0.4,"color":"ffffff00"},{"time":0.4333,"color":"ffffffff","curve":"stepped"},{"time":0.9667,"color":"ffffffff"},{"time":1.0667,"color":"ffffff00"}],"attachment":[{"time":0.6333,"name":"phaogiay1"}]},"Fire27":{"color":[{"time":0.4,"color":"ffffff00"},{"time":0.4333,"color":"ffffffff","curve":"stepped"},{"time":0.9667,"color":"ffffffff"},{"time":1.0667,"color":"ffffff00"}],"attachment":[{"time":0.7,"name":"phaogiay1"}]},"Fire28":{"color":[{"time":0.4,"color":"ffffff00"},{"time":0.4333,"color":"ffffffff","curve":"stepped"},{"time":0.9667,"color":"ffffffff"},{"time":1.0667,"color":"ffffff00"}],"attachment":[{"time":0.5333,"name":"phaogiay2"},{"time":1.0667,"name":"phaogiay3"}]},"Fire29":{"color":[{"time":0.4,"color":"ffffff00"},{"time":0.4333,"color":"ffffffff","curve":"stepped"},{"time":0.9667,"color":"ffffffff"},{"time":1.0667,"color":"ffffff00"}],"attachment":[{"time":0.5667,"name":"phaogiay1"}]},"Fire30":{"color":[{"time":0.8667,"color":"ffffff00"},{"time":0.9,"color":"ffffffff","curve":"stepped"},{"time":1.4333,"color":"ffffffff"},{"time":1.5333,"color":"ffffff00"}],"attachment":[{"time":1.0667,"name":"phaogiay2"}]},"Fire31":{"color":[{"time":0.8667,"color":"ffffff00"},{"time":0.9,"color":"ffffffff","curve":"stepped"},{"time":1.4333,"color":"ffffffff"},{"time":1.5333,"color":"ffffff00"}],"attachment":[{"time":0.8667,"name":"phaogiay1"}]},"Fire32":{"color":[{"time":0.8667,"color":"ffffff00"},{"time":0.9,"color":"ffffffff","curve":"stepped"},{"time":1.4333,"color":"ffffffff"},{"time":1.5333,"color":"ffffff00"}],"attachment":[{"time":1.0333,"name":"phaogiay1"}]},"Fire33":{"color":[{"time":0.8667,"color":"ffffff00"},{"time":0.9,"color":"ffffffff","curve":"stepped"},{"time":1.4333,"color":"ffffffff"},{"time":1.5333,"color":"ffffff00"}],"attachment":[{"time":0.9333,"name":"phaogiay3"}]},"Fire34":{"color":[{"time":0.8667,"color":"ffffff00"},{"time":0.9333,"color":"ffffffff"},{"time":1.5333,"color":"ffffff00"}],"attachment":[{"time":0.9333,"name":"phaogiay1"}]},"Fire35":{"color":[{"time":1.5333,"color":"ffffff00"}],"attachment":[{"time":1.0667,"name":"phaogiay3"}]},"Fire36":{"color":[{"time":0.8667,"color":"ffffff00"},{"time":0.9,"color":"ffffffff","curve":"stepped"},{"time":1.4333,"color":"ffffffff"},{"time":1.5333,"color":"ffffff00"}],"attachment":[{"time":1.1,"name":"phaogiay3"}]},"Fire37":{"color":[{"time":0.8667,"color":"ffffff00"},{"time":0.9,"color":"ffffffff","curve":"stepped"},{"time":1.4333,"color":"ffffffff"},{"time":1.5333,"color":"ffffff00"}],"attachment":[{"time":0.9333,"name":"phaogiay2"}]},"Fire38":{"color":[{"time":0.8667,"color":"ffffff00"},{"time":0.9,"color":"ffffffff","curve":"stepped"},{"time":1.4333,"color":"ffffffff"},{"time":1.5333,"color":"ffffff00"}],"attachment":[{"time":1.3,"name":"phaogiay3"}]},"Fire39":{"color":[{"time":0.8667,"color":"ffffff00"},{"time":0.9,"color":"ffffffff","curve":"stepped"},{"time":1.4333,"color":"ffffffff"},{"time":1.5333,"color":"ffffff00"}],"attachment":[{"time":1,"name":"phaogiay2"}]},"Fire40":{"color":[{"time":0.8667,"color":"ffffff00"},{"time":0.9,"color":"ffffffff","curve":"stepped"},{"time":1.4333,"color":"ffffffff"},{"time":1.5333,"color":"ffffff00"}],"attachment":[{"time":1.1,"name":"phaogiay1"}]},"Fire41":{"color":[{"time":0.8667,"color":"ffffff00"},{"time":0.9,"color":"ffffffff","curve":"stepped"},{"time":1.4333,"color":"ffffffff"},{"time":1.5333,"color":"ffffff00"}],"attachment":[{"time":1.1667,"name":"phaogiay1"}]},"Fire42":{"color":[{"time":0.8667,"color":"ffffff00"},{"time":0.9,"color":"ffffffff","curve":"stepped"},{"time":1.4333,"color":"ffffffff"},{"time":1.5333,"color":"ffffff00"}],"attachment":[{"time":1,"name":"phaogiay2"},{"time":1.5333,"name":"phaogiay3"}]},"Fire43":{"color":[{"time":0.8667,"color":"ffffff00"},{"time":0.9,"color":"ffffffff","curve":"stepped"},{"time":1.4333,"color":"ffffffff"},{"time":1.5333,"color":"ffffff00"}],"attachment":[{"time":1.0333,"name":"phaogiay1"}]},"Fire44":{"color":[{"time":0.4,"color":"ffffff00"},{"time":0.4333,"color":"ffffffff","curve":"stepped"},{"time":0.9667,"color":"ffffffff"},{"time":1.0667,"color":"ffffff00"}],"attachment":[{"time":0.6,"name":"phaogiay2"}]},"Fire45":{"color":[{"time":0.4,"color":"ffffff00"},{"time":0.4333,"color":"ffffffff","curve":"stepped"},{"time":0.9667,"color":"ffffffff"},{"time":1.0667,"color":"ffffff00"}],"attachment":[{"time":0.4,"name":"phaogiay1"}]},"Fire46":{"color":[{"time":0.4,"color":"ffffff00"},{"time":0.4333,"color":"ffffffff","curve":"stepped"},{"time":0.9667,"color":"ffffffff"},{"time":1.0667,"color":"ffffff00"}],"attachment":[{"time":0.5667,"name":"phaogiay1"}]},"Fire47":{"color":[{"time":0.4,"color":"ffffff00"},{"time":0.4333,"color":"ffffffff","curve":"stepped"},{"time":0.9667,"color":"ffffffff"},{"time":1.0667,"color":"ffffff00"}],"attachment":[{"time":0.4667,"name":"phaogiay3"}]},"Fire48":{"color":[{"time":0.4,"color":"ffffff00"},{"time":0.4667,"color":"ffffffff"},{"time":1.0667,"color":"ffffff00"}],"attachment":[{"time":0.4667,"name":"phaogiay1"}]},"Fire49":{"color":[{"time":1.0667,"color":"ffffff00"}],"attachment":[{"time":0.6,"name":"phaogiay3"}]},"Fire50":{"color":[{"time":0.4,"color":"ffffff00"},{"time":0.4333,"color":"ffffffff","curve":"stepped"},{"time":0.9667,"color":"ffffffff"},{"time":1.0667,"color":"ffffff00"}],"attachment":[{"time":0.6333,"name":"phaogiay3"}]},"Fire51":{"color":[{"time":0.4,"color":"ffffff00"},{"time":0.4333,"color":"ffffffff","curve":"stepped"},{"time":0.9667,"color":"ffffffff"},{"time":1.0667,"color":"ffffff00"}],"attachment":[{"time":0.4667,"name":"phaogiay2"}]},"Fire52":{"color":[{"time":0.4,"color":"ffffff00"},{"time":0.4333,"color":"ffffffff","curve":"stepped"},{"time":0.9667,"color":"ffffffff"},{"time":1.0667,"color":"ffffff00"}],"attachment":[{"time":0.8333,"name":"phaogiay3"}]},"Light":{"attachment":[{"time":0,"name":null}]},"attack2_02":{"attachment":[{"time":0,"name":null}]}},"bones":{"bone3":{"translate":[{"time":0,"x":100.09,"y":-28.1}],"scale":[{"time":0,"x":0.255,"y":0.255}]},"Fire51":{"rotate":[{"time":0.4,"angle":12.86},{"time":0.9,"angle":29.8},{"time":1.0667,"angle":19.54}],"translate":[{"time":0.4,"x":-617.28,"y":-660.48},{"time":0.4667,"x":-1724.03,"y":37.89},{"time":0.9,"x":-1550.71,"y":-1117.62},{"time":1.0667,"x":-1871.37,"y":-1426.88}],"shear":[{"time":0.4,"x":0,"y":0},{"time":0.9,"x":-30.91,"y":-64.34}]},"Fire7":{"rotate":[{"time":0.4,"angle":12.86},{"time":0.8667,"angle":116.51}],"translate":[{"time":0.4,"x":918,"y":387},{"time":0.8667,"x":1404,"y":-801},{"time":1.0667,"x":1707.43,"y":-1382.14}],"shear":[{"time":0.4,"x":0,"y":0},{"time":0.8667,"x":59.5,"y":42.75}]},"Fire13":{"rotate":[{"time":0.4,"angle":0},{"time":0.4667,"angle":12.86},{"time":0.5667,"angle":20.76},{"time":1.0667,"angle":-4.87}],"translate":[{"time":0.4,"x":0,"y":0},{"time":0.4667,"x":-576,"y":0},{"time":0.5667,"x":978.58,"y":245.38},{"time":1.0667,"x":639.3,"y":-1993.36}]},"Fire8":{"rotate":[{"time":0.4,"angle":12.86,"curve":"stepped"},{"time":0.5667,"angle":12.86},{"time":1.0667,"angle":60.18}],"translate":[{"time":0.4,"x":918,"y":387,"curve":"stepped"},{"time":0.5667,"x":918,"y":387},{"time":1.0667,"x":127.82,"y":-576.02}],"shear":[{"time":0.5667,"x":0,"y":0},{"time":1.0667,"x":-30.38,"y":0}]},"Fire14":{"rotate":[{"time":0.4,"angle":0},{"time":0.5667,"angle":-63.11},{"time":0.6333,"angle":-95.98},{"time":1.0667,"angle":-141.27}],"translate":[{"time":0.4,"x":0,"y":0},{"time":0.5667,"x":-1529.69,"y":417.98},{"time":1.0667,"x":-1710.66,"y":-791.27}]},"Fire15":{"rotate":[{"time":0.4,"angle":12.86,"curve":"stepped"},{"time":0.5333,"angle":12.86},{"time":1.0667,"angle":60.18}],"translate":[{"time":0.4,"x":918,"y":387},{"time":0.5333,"x":1471.45,"y":-324.61},{"time":1.0667,"x":1929.08,"y":-1445.68}],"scale":[{"time":0.4,"x":1.382,"y":1.382}],"shear":[{"time":0.5333,"x":0,"y":0},{"time":1.0667,"x":-30.38,"y":0}]},"Fire3":{"rotate":[{"time":0.4,"angle":12.86},{"time":0.8667,"angle":51.85},{"time":1.0667,"angle":-19.22}],"translate":[{"time":0.4,"x":-576,"y":0},{"time":0.8667,"x":-1179,"y":-1962},{"time":1.0667,"x":-1589.4,"y":-2682}],"shear":[{"time":0.4,"x":0,"y":0},{"time":0.8667,"x":-30.91,"y":-10.99}]},"Fire9":{"rotate":[{"time":0.4,"angle":12.86,"curve":"stepped"},{"time":0.5667,"angle":12.86},{"time":1.0667,"angle":60.2}],"translate":[{"time":0.4,"x":918,"y":387},{"time":0.5667,"x":360,"y":387},{"time":0.7667,"x":737.9,"y":-259.34},{"time":1.0667,"x":1197.63,"y":-1089.94}],"shear":[{"time":0.4,"x":0,"y":0},{"time":0.7667,"x":-19.22,"y":0}]},"Fire4":{"rotate":[{"time":0.4,"angle":12.86,"curve":"stepped"},{"time":0.5,"angle":12.86},{"time":1.0667,"angle":138.04}],"translate":[{"time":0.4,"x":-576,"y":0,"curve":"stepped"},{"time":0.5,"x":-576,"y":0},{"time":1.0667,"x":-1459.93,"y":-1796.14}],"shear":[{"time":0.5,"x":0,"y":0},{"time":0.9667,"x":-30.91,"y":-64.34}]},"Fire5":{"rotate":[{"time":0.4,"angle":12.86},{"time":0.7667,"angle":-37.68},{"time":1.0667,"angle":-2.51}],"translate":[{"time":0.4,"x":-617.28,"y":-660.48},{"time":0.7667,"x":-1004.84,"y":-1821.04},{"time":1.0667,"x":-636.33,"y":-2373.88}],"shear":[{"time":0.4,"x":0,"y":0},{"time":0.7667,"x":-14.04,"y":-50.91}]},"Fire2":{"rotate":[{"time":0.4,"angle":34.4},{"time":1.0667,"angle":165.74}],"translate":[{"time":0.4,"x":-477,"y":855},{"time":1.0667,"x":-176.14,"y":-1957.78}],"shear":[{"time":0.5667,"x":0,"y":0},{"time":0.7667,"x":0,"y":12.44},{"time":0.9667,"x":0,"y":-17.81}]},"Fire10":{"rotate":[{"time":0.4,"angle":12.86},{"time":0.9,"angle":29.8},{"time":1.0667,"angle":19.54}],"translate":[{"time":0.4,"x":-617.28,"y":-660.48},{"time":0.4667,"x":-1724.03,"y":37.89},{"time":0.9,"x":-1550.71,"y":-1117.62},{"time":1.0667,"x":-1871.37,"y":-1426.88}],"shear":[{"time":0.4,"x":0,"y":0},{"time":0.9,"x":-30.91,"y":-64.34}]},"Fire11":{"rotate":[{"time":0.4,"angle":0},{"time":0.7667,"angle":-63.11},{"time":1.0667,"angle":-35.53}],"translate":[{"time":0.4,"x":0,"y":0},{"time":0.7667,"x":594.31,"y":93.98},{"time":1.0667,"x":565.25,"y":-457.01}]},"Fire12":{"rotate":[{"time":0.4,"angle":0},{"time":0.5,"angle":34.4},{"time":1.0667,"angle":164.06}],"translate":[{"time":0.4,"x":0,"y":0},{"time":0.5,"x":214.53,"y":-408.78},{"time":1.0667,"x":121.75,"y":-1990.05}],"shear":[{"time":0.5,"x":0,"y":0},{"time":0.7667,"x":0,"y":12.44},{"time":0.9667,"x":0,"y":-17.81}]},"Fire16":{"rotate":[{"time":0.4,"angle":12.86,"curve":"stepped"},{"time":0.5,"angle":12.86},{"time":1.0667,"angle":138.04}],"translate":[{"time":0.4,"x":-576,"y":0},{"time":0.5,"x":479.54,"y":-488.35},{"time":1.0667,"x":1137.85,"y":-2876.83}],"shear":[{"time":0.5,"x":0,"y":0},{"time":0.9667,"x":-30.91,"y":-64.34}]},"Fire6":{"rotate":[{"time":0.4,"angle":34.4},{"time":1.0667,"angle":165.74}],"translate":[{"time":0.4,"x":-477,"y":855},{"time":1.0667,"x":-176.14,"y":-1957.78}],"shear":[{"time":0.5667,"x":0,"y":0},{"time":0.7667,"x":0,"y":12.44},{"time":0.9667,"x":0,"y":-17.81}]},"Fire17":{"rotate":[{"time":0.4,"angle":12.86},{"time":0.8667,"angle":51.85},{"time":1.0667,"angle":-19.22}],"translate":[{"time":0.4,"x":-576,"y":0},{"time":0.8667,"x":-1179,"y":-1962},{"time":1.0667,"x":-1589.4,"y":-2682}],"shear":[{"time":0.4,"x":0,"y":0},{"time":0.8667,"x":-30.91,"y":-10.99}]},"Fire18":{"rotate":[{"time":0.4,"angle":12.86,"curve":"stepped"},{"time":0.5,"angle":12.86},{"time":1.0667,"angle":138.04}],"translate":[{"time":0.4,"x":-576,"y":0,"curve":"stepped"},{"time":0.5,"x":-576,"y":0},{"time":1.0667,"x":-1459.93,"y":-1796.14}],"shear":[{"time":0.5,"x":0,"y":0},{"time":0.9667,"x":-30.91,"y":-64.34}]},"Fire19":{"rotate":[{"time":0.4,"angle":12.86},{"time":0.7667,"angle":-37.68},{"time":1.0667,"angle":-2.51}],"translate":[{"time":0.4,"x":-617.28,"y":-660.48},{"time":0.7667,"x":-1004.84,"y":-1821.04},{"time":1.0667,"x":-636.33,"y":-2373.88}],"shear":[{"time":0.4,"x":0,"y":0},{"time":0.7667,"x":-14.04,"y":-50.91}]},"Fire20":{"rotate":[{"time":0.4,"angle":12.86},{"time":0.8667,"angle":116.51}],"translate":[{"time":0.4,"x":918,"y":387},{"time":0.8667,"x":1404,"y":-801},{"time":1.0667,"x":1707.43,"y":-1382.14}],"shear":[{"time":0.4,"x":0,"y":0},{"time":0.8667,"x":59.5,"y":42.75}]},"Fire21":{"rotate":[{"time":0.4,"angle":12.86,"curve":"stepped"},{"time":0.5667,"angle":12.86},{"time":1.0667,"angle":60.18}],"translate":[{"time":0.4,"x":918,"y":387,"curve":"stepped"},{"time":0.5667,"x":918,"y":387},{"time":1.0667,"x":127.82,"y":-576.02}],"shear":[{"time":0.5667,"x":0,"y":0},{"time":1.0667,"x":-30.38,"y":0}]},"Fire22":{"rotate":[{"time":0.4,"angle":12.86,"curve":"stepped"},{"time":0.5667,"angle":12.86},{"time":1.0667,"angle":60.2}],"translate":[{"time":0.4,"x":918,"y":387},{"time":0.5667,"x":360,"y":387},{"time":0.7667,"x":737.9,"y":-259.34},{"time":1.0667,"x":1197.63,"y":-1089.94}],"shear":[{"time":0.4,"x":0,"y":0},{"time":0.7667,"x":-19.22,"y":0}]},"Fire23":{"rotate":[{"time":0.4,"angle":12.86},{"time":0.9,"angle":29.8},{"time":1.0667,"angle":19.54}],"translate":[{"time":0.4,"x":-617.28,"y":-660.48},{"time":0.4667,"x":-1724.03,"y":37.89},{"time":0.9,"x":-1550.71,"y":-1117.62},{"time":1.0667,"x":-1871.37,"y":-1426.88}],"shear":[{"time":0.4,"x":0,"y":0},{"time":0.9,"x":-30.91,"y":-64.34}]},"Fire24":{"rotate":[{"time":0.4,"angle":0},{"time":0.7667,"angle":-63.11},{"time":1.0667,"angle":-35.53}],"translate":[{"time":0.4,"x":0,"y":0},{"time":0.7667,"x":594.31,"y":93.98},{"time":1.0667,"x":565.25,"y":-457.01}]},"Fire25":{"rotate":[{"time":0.4,"angle":0},{"time":0.5,"angle":34.4},{"time":1.0667,"angle":164.06}],"translate":[{"time":0.4,"x":0,"y":0},{"time":0.5,"x":214.53,"y":-408.78},{"time":1.0667,"x":121.75,"y":-1990.05}],"shear":[{"time":0.5,"x":0,"y":0},{"time":0.7667,"x":0,"y":12.44},{"time":0.9667,"x":0,"y":-17.81}]},"Fire26":{"rotate":[{"time":0.4,"angle":0},{"time":0.4667,"angle":12.86},{"time":0.5667,"angle":20.76},{"time":1.0667,"angle":-4.87}],"translate":[{"time":0.4,"x":0,"y":0},{"time":0.4667,"x":-576,"y":0},{"time":0.5667,"x":978.58,"y":245.38},{"time":1.0667,"x":639.3,"y":-1993.36}]},"Fire27":{"rotate":[{"time":0.4,"angle":0},{"time":0.5667,"angle":-63.11},{"time":0.6333,"angle":-95.98},{"time":1.0667,"angle":-141.27}],"translate":[{"time":0.4,"x":0,"y":0},{"time":0.5667,"x":-1529.69,"y":417.98},{"time":1.0667,"x":-1710.66,"y":-791.27}]},"Fire28":{"rotate":[{"time":0.4,"angle":12.86,"curve":"stepped"},{"time":0.5333,"angle":12.86},{"time":1.0667,"angle":60.18}],"translate":[{"time":0.4,"x":918,"y":387},{"time":0.5333,"x":1471.45,"y":-324.61},{"time":1.0667,"x":1929.08,"y":-1445.68}],"scale":[{"time":0.4,"x":1.382,"y":1.382}],"shear":[{"time":0.5333,"x":0,"y":0},{"time":1.0667,"x":-30.38,"y":0}]},"Fire29":{"rotate":[{"time":0.4,"angle":12.86,"curve":"stepped"},{"time":0.5,"angle":12.86},{"time":1.0667,"angle":138.04}],"translate":[{"time":0.4,"x":-576,"y":0},{"time":0.5,"x":479.54,"y":-488.35},{"time":1.0667,"x":1137.85,"y":-2876.83}],"shear":[{"time":0.5,"x":0,"y":0},{"time":0.9667,"x":-30.91,"y":-64.34}]},"Fire44":{"rotate":[{"time":0.4,"angle":34.4},{"time":1.0667,"angle":165.74}],"translate":[{"time":0.4,"x":-477,"y":855},{"time":1.0667,"x":-176.14,"y":-1957.78}],"shear":[{"time":0.5667,"x":0,"y":0},{"time":0.7667,"x":0,"y":12.44},{"time":0.9667,"x":0,"y":-17.81}]},"Fire45":{"rotate":[{"time":0.4,"angle":12.86},{"time":0.8667,"angle":51.85},{"time":1.0667,"angle":-19.22}],"translate":[{"time":0.4,"x":-576,"y":0},{"time":0.8667,"x":-1179,"y":-1962},{"time":1.0667,"x":-1589.4,"y":-2682}],"shear":[{"time":0.4,"x":0,"y":0},{"time":0.8667,"x":-30.91,"y":-10.99}]},"Fire46":{"rotate":[{"time":0.4,"angle":12.86,"curve":"stepped"},{"time":0.5,"angle":12.86},{"time":1.0667,"angle":138.04}],"translate":[{"time":0.4,"x":-576,"y":0,"curve":"stepped"},{"time":0.5,"x":-576,"y":0},{"time":1.0667,"x":-1459.93,"y":-1796.14}],"shear":[{"time":0.5,"x":0,"y":0},{"time":0.9667,"x":-30.91,"y":-64.34}]},"Fire47":{"rotate":[{"time":0.4,"angle":12.86},{"time":0.7667,"angle":-37.68},{"time":1.0667,"angle":-2.51}],"translate":[{"time":0.4,"x":-617.28,"y":-660.48},{"time":0.7667,"x":-1004.84,"y":-1821.04},{"time":1.0667,"x":-636.33,"y":-2373.88}],"shear":[{"time":0.4,"x":0,"y":0},{"time":0.7667,"x":-14.04,"y":-50.91}]},"Fire48":{"rotate":[{"time":0.4,"angle":12.86},{"time":0.8667,"angle":116.51}],"translate":[{"time":0.4,"x":918,"y":387},{"time":0.8667,"x":1404,"y":-801},{"time":1.0667,"x":1707.43,"y":-1382.14}],"shear":[{"time":0.4,"x":0,"y":0},{"time":0.8667,"x":59.5,"y":42.75}]},"Fire49":{"rotate":[{"time":0.4,"angle":12.86,"curve":"stepped"},{"time":0.5667,"angle":12.86},{"time":1.0667,"angle":60.18}],"translate":[{"time":0.4,"x":918,"y":387,"curve":"stepped"},{"time":0.5667,"x":918,"y":387},{"time":1.0667,"x":127.82,"y":-576.02}],"shear":[{"time":0.5667,"x":0,"y":0},{"time":1.0667,"x":-30.38,"y":0}]},"Fire50":{"rotate":[{"time":0.4,"angle":12.86,"curve":"stepped"},{"time":0.5667,"angle":12.86},{"time":1.0667,"angle":60.2}],"translate":[{"time":0.4,"x":918,"y":387},{"time":0.5667,"x":360,"y":387},{"time":0.7667,"x":737.9,"y":-259.34},{"time":1.0667,"x":1197.63,"y":-1089.94}],"shear":[{"time":0.4,"x":0,"y":0},{"time":0.7667,"x":-19.22,"y":0}]},"Fire52":{"rotate":[{"time":0.4,"angle":0},{"time":0.7667,"angle":-63.11},{"time":1.0667,"angle":-35.53}],"translate":[{"time":0.4,"x":0,"y":0},{"time":0.7667,"x":594.31,"y":93.98},{"time":1.0667,"x":565.25,"y":-457.01}]},"Fire43":{"rotate":[{"time":0.8667,"angle":12.86,"curve":"stepped"},{"time":0.9667,"angle":12.86},{"time":1.5333,"angle":138.04}],"translate":[{"time":0.8667,"x":-576,"y":0},{"time":0.9667,"x":479.54,"y":-488.35},{"time":1.5333,"x":1137.85,"y":-2876.83}],"shear":[{"time":0.9667,"x":0,"y":0},{"time":1.4333,"x":-30.91,"y":-64.34}]},"Fire30":{"rotate":[{"time":0.8667,"angle":34.4},{"time":1.5333,"angle":165.74}],"translate":[{"time":0.8667,"x":-477,"y":855},{"time":1.5333,"x":-176.14,"y":-1957.78}],"shear":[{"time":1.0333,"x":0,"y":0},{"time":1.2333,"x":0,"y":12.44},{"time":1.4333,"x":0,"y":-17.81}]},"Fire31":{"rotate":[{"time":0.8667,"angle":12.86},{"time":1.3333,"angle":51.85},{"time":1.5333,"angle":-19.22}],"translate":[{"time":0.8667,"x":-576,"y":0},{"time":1.3333,"x":-1179,"y":-1962},{"time":1.5333,"x":-1589.4,"y":-2682}],"shear":[{"time":0.8667,"x":0,"y":0},{"time":1.3333,"x":-30.91,"y":-10.99}]},"Fire32":{"rotate":[{"time":0.8667,"angle":12.86,"curve":"stepped"},{"time":0.9667,"angle":12.86},{"time":1.5333,"angle":138.04}],"translate":[{"time":0.8667,"x":-576,"y":0,"curve":"stepped"},{"time":0.9667,"x":-576,"y":0},{"time":1.5333,"x":-1459.93,"y":-1796.14}],"shear":[{"time":0.9667,"x":0,"y":0},{"time":1.4333,"x":-30.91,"y":-64.34}]},"Fire33":{"rotate":[{"time":0.8667,"angle":12.86},{"time":1.2333,"angle":-37.68},{"time":1.5333,"angle":-2.51}],"translate":[{"time":0.8667,"x":-617.28,"y":-660.48},{"time":1.2333,"x":-1004.84,"y":-1821.04},{"time":1.5333,"x":-636.33,"y":-2373.88}],"shear":[{"time":0.8667,"x":0,"y":0},{"time":1.2333,"x":-14.04,"y":-50.91}]},"Fire34":{"rotate":[{"time":0.8667,"angle":12.86},{"time":1.3333,"angle":116.51}],"translate":[{"time":0.8667,"x":918,"y":387},{"time":1.3333,"x":1404,"y":-801},{"time":1.5333,"x":1707.43,"y":-1382.14}],"shear":[{"time":0.8667,"x":0,"y":0},{"time":1.3333,"x":59.5,"y":42.75}]},"Fire35":{"rotate":[{"time":0.8667,"angle":12.86,"curve":"stepped"},{"time":1.0333,"angle":12.86},{"time":1.5333,"angle":60.18}],"translate":[{"time":0.8667,"x":918,"y":387,"curve":"stepped"},{"time":1.0333,"x":918,"y":387},{"time":1.5333,"x":127.82,"y":-576.02}],"shear":[{"time":1.0333,"x":0,"y":0},{"time":1.5333,"x":-30.38,"y":0}]},"Fire36":{"rotate":[{"time":0.8667,"angle":12.86,"curve":"stepped"},{"time":1.0333,"angle":12.86},{"time":1.5333,"angle":60.2}],"translate":[{"time":0.8667,"x":918,"y":387},{"time":1.0333,"x":360,"y":387},{"time":1.2333,"x":737.9,"y":-259.34},{"time":1.5333,"x":1197.63,"y":-1089.94}],"shear":[{"time":0.8667,"x":0,"y":0},{"time":1.2333,"x":-19.22,"y":0}]},"Fire37":{"rotate":[{"time":0.8667,"angle":12.86},{"time":1.3667,"angle":29.8},{"time":1.5333,"angle":19.54}],"translate":[{"time":0.8667,"x":-617.28,"y":-660.48},{"time":0.9333,"x":-1724.03,"y":37.89},{"time":1.3667,"x":-1550.71,"y":-1117.62},{"time":1.5333,"x":-1871.37,"y":-1426.88}],"shear":[{"time":0.8667,"x":0,"y":0},{"time":1.3667,"x":-30.91,"y":-64.34}]},"Fire38":{"rotate":[{"time":0.8667,"angle":0},{"time":1.2333,"angle":-63.11},{"time":1.5333,"angle":-35.53}],"translate":[{"time":0.8667,"x":0,"y":0},{"time":1.2333,"x":594.31,"y":93.98},{"time":1.5333,"x":565.25,"y":-457.01}]},"Fire39":{"rotate":[{"time":0.8667,"angle":0},{"time":0.9667,"angle":34.4},{"time":1.5333,"angle":164.06}],"translate":[{"time":0.8667,"x":0,"y":0},{"time":0.9667,"x":214.53,"y":-408.78},{"time":1.5333,"x":121.75,"y":-1990.05}],"shear":[{"time":0.9667,"x":0,"y":0},{"time":1.2333,"x":0,"y":12.44},{"time":1.4333,"x":0,"y":-17.81}]},"Fire40":{"rotate":[{"time":0.8667,"angle":0},{"time":0.9333,"angle":12.86},{"time":1.0333,"angle":20.76},{"time":1.5333,"angle":-4.87}],"translate":[{"time":0.8667,"x":0,"y":0},{"time":0.9333,"x":-576,"y":0},{"time":1.0333,"x":978.58,"y":245.38},{"time":1.5333,"x":639.3,"y":-1993.36}]},"Fire41":{"rotate":[{"time":0.8667,"angle":0},{"time":1.0333,"angle":-63.11},{"time":1.1,"angle":-95.98},{"time":1.5333,"angle":-141.27}],"translate":[{"time":0.8667,"x":0,"y":0},{"time":1.0333,"x":-1529.69,"y":417.98},{"time":1.5333,"x":-1710.66,"y":-791.27}]},"Fire42":{"rotate":[{"time":0.8667,"angle":12.86,"curve":"stepped"},{"time":1,"angle":12.86},{"time":1.5333,"angle":60.18}],"translate":[{"time":0.8667,"x":918,"y":387},{"time":1,"x":1471.45,"y":-324.61},{"time":1.5333,"x":1929.08,"y":-1445.68}],"scale":[{"time":0.8667,"x":1.382,"y":1.382}],"shear":[{"time":1,"x":0,"y":0},{"time":1.5333,"x":-30.38,"y":0}]}}},"Lop trong":{"slots":{"attack2_02":{"color":[{"time":0.7333,"color":"ffffffff"},{"time":1.2,"color":"ffffff0d"}],"attachment":[{"time":0,"name":null},{"time":0.5,"name":"attack2_02"},{"time":1.2667,"name":null}]}},"bones":{"effect03":{"translate":[{"time":0.5,"x":0,"y":0},{"time":0.7333,"x":0,"y":283.22},{"time":1.4,"x":0,"y":156.68}],"scale":[{"time":0,"x":5.791,"y":3.776,"curve":"stepped"},{"time":0.0667,"x":5.791,"y":3.776},{"time":0.5,"x":2.551,"y":2.551},{"time":1.2,"x":4,"y":4}]},"bone3":{"translate":[{"time":0,"x":100.09,"y":-28.1}],"scale":[{"time":0,"x":0.255,"y":0.255}]},"bone":{"rotate":[{"time":0,"angle":0},{"time":0.7667,"angle":180},{"time":1.5333,"angle":0}]}}}}},"_atlasText":"\nEffect.png\nsize: 1366,1364\nformat: RGBA8888\nfilter: Linear,Linear\nrepeat: none\nLight\n  rotate: false\n  xy: 2, 605\n  size: 760, 757\n  orig: 760, 757\n  offset: 0, 0\n  index: -1\nattack2_02\n  rotate: false\n  xy: 764, 640\n  size: 120, 120\n  orig: 120, 120\n  offset: 0, 0\n  index: -1\nphaogiay1\n  rotate: false\n  xy: 2, 3\n  size: 600, 600\n  orig: 600, 600\n  offset: 0, 0\n  index: -1\nphaogiay2\n  rotate: false\n  xy: 764, 762\n  size: 600, 600\n  orig: 600, 600\n  offset: 0, 0\n  index: -1\nphaogiay3\n  rotate: false\n  xy: 604, 3\n  size: 600, 600\n  orig: 600, 600\n  offset: 0, 0\n  index: -1","textures":[{"__uuid__":"15VphYXBVBb7IPvIItgCnF"}],"textureNames":["Effect.png"]}