{"__type__":"sp.SkeletonData","_name":"item3","skeletonJsonStr":"{\n\"skeleton\": { \"hash\": \"gqh6K7huG3oagiyp8QiZ4tv1acA\", \"spine\": \"3.6.53\", \"width\": 308, \"height\": 303, \"images\": \"./images/\" },\n\"bones\": [\n\t{ \"name\": \"root\" },\n\t{ \"name\": \"explore_all\", \"parent\": \"root\" },\n\t{ \"name\": \"gach_ALL\", \"parent\": \"explore_all\", \"x\": 1.7, \"y\": -12.98 },\n\t{ \"name\": \"gach1\", \"parent\": \"gach_ALL\", \"x\": 32.27, \"y\": 24.45 },\n\t{ \"name\": \"UD\", \"parent\": \"gach1\" },\n\t{ \"name\": \"gach5\", \"parent\": \"gach_ALL\", \"x\": -31, \"y\": -7.91 },\n\t{ \"name\": \"UD2\", \"parent\": \"gach5\", \"x\": -5.28, \"y\": 17.61 },\n\t{ \"name\": \"gach12\", \"parent\": \"gach_ALL\", \"rotation\": -75.74, \"x\": -16.5, \"y\": 2.06 },\n\t{ \"name\": \"UD3\", \"parent\": \"gach12\", \"x\": -5.28, \"y\": 17.61 },\n\t{ \"name\": \"gach16\", \"parent\": \"gach_ALL\", \"rotation\": -68.7, \"x\": -32.96, \"y\": -0.92 },\n\t{ \"name\": \"UD4\", \"parent\": \"gach16\" },\n\t{ \"name\": \"gach2\", \"parent\": \"gach_ALL\", \"x\": -40.1, \"y\": 25.43 },\n\t{ \"name\": \"gach3\", \"parent\": \"gach_ALL\", \"x\": -6.36, \"y\": 42.05 },\n\t{ \"name\": \"gach4\", \"parent\": \"gach_ALL\", \"x\": 2.93, \"y\": 1.47 },\n\t{ \"name\": \"gach6\", \"parent\": \"gach_ALL\", \"rotation\": 166.22, \"x\": 5.09, \"y\": 30.23 },\n\t{ \"name\": \"gach7\", \"parent\": \"gach_ALL\", \"rotation\": -143.1, \"x\": 9.46, \"y\": 19.76 },\n\t{ \"name\": \"gach8\", \"parent\": \"gach_ALL\", \"rotation\": 158.71, \"x\": 34.68, \"y\": 33.34 },\n\t{ \"name\": \"gach9\", \"parent\": \"gach_ALL\", \"rotation\": 16.72, \"x\": -1.56, \"y\": 17.03 },\n\t{ \"name\": \"gach10\", \"parent\": \"gach_ALL\", \"rotation\": -23.66, \"x\": -31.31, \"y\": 43.32 },\n\t{ \"name\": \"gach11\", \"parent\": \"gach_ALL\", \"rotation\": -143.68, \"x\": 31.36, \"y\": 41.1 },\n\t{ \"name\": \"gach13\", \"parent\": \"gach_ALL\", \"rotation\": 149.95, \"x\": 29.21, \"y\": 12.34 },\n\t{ \"name\": \"gach14\", \"parent\": \"gach_ALL\", \"rotation\": 161.69, \"x\": -0.92, \"y\": -15.93 },\n\t{ \"name\": \"gach15\", \"parent\": \"gach_ALL\", \"rotation\": 53.25, \"x\": 26.95, \"y\": -9 },\n\t{ \"name\": \"gach17\", \"parent\": \"gach_ALL\", \"rotation\": -23.66, \"x\": -31.31, \"y\": 43.32 },\n\t{ \"name\": \"gach18\", \"parent\": \"gach_ALL\", \"rotation\": -143.68, \"x\": 31.36, \"y\": 41.1 },\n\t{ \"name\": \"gach19\", \"parent\": \"gach_ALL\", \"rotation\": 149.95, \"x\": 29.21, \"y\": 12.34 },\n\t{ \"name\": \"gach20\", \"parent\": \"gach_ALL\", \"x\": -40.1, \"y\": 25.43 },\n\t{ \"name\": \"khung4\", \"parent\": \"root\" },\n\t{ \"name\": \"item3\", \"parent\": \"khung4\", \"x\": -2.15, \"y\": 10.8 },\n\t{ \"name\": \"light_item5\", \"parent\": \"item3\", \"x\": -2.23, \"y\": 0.73, \"scaleX\": 1.3, \"scaleY\": 1.3 },\n\t{ \"name\": \"smokebom\", \"parent\": \"explore_all\", \"x\": 6.08, \"y\": -27, \"scaleX\": 1.5, \"scaleY\": 1.5 },\n\t{ \"name\": \"smokebom2\", \"parent\": \"explore_all\", \"x\": 6.08, \"y\": -27, \"scaleX\": 0.8, \"scaleY\": 0.8 },\n\t{ \"name\": \"smokebom3\", \"parent\": \"explore_all\", \"x\": 6.08, \"y\": -27, \"scaleX\": 0.7, \"scaleY\": 0.7 },\n\t{ \"name\": \"smokebom4\", \"parent\": \"explore_all\", \"x\": 6.08, \"y\": -27, \"scaleX\": 0.8, \"scaleY\": 0.8 }\n],\n\"slots\": [\n\t{ \"name\": \"khung4\", \"bone\": \"khung4\", \"attachment\": \"khung1\" },\n\t{ \"name\": \"item3\", \"bone\": \"item3\", \"attachment\": \"item3\" },\n\t{ \"name\": \"lightitem5\", \"bone\": \"light_item5\", \"attachment\": \"lightitem3\", \"blend\": \"additive\" },\n\t{\n\t\t\"name\": \"explore/special.0_0\",\n\t\t\"bone\": \"smokebom\",\n\t\t\"color\": \"ffffff00\",\n\t\t\"attachment\": \"explore/special.0_0\",\n\t\t\"blend\": \"additive\"\n\t},\n\t{\n\t\t\"name\": \"explore/special.0_1\",\n\t\t\"bone\": \"smokebom2\",\n\t\t\"color\": \"ffffff00\",\n\t\t\"attachment\": \"explore/special.0_0\",\n\t\t\"blend\": \"additive\"\n\t},\n\t{\n\t\t\"name\": \"explore/special.0_3\",\n\t\t\"bone\": \"smokebom4\",\n\t\t\"color\": \"ffffff00\",\n\t\t\"attachment\": \"explore/special.0_0\",\n\t\t\"blend\": \"additive\"\n\t},\n\t{\n\t\t\"name\": \"explore/special.0_2\",\n\t\t\"bone\": \"smokebom3\",\n\t\t\"color\": \"ffffff00\",\n\t\t\"attachment\": \"explore/special.0_0\",\n\t\t\"blend\": \"additive\"\n\t},\n\t{ \"name\": \"explore/gach1\", \"bone\": \"UD\", \"color\": \"ffffff00\", \"attachment\": \"explore/gach1\" },\n\t{ \"name\": \"explore/gach16\", \"bone\": \"UD4\", \"color\": \"ffffff00\", \"attachment\": \"explore/gach1\" },\n\t{ \"name\": \"explore/gach5\", \"bone\": \"UD2\", \"color\": \"ffffff00\", \"attachment\": \"explore/gach2\" },\n\t{ \"name\": \"explore/gach12\", \"bone\": \"UD3\", \"color\": \"ffffff00\", \"attachment\": \"explore/gach2\" },\n\t{ \"name\": \"explore/gach2\", \"bone\": \"gach2\", \"color\": \"ffffff00\", \"attachment\": \"explore/gach2\" },\n\t{ \"name\": \"explore/gach20\", \"bone\": \"gach20\", \"color\": \"ffffff00\", \"attachment\": \"explore/gach2\" },\n\t{ \"name\": \"explore/gach15\", \"bone\": \"gach15\", \"color\": \"ffffff00\", \"attachment\": \"explore/gach2\" },\n\t{ \"name\": \"explore/gach8\", \"bone\": \"gach8\", \"color\": \"ffffff00\", \"attachment\": \"explore/gach2\" },\n\t{ \"name\": \"explore/gach9\", \"bone\": \"gach9\", \"color\": \"ffffff00\", \"attachment\": \"explore/gach2\" },\n\t{ \"name\": \"explore/gach3\", \"bone\": \"gach3\", \"color\": \"ffffff00\", \"attachment\": \"explore/gach3\" },\n\t{ \"name\": \"explore/gach14\", \"bone\": \"gach14\", \"color\": \"ffffff00\", \"attachment\": \"explore/gach3\" },\n\t{ \"name\": \"explore/gach7\", \"bone\": \"gach7\", \"color\": \"ffffff00\", \"attachment\": \"explore/gach3\" },\n\t{ \"name\": \"explore/gach10\", \"bone\": \"gach10\", \"color\": \"ffffff00\", \"attachment\": \"explore/gach3\" },\n\t{ \"name\": \"explore/gach17\", \"bone\": \"gach17\", \"color\": \"ffffff00\", \"attachment\": \"explore/gach3\" },\n\t{ \"name\": \"explore/gach4\", \"bone\": \"gach4\", \"color\": \"ffffff00\", \"attachment\": \"explore/gach4\" },\n\t{ \"name\": \"explore/gach13\", \"bone\": \"gach13\", \"color\": \"ffffff00\", \"attachment\": \"explore/gach4\" },\n\t{ \"name\": \"explore/gach19\", \"bone\": \"gach19\", \"color\": \"ffffff00\", \"attachment\": \"explore/gach4\" },\n\t{ \"name\": \"explore/gach6\", \"bone\": \"gach6\", \"color\": \"ffffff00\", \"attachment\": \"explore/gach4\" },\n\t{ \"name\": \"explore/gach11\", \"bone\": \"gach11\", \"color\": \"ffffff00\", \"attachment\": \"explore/gach4\" },\n\t{ \"name\": \"explore/gach18\", \"bone\": \"gach18\", \"color\": \"ffffff00\", \"attachment\": \"explore/gach4\" }\n],\n\"skins\": {\n\t\"default\": {\n\t\t\"explore/gach1\": {\n\t\t\t\"explore/gach1\": { \"width\": 50, \"height\": 11 }\n\t\t},\n\t\t\"explore/gach10\": {\n\t\t\t\"explore/gach3\": { \"width\": 41, \"height\": 16 }\n\t\t},\n\t\t\"explore/gach11\": {\n\t\t\t\"explore/gach4\": { \"width\": 52, \"height\": 17 }\n\t\t},\n\t\t\"explore/gach12\": {\n\t\t\t\"explore/gach2\": { \"x\": 0.25, \"y\": 0.36, \"rotation\": -141.65, \"width\": 38, \"height\": 20 }\n\t\t},\n\t\t\"explore/gach13\": {\n\t\t\t\"explore/gach4\": { \"width\": 52, \"height\": 17 }\n\t\t},\n\t\t\"explore/gach14\": {\n\t\t\t\"explore/gach3\": { \"width\": 41, \"height\": 16 }\n\t\t},\n\t\t\"explore/gach15\": {\n\t\t\t\"explore/gach2\": { \"width\": 38, \"height\": 20 }\n\t\t},\n\t\t\"explore/gach16\": {\n\t\t\t\"explore/gach1\": { \"width\": 50, \"height\": 11 }\n\t\t},\n\t\t\"explore/gach17\": {\n\t\t\t\"explore/gach3\": { \"width\": 41, \"height\": 16 }\n\t\t},\n\t\t\"explore/gach18\": {\n\t\t\t\"explore/gach4\": { \"width\": 52, \"height\": 17 }\n\t\t},\n\t\t\"explore/gach19\": {\n\t\t\t\"explore/gach4\": { \"width\": 52, \"height\": 17 }\n\t\t},\n\t\t\"explore/gach2\": {\n\t\t\t\"explore/gach2\": { \"width\": 38, \"height\": 20 }\n\t\t},\n\t\t\"explore/gach20\": {\n\t\t\t\"explore/gach2\": { \"width\": 38, \"height\": 20 }\n\t\t},\n\t\t\"explore/gach3\": {\n\t\t\t\"explore/gach3\": { \"width\": 41, \"height\": 16 }\n\t\t},\n\t\t\"explore/gach4\": {\n\t\t\t\"explore/gach4\": { \"width\": 52, \"height\": 17 }\n\t\t},\n\t\t\"explore/gach5\": {\n\t\t\t\"explore/gach2\": { \"x\": 0.25, \"y\": 0.36, \"rotation\": -141.65, \"width\": 38, \"height\": 20 }\n\t\t},\n\t\t\"explore/gach6\": {\n\t\t\t\"explore/gach4\": { \"width\": 52, \"height\": 17 }\n\t\t},\n\t\t\"explore/gach7\": {\n\t\t\t\"explore/gach3\": { \"width\": 41, \"height\": 16 }\n\t\t},\n\t\t\"explore/gach8\": {\n\t\t\t\"explore/gach2\": { \"width\": 38, \"height\": 20 }\n\t\t},\n\t\t\"explore/gach9\": {\n\t\t\t\"explore/gach2\": { \"width\": 38, \"height\": 20 }\n\t\t},\n\t\t\"explore/special.0_0\": {\n\t\t\t\"explore/special.0_0\": { \"width\": 117, \"height\": 113 },\n\t\t\t\"explore/special.0_1\": { \"width\": 117, \"height\": 113 },\n\t\t\t\"explore/special.0_2\": { \"width\": 117, \"height\": 113 },\n\t\t\t\"explore/special.0_3\": { \"width\": 117, \"height\": 113 },\n\t\t\t\"explore/special.0_4\": { \"width\": 117, \"height\": 113 },\n\t\t\t\"explore/special.0_5\": { \"width\": 117, \"height\": 113 },\n\t\t\t\"explore/special.0_6\": { \"width\": 117, \"height\": 113 }\n\t\t},\n\t\t\"explore/special.0_1\": {\n\t\t\t\"explore/special.0_0\": { \"width\": 117, \"height\": 113 },\n\t\t\t\"explore/special.0_1\": { \"width\": 117, \"height\": 113 },\n\t\t\t\"explore/special.0_2\": { \"width\": 117, \"height\": 113 },\n\t\t\t\"explore/special.0_3\": { \"width\": 117, \"height\": 113 },\n\t\t\t\"explore/special.0_4\": { \"width\": 117, \"height\": 113 },\n\t\t\t\"explore/special.0_5\": { \"width\": 117, \"height\": 113 },\n\t\t\t\"explore/special.0_6\": { \"width\": 117, \"height\": 113 }\n\t\t},\n\t\t\"explore/special.0_2\": {\n\t\t\t\"explore/special.0_0\": { \"width\": 117, \"height\": 113 },\n\t\t\t\"explore/special.0_1\": { \"width\": 117, \"height\": 113 },\n\t\t\t\"explore/special.0_2\": { \"width\": 117, \"height\": 113 },\n\t\t\t\"explore/special.0_3\": { \"width\": 117, \"height\": 113 },\n\t\t\t\"explore/special.0_4\": { \"width\": 117, \"height\": 113 },\n\t\t\t\"explore/special.0_5\": { \"width\": 117, \"height\": 113 },\n\t\t\t\"explore/special.0_6\": { \"width\": 117, \"height\": 113 }\n\t\t},\n\t\t\"explore/special.0_3\": {\n\t\t\t\"explore/special.0_0\": { \"width\": 117, \"height\": 113 },\n\t\t\t\"explore/special.0_1\": { \"width\": 117, \"height\": 113 },\n\t\t\t\"explore/special.0_2\": { \"width\": 117, \"height\": 113 },\n\t\t\t\"explore/special.0_3\": { \"width\": 117, \"height\": 113 },\n\t\t\t\"explore/special.0_4\": { \"width\": 117, \"height\": 113 },\n\t\t\t\"explore/special.0_5\": { \"width\": 117, \"height\": 113 },\n\t\t\t\"explore/special.0_6\": { \"width\": 117, \"height\": 113 }\n\t\t},\n\t\t\"item3\": {\n\t\t\t\"item3\": { \"x\": -0.47, \"y\": -10.3, \"width\": 148, \"height\": 147 }\n\t\t},\n\t\t\"khung4\": {\n\t\t\t\"khung1\": { \"width\": 185, \"height\": 186 }\n\t\t},\n\t\t\"lightitem5\": {\n\t\t\t\"lightitem3\": { \"x\": 2.81, \"y\": -3.55, \"width\": 95, \"height\": 89 }\n\t\t}\n\t}\n},\n\"animations\": {\n\t\"anim_no\": {\n\t\t\"slots\": {\n\t\t\t\"explore/gach1\": {\n\t\t\t\t\"color\": [\n\t\t\t\t\t{ \"time\": 0, \"color\": \"ffffff00\", \"curve\": \"stepped\" },\n\t\t\t\t\t{ \"time\": 0.0667, \"color\": \"ffffffff\", \"curve\": \"stepped\" },\n\t\t\t\t\t{ \"time\": 0.3667, \"color\": \"ffffffff\" },\n\t\t\t\t\t{ \"time\": 0.5, \"color\": \"ffffff00\" }\n\t\t\t\t]\n\t\t\t},\n\t\t\t\"explore/gach2\": {\n\t\t\t\t\"color\": [\n\t\t\t\t\t{ \"time\": 0, \"color\": \"ffffff00\", \"curve\": \"stepped\" },\n\t\t\t\t\t{ \"time\": 0.0667, \"color\": \"ffffffff\", \"curve\": \"stepped\" },\n\t\t\t\t\t{ \"time\": 0.3667, \"color\": \"ffffffff\" },\n\t\t\t\t\t{ \"time\": 0.5, \"color\": \"ffffff00\" }\n\t\t\t\t]\n\t\t\t},\n\t\t\t\"explore/gach3\": {\n\t\t\t\t\"color\": [\n\t\t\t\t\t{ \"time\": 0, \"color\": \"ffffff00\", \"curve\": \"stepped\" },\n\t\t\t\t\t{ \"time\": 0.0667, \"color\": \"ffffffff\", \"curve\": \"stepped\" },\n\t\t\t\t\t{ \"time\": 0.3667, \"color\": \"ffffffff\" },\n\t\t\t\t\t{ \"time\": 0.5, \"color\": \"ffffff00\" }\n\t\t\t\t]\n\t\t\t},\n\t\t\t\"explore/gach4\": {\n\t\t\t\t\"color\": [\n\t\t\t\t\t{ \"time\": 0, \"color\": \"ffffff00\", \"curve\": \"stepped\" },\n\t\t\t\t\t{ \"time\": 0.0667, \"color\": \"ffffffff\", \"curve\": \"stepped\" },\n\t\t\t\t\t{ \"time\": 0.3667, \"color\": \"ffffffff\" },\n\t\t\t\t\t{ \"time\": 0.5, \"color\": \"ffffff00\" }\n\t\t\t\t]\n\t\t\t},\n\t\t\t\"explore/gach5\": {\n\t\t\t\t\"color\": [\n\t\t\t\t\t{ \"time\": 0, \"color\": \"ffffff00\", \"curve\": \"stepped\" },\n\t\t\t\t\t{ \"time\": 0.0667, \"color\": \"ffffffff\", \"curve\": \"stepped\" },\n\t\t\t\t\t{ \"time\": 0.3667, \"color\": \"ffffffff\" },\n\t\t\t\t\t{ \"time\": 0.5, \"color\": \"ffffff00\" }\n\t\t\t\t]\n\t\t\t},\n\t\t\t\"explore/gach6\": {\n\t\t\t\t\"color\": [\n\t\t\t\t\t{ \"time\": 0, \"color\": \"ffffff00\", \"curve\": \"stepped\" },\n\t\t\t\t\t{ \"time\": 0.0667, \"color\": \"ffffffff\", \"curve\": \"stepped\" },\n\t\t\t\t\t{ \"time\": 0.3667, \"color\": \"ffffffff\" },\n\t\t\t\t\t{ \"time\": 0.5, \"color\": \"ffffff00\" }\n\t\t\t\t]\n\t\t\t},\n\t\t\t\"explore/gach7\": {\n\t\t\t\t\"color\": [\n\t\t\t\t\t{ \"time\": 0, \"color\": \"ffffff00\", \"curve\": \"stepped\" },\n\t\t\t\t\t{ \"time\": 0.0667, \"color\": \"ffffffff\", \"curve\": \"stepped\" },\n\t\t\t\t\t{ \"time\": 0.3667, \"color\": \"ffffffff\" },\n\t\t\t\t\t{ \"time\": 0.5, \"color\": \"ffffff00\" }\n\t\t\t\t]\n\t\t\t},\n\t\t\t\"explore/gach8\": {\n\t\t\t\t\"color\": [\n\t\t\t\t\t{ \"time\": 0, \"color\": \"ffffff00\", \"curve\": \"stepped\" },\n\t\t\t\t\t{ \"time\": 0.0667, \"color\": \"ffffffff\", \"curve\": \"stepped\" },\n\t\t\t\t\t{ \"time\": 0.3667, \"color\": \"ffffffff\" },\n\t\t\t\t\t{ \"time\": 0.5, \"color\": \"ffffff00\" }\n\t\t\t\t]\n\t\t\t},\n\t\t\t\"explore/gach9\": {\n\t\t\t\t\"color\": [\n\t\t\t\t\t{ \"time\": 0, \"color\": \"ffffff00\", \"curve\": \"stepped\" },\n\t\t\t\t\t{ \"time\": 0.0667, \"color\": \"ffffffff\", \"curve\": \"stepped\" },\n\t\t\t\t\t{ \"time\": 0.3667, \"color\": \"ffffffff\" },\n\t\t\t\t\t{ \"time\": 0.5, \"color\": \"ffffff00\" }\n\t\t\t\t]\n\t\t\t},\n\t\t\t\"explore/gach10\": {\n\t\t\t\t\"color\": [\n\t\t\t\t\t{ \"time\": 0, \"color\": \"ffffff00\", \"curve\": \"stepped\" },\n\t\t\t\t\t{ \"time\": 0.0667, \"color\": \"ffffffff\", \"curve\": \"stepped\" },\n\t\t\t\t\t{ \"time\": 0.3667, \"color\": \"ffffffff\" },\n\t\t\t\t\t{ \"time\": 0.5, \"color\": \"ffffff00\" }\n\t\t\t\t]\n\t\t\t},\n\t\t\t\"explore/gach11\": {\n\t\t\t\t\"color\": [\n\t\t\t\t\t{ \"time\": 0, \"color\": \"ffffff00\", \"curve\": \"stepped\" },\n\t\t\t\t\t{ \"time\": 0.0667, \"color\": \"ffffffff\", \"curve\": \"stepped\" },\n\t\t\t\t\t{ \"time\": 0.3667, \"color\": \"ffffffff\" },\n\t\t\t\t\t{ \"time\": 0.5, \"color\": \"ffffff00\" }\n\t\t\t\t]\n\t\t\t},\n\t\t\t\"explore/gach12\": {\n\t\t\t\t\"color\": [\n\t\t\t\t\t{ \"time\": 0, \"color\": \"ffffff00\", \"curve\": \"stepped\" },\n\t\t\t\t\t{ \"time\": 0.0667, \"color\": \"ffffffff\", \"curve\": \"stepped\" },\n\t\t\t\t\t{ \"time\": 0.3667, \"color\": \"ffffffff\" },\n\t\t\t\t\t{ \"time\": 0.5, \"color\": \"ffffff00\" }\n\t\t\t\t]\n\t\t\t},\n\t\t\t\"explore/gach13\": {\n\t\t\t\t\"color\": [\n\t\t\t\t\t{ \"time\": 0, \"color\": \"ffffff00\", \"curve\": \"stepped\" },\n\t\t\t\t\t{ \"time\": 0.0667, \"color\": \"ffffffff\", \"curve\": \"stepped\" },\n\t\t\t\t\t{ \"time\": 0.3667, \"color\": \"ffffffff\" },\n\t\t\t\t\t{ \"time\": 0.5, \"color\": \"ffffff00\" }\n\t\t\t\t]\n\t\t\t},\n\t\t\t\"explore/gach14\": {\n\t\t\t\t\"color\": [\n\t\t\t\t\t{ \"time\": 0, \"color\": \"ffffff00\", \"curve\": \"stepped\" },\n\t\t\t\t\t{ \"time\": 0.0667, \"color\": \"ffffffff\", \"curve\": \"stepped\" },\n\t\t\t\t\t{ \"time\": 0.3667, \"color\": \"ffffffff\" },\n\t\t\t\t\t{ \"time\": 0.5, \"color\": \"ffffff00\" }\n\t\t\t\t]\n\t\t\t},\n\t\t\t\"explore/gach15\": {\n\t\t\t\t\"color\": [\n\t\t\t\t\t{ \"time\": 0, \"color\": \"ffffff00\", \"curve\": \"stepped\" },\n\t\t\t\t\t{ \"time\": 0.0667, \"color\": \"ffffffff\", \"curve\": \"stepped\" },\n\t\t\t\t\t{ \"time\": 0.3667, \"color\": \"ffffffff\" },\n\t\t\t\t\t{ \"time\": 0.5, \"color\": \"ffffff00\" }\n\t\t\t\t]\n\t\t\t},\n\t\t\t\"explore/gach16\": {\n\t\t\t\t\"color\": [\n\t\t\t\t\t{ \"time\": 0, \"color\": \"ffffff00\", \"curve\": \"stepped\" },\n\t\t\t\t\t{ \"time\": 0.0667, \"color\": \"ffffffff\", \"curve\": \"stepped\" },\n\t\t\t\t\t{ \"time\": 0.3667, \"color\": \"ffffffff\" },\n\t\t\t\t\t{ \"time\": 0.5, \"color\": \"ffffff00\" }\n\t\t\t\t]\n\t\t\t},\n\t\t\t\"explore/gach17\": {\n\t\t\t\t\"color\": [\n\t\t\t\t\t{ \"time\": 0, \"color\": \"ffffff00\", \"curve\": \"stepped\" },\n\t\t\t\t\t{ \"time\": 0.0667, \"color\": \"ffffffff\", \"curve\": \"stepped\" },\n\t\t\t\t\t{ \"time\": 0.3667, \"color\": \"ffffffff\" },\n\t\t\t\t\t{ \"time\": 0.5, \"color\": \"ffffff00\" }\n\t\t\t\t]\n\t\t\t},\n\t\t\t\"explore/gach18\": {\n\t\t\t\t\"color\": [\n\t\t\t\t\t{ \"time\": 0, \"color\": \"ffffff00\", \"curve\": \"stepped\" },\n\t\t\t\t\t{ \"time\": 0.0667, \"color\": \"ffffffff\", \"curve\": \"stepped\" },\n\t\t\t\t\t{ \"time\": 0.3667, \"color\": \"ffffffff\" },\n\t\t\t\t\t{ \"time\": 0.5, \"color\": \"ffffff00\" }\n\t\t\t\t]\n\t\t\t},\n\t\t\t\"explore/gach19\": {\n\t\t\t\t\"color\": [\n\t\t\t\t\t{ \"time\": 0, \"color\": \"ffffff00\", \"curve\": \"stepped\" },\n\t\t\t\t\t{ \"time\": 0.0667, \"color\": \"ffffffff\", \"curve\": \"stepped\" },\n\t\t\t\t\t{ \"time\": 0.3667, \"color\": \"ffffffff\" },\n\t\t\t\t\t{ \"time\": 0.5, \"color\": \"ffffff00\" }\n\t\t\t\t]\n\t\t\t},\n\t\t\t\"explore/gach20\": {\n\t\t\t\t\"color\": [\n\t\t\t\t\t{ \"time\": 0, \"color\": \"ffffff00\", \"curve\": \"stepped\" },\n\t\t\t\t\t{ \"time\": 0.0667, \"color\": \"ffffffff\", \"curve\": \"stepped\" },\n\t\t\t\t\t{ \"time\": 0.3667, \"color\": \"ffffffff\" },\n\t\t\t\t\t{ \"time\": 0.5, \"color\": \"ffffff00\" }\n\t\t\t\t]\n\t\t\t},\n\t\t\t\"explore/special.0_0\": {\n\t\t\t\t\"color\": [\n\t\t\t\t\t{ \"time\": 0, \"color\": \"ffffff00\" },\n\t\t\t\t\t{ \"time\": 0.1, \"color\": \"ffffffff\", \"curve\": \"stepped\" },\n\t\t\t\t\t{ \"time\": 0.4333, \"color\": \"ffffffff\" },\n\t\t\t\t\t{ \"time\": 0.5667, \"color\": \"ffffff00\" }\n\t\t\t\t],\n\t\t\t\t\"attachment\": [\n\t\t\t\t\t{ \"time\": 0.0667, \"name\": \"explore/special.0_0\" },\n\t\t\t\t\t{ \"time\": 0.1333, \"name\": \"explore/special.0_1\" },\n\t\t\t\t\t{ \"time\": 0.2, \"name\": \"explore/special.0_2\" },\n\t\t\t\t\t{ \"time\": 0.2667, \"name\": \"explore/special.0_3\" },\n\t\t\t\t\t{ \"time\": 0.3333, \"name\": \"explore/special.0_4\" },\n\t\t\t\t\t{ \"time\": 0.4, \"name\": \"explore/special.0_5\" },\n\t\t\t\t\t{ \"time\": 0.4667, \"name\": \"explore/special.0_6\" },\n\t\t\t\t\t{ \"time\": 0.5333, \"name\": null }\n\t\t\t\t]\n\t\t\t},\n\t\t\t\"explore/special.0_1\": {\n\t\t\t\t\"color\": [\n\t\t\t\t\t{ \"time\": 0, \"color\": \"ffffff00\", \"curve\": \"stepped\" },\n\t\t\t\t\t{ \"time\": 0.0667, \"color\": \"ffffff00\" },\n\t\t\t\t\t{ \"time\": 0.1667, \"color\": \"ffffffff\", \"curve\": \"stepped\" },\n\t\t\t\t\t{ \"time\": 0.5, \"color\": \"ffffffff\" },\n\t\t\t\t\t{ \"time\": 0.6333, \"color\": \"ffffff00\" }\n\t\t\t\t],\n\t\t\t\t\"attachment\": [\n\t\t\t\t\t{ \"time\": 0.1333, \"name\": \"explore/special.0_0\" },\n\t\t\t\t\t{ \"time\": 0.2, \"name\": \"explore/special.0_1\" },\n\t\t\t\t\t{ \"time\": 0.2667, \"name\": \"explore/special.0_2\" },\n\t\t\t\t\t{ \"time\": 0.3333, \"name\": \"explore/special.0_3\" },\n\t\t\t\t\t{ \"time\": 0.4, \"name\": \"explore/special.0_4\" },\n\t\t\t\t\t{ \"time\": 0.4667, \"name\": \"explore/special.0_5\" },\n\t\t\t\t\t{ \"time\": 0.5333, \"name\": \"explore/special.0_6\" },\n\t\t\t\t\t{ \"time\": 0.6, \"name\": null }\n\t\t\t\t]\n\t\t\t},\n\t\t\t\"explore/special.0_2\": {\n\t\t\t\t\"color\": [\n\t\t\t\t\t{ \"time\": 0, \"color\": \"ffffff00\", \"curve\": \"stepped\" },\n\t\t\t\t\t{ \"time\": 0.0333, \"color\": \"ffffff00\" },\n\t\t\t\t\t{ \"time\": 0.1333, \"color\": \"ffffffff\", \"curve\": \"stepped\" },\n\t\t\t\t\t{ \"time\": 0.4667, \"color\": \"ffffffff\" },\n\t\t\t\t\t{ \"time\": 0.6, \"color\": \"ffffff00\" }\n\t\t\t\t],\n\t\t\t\t\"attachment\": [\n\t\t\t\t\t{ \"time\": 0.1, \"name\": \"explore/special.0_0\" },\n\t\t\t\t\t{ \"time\": 0.1667, \"name\": \"explore/special.0_1\" },\n\t\t\t\t\t{ \"time\": 0.2333, \"name\": \"explore/special.0_2\" },\n\t\t\t\t\t{ \"time\": 0.3, \"name\": \"explore/special.0_3\" },\n\t\t\t\t\t{ \"time\": 0.3667, \"name\": \"explore/special.0_4\" },\n\t\t\t\t\t{ \"time\": 0.4333, \"name\": \"explore/special.0_5\" },\n\t\t\t\t\t{ \"time\": 0.5, \"name\": \"explore/special.0_6\" },\n\t\t\t\t\t{ \"time\": 0.5667, \"name\": null }\n\t\t\t\t]\n\t\t\t},\n\t\t\t\"explore/special.0_3\": {\n\t\t\t\t\"color\": [\n\t\t\t\t\t{ \"time\": 0, \"color\": \"ffffff00\", \"curve\": \"stepped\" },\n\t\t\t\t\t{ \"time\": 0.1, \"color\": \"ffffff00\" },\n\t\t\t\t\t{ \"time\": 0.2, \"color\": \"ffffffff\", \"curve\": \"stepped\" },\n\t\t\t\t\t{ \"time\": 0.5333, \"color\": \"ffffffff\" },\n\t\t\t\t\t{ \"time\": 0.6667, \"color\": \"ffffff00\" }\n\t\t\t\t],\n\t\t\t\t\"attachment\": [\n\t\t\t\t\t{ \"time\": 0.1667, \"name\": \"explore/special.0_0\" },\n\t\t\t\t\t{ \"time\": 0.2333, \"name\": \"explore/special.0_1\" },\n\t\t\t\t\t{ \"time\": 0.3, \"name\": \"explore/special.0_2\" },\n\t\t\t\t\t{ \"time\": 0.3667, \"name\": \"explore/special.0_3\" },\n\t\t\t\t\t{ \"time\": 0.4333, \"name\": \"explore/special.0_4\" },\n\t\t\t\t\t{ \"time\": 0.5, \"name\": \"explore/special.0_5\" },\n\t\t\t\t\t{ \"time\": 0.5667, \"name\": \"explore/special.0_6\" },\n\t\t\t\t\t{ \"time\": 0.6333, \"name\": null }\n\t\t\t\t]\n\t\t\t},\n\t\t\t\"item3\": {\n\t\t\t\t\"color\": [\n\t\t\t\t\t{ \"time\": 0, \"color\": \"ffffff00\" }\n\t\t\t\t]\n\t\t\t},\n\t\t\t\"khung4\": {\n\t\t\t\t\"color\": [\n\t\t\t\t\t{ \"time\": 0, \"color\": \"ffffff00\" }\n\t\t\t\t]\n\t\t\t},\n\t\t\t\"lightitem5\": {\n\t\t\t\t\"color\": [\n\t\t\t\t\t{ \"time\": 0, \"color\": \"ffffff00\" }\n\t\t\t\t]\n\t\t\t}\n\t\t},\n\t\t\"bones\": {\n\t\t\t\"item3\": {\n\t\t\t\t\"scale\": [\n\t\t\t\t\t{ \"time\": 0, \"x\": 0.969, \"y\": 0.969 }\n\t\t\t\t]\n\t\t\t},\n\t\t\t\"gach3\": {\n\t\t\t\t\"rotate\": [\n\t\t\t\t\t{ \"time\": 0, \"angle\": 0, \"curve\": \"stepped\" },\n\t\t\t\t\t{ \"time\": 0.0667, \"angle\": 0 },\n\t\t\t\t\t{ \"time\": 0.2333, \"angle\": 33.98 },\n\t\t\t\t\t{ \"time\": 0.4333, \"angle\": 161.39 }\n\t\t\t\t],\n\t\t\t\t\"translate\": [\n\t\t\t\t\t{ \"time\": 0, \"x\": 1.91, \"y\": -2.55, \"curve\": \"stepped\" },\n\t\t\t\t\t{ \"time\": 0.0667, \"x\": 1.91, \"y\": -2.55 },\n\t\t\t\t\t{ \"time\": 0.4333, \"x\": -36.11, \"y\": -117.14 }\n\t\t\t\t],\n\t\t\t\t\"scale\": [\n\t\t\t\t\t{ \"time\": 0, \"x\": 1, \"y\": 1, \"curve\": \"stepped\" },\n\t\t\t\t\t{ \"time\": 0.0667, \"x\": 1, \"y\": 1 }\n\t\t\t\t]\n\t\t\t},\n\t\t\t\"gach2\": {\n\t\t\t\t\"rotate\": [\n\t\t\t\t\t{ \"time\": 0, \"angle\": -12.79, \"curve\": \"stepped\" },\n\t\t\t\t\t{ \"time\": 0.0667, \"angle\": -12.79 },\n\t\t\t\t\t{ \"time\": 0.4333, \"angle\": 178.81 }\n\t\t\t\t],\n\t\t\t\t\"translate\": [\n\t\t\t\t\t{ \"time\": 0, \"x\": 56.54, \"y\": -9.42, \"curve\": \"stepped\" },\n\t\t\t\t\t{ \"time\": 0.0667, \"x\": 56.54, \"y\": -9.42 },\n\t\t\t\t\t{ \"time\": 0.4333, \"x\": 137.74, \"y\": -81.58 }\n\t\t\t\t],\n\t\t\t\t\"scale\": [\n\t\t\t\t\t{ \"time\": 0, \"x\": 1, \"y\": 1, \"curve\": \"stepped\" },\n\t\t\t\t\t{ \"time\": 0.0667, \"x\": 1, \"y\": 1 }\n\t\t\t\t]\n\t\t\t},\n\t\t\t\"gach4\": {\n\t\t\t\t\"rotate\": [\n\t\t\t\t\t{ \"time\": 0, \"angle\": 147.69, \"curve\": \"stepped\" },\n\t\t\t\t\t{ \"time\": 0.0667, \"angle\": 147.69 },\n\t\t\t\t\t{ \"time\": 0.4333, \"angle\": -23.23 }\n\t\t\t\t],\n\t\t\t\t\"translate\": [\n\t\t\t\t\t{ \"time\": 0, \"x\": 20.67, \"y\": -14.31, \"curve\": \"stepped\" },\n\t\t\t\t\t{ \"time\": 0.0667, \"x\": 20.67, \"y\": -14.31 },\n\t\t\t\t\t{ \"time\": 0.4333, \"x\": 17.79, \"y\": -105.87 }\n\t\t\t\t],\n\t\t\t\t\"scale\": [\n\t\t\t\t\t{ \"time\": 0, \"x\": 1, \"y\": 1, \"curve\": \"stepped\" },\n\t\t\t\t\t{ \"time\": 0.0667, \"x\": 1, \"y\": 1 }\n\t\t\t\t]\n\t\t\t},\n\t\t\t\"gach1\": {\n\t\t\t\t\"translate\": [\n\t\t\t\t\t{\n\t\t\t\t\t\t\"time\": 0,\n\t\t\t\t\t\t\"x\": 0,\n\t\t\t\t\t\t\"y\": 0,\n\t\t\t\t\t\t\"curve\": [ 0.147, 0.21, 0.744, 1 ]\n\t\t\t\t\t},\n\t\t\t\t\t{ \"time\": 0.5333, \"x\": 106.21, \"y\": -1.91 }\n\t\t\t\t],\n\t\t\t\t\"scale\": [\n\t\t\t\t\t{ \"time\": 0, \"x\": 1, \"y\": 1 }\n\t\t\t\t]\n\t\t\t},\n\t\t\t\"UD\": {\n\t\t\t\t\"rotate\": [\n\t\t\t\t\t{ \"time\": 0, \"angle\": 14.02, \"curve\": \"stepped\" },\n\t\t\t\t\t{\n\t\t\t\t\t\t\"time\": 0.0667,\n\t\t\t\t\t\t\"angle\": 14.02,\n\t\t\t\t\t\t\"curve\": [ 0.25, 0, 0.75, 1 ]\n\t\t\t\t\t},\n\t\t\t\t\t{ \"time\": 0.5667, \"angle\": -23.5 }\n\t\t\t\t],\n\t\t\t\t\"translate\": [\n\t\t\t\t\t{ \"time\": 0, \"x\": 0, \"y\": 0, \"curve\": \"stepped\" },\n\t\t\t\t\t{\n\t\t\t\t\t\t\"time\": 0.0667,\n\t\t\t\t\t\t\"x\": 0,\n\t\t\t\t\t\t\"y\": 0,\n\t\t\t\t\t\t\"curve\": [ 0.189, 0.13, 0.684, 1 ]\n\t\t\t\t\t},\n\t\t\t\t\t{\n\t\t\t\t\t\t\"time\": 0.3,\n\t\t\t\t\t\t\"x\": 0,\n\t\t\t\t\t\t\"y\": 18.33,\n\t\t\t\t\t\t\"curve\": [ 0.25, 0, 0.849, 0.65 ]\n\t\t\t\t\t},\n\t\t\t\t\t{ \"time\": 0.5667, \"x\": 0, \"y\": -44.34 }\n\t\t\t\t]\n\t\t\t},\n\t\t\t\"UD2\": {\n\t\t\t\t\"rotate\": [\n\t\t\t\t\t{ \"time\": 0, \"angle\": 14.02, \"curve\": \"stepped\" },\n\t\t\t\t\t{ \"time\": 0.0667, \"angle\": 14.02 },\n\t\t\t\t\t{ \"time\": 0.3, \"angle\": 119.66 },\n\t\t\t\t\t{ \"time\": 0.5667, \"angle\": -136.3 }\n\t\t\t\t],\n\t\t\t\t\"translate\": [\n\t\t\t\t\t{ \"time\": 0, \"x\": 0, \"y\": 0, \"curve\": \"stepped\" },\n\t\t\t\t\t{ \"time\": 0.0667, \"x\": 0, \"y\": 0 },\n\t\t\t\t\t{ \"time\": 0.3, \"x\": 8.96, \"y\": 19.95 },\n\t\t\t\t\t{ \"time\": 0.5667, \"x\": 5.28, \"y\": -70.01 }\n\t\t\t\t]\n\t\t\t},\n\t\t\t\"gach5\": {\n\t\t\t\t\"translate\": [\n\t\t\t\t\t{\n\t\t\t\t\t\t\"time\": 0,\n\t\t\t\t\t\t\"x\": 0,\n\t\t\t\t\t\t\"y\": 0,\n\t\t\t\t\t\t\"curve\": [ 0.147, 0.21, 0.744, 1 ]\n\t\t\t\t\t},\n\t\t\t\t\t{ \"time\": 0.5333, \"x\": -76.91, \"y\": -1.91 }\n\t\t\t\t],\n\t\t\t\t\"scale\": [\n\t\t\t\t\t{ \"time\": 0, \"x\": 1, \"y\": 1 }\n\t\t\t\t]\n\t\t\t},\n\t\t\t\"gach6\": {\n\t\t\t\t\"rotate\": [\n\t\t\t\t\t{ \"time\": 0, \"angle\": 147.69, \"curve\": \"stepped\" },\n\t\t\t\t\t{ \"time\": 0.0667, \"angle\": 147.69 },\n\t\t\t\t\t{ \"time\": 0.4333, \"angle\": -51.62 }\n\t\t\t\t],\n\t\t\t\t\"translate\": [\n\t\t\t\t\t{ \"time\": 0, \"x\": 0.01, \"y\": -11.21, \"curve\": \"stepped\" },\n\t\t\t\t\t{ \"time\": 0.0667, \"x\": 0.01, \"y\": -11.21 },\n\t\t\t\t\t{ \"time\": 0.4333, \"x\": -85.41, \"y\": 36.03 }\n\t\t\t\t],\n\t\t\t\t\"scale\": [\n\t\t\t\t\t{ \"time\": 0, \"x\": 1, \"y\": 1, \"curve\": \"stepped\" },\n\t\t\t\t\t{ \"time\": 0.0667, \"x\": 1, \"y\": 1 }\n\t\t\t\t]\n\t\t\t},\n\t\t\t\"gach7\": {\n\t\t\t\t\"rotate\": [\n\t\t\t\t\t{ \"time\": 0, \"angle\": 0, \"curve\": \"stepped\" },\n\t\t\t\t\t{ \"time\": 0.0667, \"angle\": 0 },\n\t\t\t\t\t{ \"time\": 0.4333, \"angle\": 195.75 }\n\t\t\t\t],\n\t\t\t\t\"translate\": [\n\t\t\t\t\t{ \"time\": 0, \"x\": 1.91, \"y\": -2.55, \"curve\": \"stepped\" },\n\t\t\t\t\t{ \"time\": 0.0667, \"x\": 1.91, \"y\": -2.55 },\n\t\t\t\t\t{ \"time\": 0.4333, \"x\": 61.38, \"y\": 23.22 }\n\t\t\t\t],\n\t\t\t\t\"scale\": [\n\t\t\t\t\t{ \"time\": 0, \"x\": 1, \"y\": 1, \"curve\": \"stepped\" },\n\t\t\t\t\t{ \"time\": 0.0667, \"x\": 1, \"y\": 1 }\n\t\t\t\t]\n\t\t\t},\n\t\t\t\"gach8\": {\n\t\t\t\t\"rotate\": [\n\t\t\t\t\t{ \"time\": 0, \"angle\": -12.79, \"curve\": \"stepped\" },\n\t\t\t\t\t{ \"time\": 0.0667, \"angle\": -12.79 },\n\t\t\t\t\t{ \"time\": 0.4333, \"angle\": -86.42 }\n\t\t\t\t],\n\t\t\t\t\"translate\": [\n\t\t\t\t\t{ \"time\": 0, \"x\": 0, \"y\": 0, \"curve\": \"stepped\" },\n\t\t\t\t\t{ \"time\": 0.0667, \"x\": 0, \"y\": 0 },\n\t\t\t\t\t{ \"time\": 0.4333, \"x\": -139.46, \"y\": -112.35 }\n\t\t\t\t],\n\t\t\t\t\"scale\": [\n\t\t\t\t\t{ \"time\": 0, \"x\": 1, \"y\": 1, \"curve\": \"stepped\" },\n\t\t\t\t\t{ \"time\": 0.0667, \"x\": 1, \"y\": 1 }\n\t\t\t\t]\n\t\t\t},\n\t\t\t\"gach_ALL\": {\n\t\t\t\t\"rotate\": [\n\t\t\t\t\t{ \"time\": 0, \"angle\": 0 }\n\t\t\t\t],\n\t\t\t\t\"translate\": [\n\t\t\t\t\t{ \"time\": 0, \"x\": 0, \"y\": 19.21 },\n\t\t\t\t\t{ \"time\": 0.4667, \"x\": 0, \"y\": 11.92 }\n\t\t\t\t],\n\t\t\t\t\"scale\": [\n\t\t\t\t\t{ \"time\": 0, \"x\": 1, \"y\": 1 },\n\t\t\t\t\t{ \"time\": 0.4667, \"x\": 1.2, \"y\": 1.2 }\n\t\t\t\t]\n\t\t\t},\n\t\t\t\"gach9\": {\n\t\t\t\t\"rotate\": [\n\t\t\t\t\t{ \"time\": 0, \"angle\": -12.79, \"curve\": \"stepped\" },\n\t\t\t\t\t{ \"time\": 0.0667, \"angle\": -12.79 },\n\t\t\t\t\t{ \"time\": 0.4333, \"angle\": 159.22 }\n\t\t\t\t],\n\t\t\t\t\"translate\": [\n\t\t\t\t\t{ \"time\": 0, \"x\": 0, \"y\": 0, \"curve\": \"stepped\" },\n\t\t\t\t\t{ \"time\": 0.0667, \"x\": 0, \"y\": 0 },\n\t\t\t\t\t{ \"time\": 0.4333, \"x\": -93.36, \"y\": -128.59 }\n\t\t\t\t],\n\t\t\t\t\"scale\": [\n\t\t\t\t\t{ \"time\": 0, \"x\": 1, \"y\": 1, \"curve\": \"stepped\" },\n\t\t\t\t\t{ \"time\": 0.0667, \"x\": 1, \"y\": 1 }\n\t\t\t\t]\n\t\t\t},\n\t\t\t\"gach10\": {\n\t\t\t\t\"rotate\": [\n\t\t\t\t\t{ \"time\": 0, \"angle\": 0, \"curve\": \"stepped\" },\n\t\t\t\t\t{ \"time\": 0.0667, \"angle\": 0 },\n\t\t\t\t\t{ \"time\": 0.4333, \"angle\": 195.75 }\n\t\t\t\t],\n\t\t\t\t\"translate\": [\n\t\t\t\t\t{ \"time\": 0, \"x\": 1.91, \"y\": -2.55, \"curve\": \"stepped\" },\n\t\t\t\t\t{ \"time\": 0.0667, \"x\": 1.91, \"y\": -2.55 },\n\t\t\t\t\t{ \"time\": 0.4333, \"x\": 61.38, \"y\": 23.22 }\n\t\t\t\t],\n\t\t\t\t\"scale\": [\n\t\t\t\t\t{ \"time\": 0, \"x\": 1, \"y\": 1, \"curve\": \"stepped\" },\n\t\t\t\t\t{ \"time\": 0.0667, \"x\": 1, \"y\": 1 }\n\t\t\t\t]\n\t\t\t},\n\t\t\t\"gach11\": {\n\t\t\t\t\"rotate\": [\n\t\t\t\t\t{ \"time\": 0, \"angle\": 147.69, \"curve\": \"stepped\" },\n\t\t\t\t\t{ \"time\": 0.0667, \"angle\": 147.69 },\n\t\t\t\t\t{ \"time\": 0.4, \"angle\": -51.62 }\n\t\t\t\t],\n\t\t\t\t\"translate\": [\n\t\t\t\t\t{ \"time\": 0, \"x\": 0.01, \"y\": -11.21, \"curve\": \"stepped\" },\n\t\t\t\t\t{ \"time\": 0.0667, \"x\": 0.01, \"y\": -11.21 },\n\t\t\t\t\t{ \"time\": 0.4, \"x\": -44.1, \"y\": 36.81 }\n\t\t\t\t],\n\t\t\t\t\"scale\": [\n\t\t\t\t\t{ \"time\": 0, \"x\": 1, \"y\": 1, \"curve\": \"stepped\" },\n\t\t\t\t\t{ \"time\": 0.0667, \"x\": 1, \"y\": 1 }\n\t\t\t\t]\n\t\t\t},\n\t\t\t\"UD3\": {\n\t\t\t\t\"rotate\": [\n\t\t\t\t\t{ \"time\": 0, \"angle\": 14.02, \"curve\": \"stepped\" },\n\t\t\t\t\t{ \"time\": 0.0667, \"angle\": 14.02 },\n\t\t\t\t\t{ \"time\": 0.3, \"angle\": 119.66 },\n\t\t\t\t\t{ \"time\": 0.5667, \"angle\": -136.3 }\n\t\t\t\t],\n\t\t\t\t\"translate\": [\n\t\t\t\t\t{ \"time\": 0, \"x\": 0, \"y\": 0, \"curve\": \"stepped\" },\n\t\t\t\t\t{ \"time\": 0.0667, \"x\": 0, \"y\": 0 },\n\t\t\t\t\t{ \"time\": 0.3, \"x\": 0, \"y\": 18.33 },\n\t\t\t\t\t{ \"time\": 0.5667, \"x\": 0, \"y\": -44.34 }\n\t\t\t\t]\n\t\t\t},\n\t\t\t\"gach12\": {\n\t\t\t\t\"translate\": [\n\t\t\t\t\t{\n\t\t\t\t\t\t\"time\": 0,\n\t\t\t\t\t\t\"x\": 0,\n\t\t\t\t\t\t\"y\": 0,\n\t\t\t\t\t\t\"curve\": [ 0.147, 0.21, 0.744, 1 ]\n\t\t\t\t\t},\n\t\t\t\t\t{ \"time\": 0.5333, \"x\": -76.91, \"y\": -1.91 }\n\t\t\t\t],\n\t\t\t\t\"scale\": [\n\t\t\t\t\t{ \"time\": 0, \"x\": 1, \"y\": 1 }\n\t\t\t\t]\n\t\t\t},\n\t\t\t\"gach13\": {\n\t\t\t\t\"rotate\": [\n\t\t\t\t\t{ \"time\": 0, \"angle\": 147.69, \"curve\": \"stepped\" },\n\t\t\t\t\t{ \"time\": 0.0667, \"angle\": 147.69 },\n\t\t\t\t\t{ \"time\": 0.4333, \"angle\": -23.23 }\n\t\t\t\t],\n\t\t\t\t\"translate\": [\n\t\t\t\t\t{ \"time\": 0, \"x\": 20.67, \"y\": -14.31, \"curve\": \"stepped\" },\n\t\t\t\t\t{ \"time\": 0.0667, \"x\": 20.67, \"y\": -14.31 },\n\t\t\t\t\t{ \"time\": 0.4333, \"x\": 41.95, \"y\": -105.09 }\n\t\t\t\t],\n\t\t\t\t\"scale\": [\n\t\t\t\t\t{ \"time\": 0, \"x\": 1, \"y\": 1, \"curve\": \"stepped\" },\n\t\t\t\t\t{ \"time\": 0.0667, \"x\": 1, \"y\": 1 }\n\t\t\t\t]\n\t\t\t},\n\t\t\t\"gach14\": {\n\t\t\t\t\"rotate\": [\n\t\t\t\t\t{ \"time\": 0, \"angle\": 0, \"curve\": \"stepped\" },\n\t\t\t\t\t{ \"time\": 0.0667, \"angle\": 0 },\n\t\t\t\t\t{ \"time\": 0.2333, \"angle\": 33.98 },\n\t\t\t\t\t{ \"time\": 0.4333, \"angle\": 161.39 }\n\t\t\t\t],\n\t\t\t\t\"translate\": [\n\t\t\t\t\t{ \"time\": 0, \"x\": 1.91, \"y\": -2.55, \"curve\": \"stepped\" },\n\t\t\t\t\t{ \"time\": 0.0667, \"x\": 1.91, \"y\": -2.55 },\n\t\t\t\t\t{ \"time\": 0.4333, \"x\": -36.11, \"y\": -117.14 }\n\t\t\t\t],\n\t\t\t\t\"scale\": [\n\t\t\t\t\t{ \"time\": 0, \"x\": 1, \"y\": 1, \"curve\": \"stepped\" },\n\t\t\t\t\t{ \"time\": 0.0667, \"x\": 1, \"y\": 1 }\n\t\t\t\t]\n\t\t\t},\n\t\t\t\"gach15\": {\n\t\t\t\t\"rotate\": [\n\t\t\t\t\t{ \"time\": 0, \"angle\": -12.79, \"curve\": \"stepped\" },\n\t\t\t\t\t{ \"time\": 0.0667, \"angle\": -12.79 },\n\t\t\t\t\t{ \"time\": 0.4333, \"angle\": 178.81 }\n\t\t\t\t],\n\t\t\t\t\"translate\": [\n\t\t\t\t\t{ \"time\": 0, \"x\": 56.54, \"y\": -9.42, \"curve\": \"stepped\" },\n\t\t\t\t\t{ \"time\": 0.0667, \"x\": 56.54, \"y\": -9.42 },\n\t\t\t\t\t{ \"time\": 0.4333, \"x\": 137.74, \"y\": -81.58 }\n\t\t\t\t],\n\t\t\t\t\"scale\": [\n\t\t\t\t\t{ \"time\": 0, \"x\": 1, \"y\": 1, \"curve\": \"stepped\" },\n\t\t\t\t\t{ \"time\": 0.0667, \"x\": 1, \"y\": 1 }\n\t\t\t\t]\n\t\t\t},\n\t\t\t\"UD4\": {\n\t\t\t\t\"rotate\": [\n\t\t\t\t\t{ \"time\": 0, \"angle\": 14.02, \"curve\": \"stepped\" },\n\t\t\t\t\t{\n\t\t\t\t\t\t\"time\": 0.0667,\n\t\t\t\t\t\t\"angle\": 14.02,\n\t\t\t\t\t\t\"curve\": [ 0.252, 0, 0.622, 0.48 ]\n\t\t\t\t\t},\n\t\t\t\t\t{\n\t\t\t\t\t\t\"time\": 0.3,\n\t\t\t\t\t\t\"angle\": 161.05,\n\t\t\t\t\t\t\"curve\": [ 0.372, 0.48, 0.752, 1 ]\n\t\t\t\t\t},\n\t\t\t\t\t{ \"time\": 0.5667, \"angle\": -23.5 }\n\t\t\t\t],\n\t\t\t\t\"translate\": [\n\t\t\t\t\t{ \"time\": 0, \"x\": 0, \"y\": 0, \"curve\": \"stepped\" },\n\t\t\t\t\t{\n\t\t\t\t\t\t\"time\": 0.0667,\n\t\t\t\t\t\t\"x\": 0,\n\t\t\t\t\t\t\"y\": 0,\n\t\t\t\t\t\t\"curve\": [ 0.189, 0.13, 0.684, 1 ]\n\t\t\t\t\t},\n\t\t\t\t\t{\n\t\t\t\t\t\t\"time\": 0.3,\n\t\t\t\t\t\t\"x\": 0,\n\t\t\t\t\t\t\"y\": 18.33,\n\t\t\t\t\t\t\"curve\": [ 0.25, 0, 0.849, 0.65 ]\n\t\t\t\t\t},\n\t\t\t\t\t{ \"time\": 0.5667, \"x\": 83.74, \"y\": -19.2 }\n\t\t\t\t]\n\t\t\t},\n\t\t\t\"gach16\": {\n\t\t\t\t\"translate\": [\n\t\t\t\t\t{\n\t\t\t\t\t\t\"time\": 0,\n\t\t\t\t\t\t\"x\": 0,\n\t\t\t\t\t\t\"y\": 0,\n\t\t\t\t\t\t\"curve\": [ 0.147, 0.21, 0.744, 1 ]\n\t\t\t\t\t},\n\t\t\t\t\t{ \"time\": 0.6, \"x\": 106.21, \"y\": -1.91 }\n\t\t\t\t],\n\t\t\t\t\"scale\": [\n\t\t\t\t\t{ \"time\": 0, \"x\": 1, \"y\": 1 }\n\t\t\t\t]\n\t\t\t},\n\t\t\t\"gach17\": {\n\t\t\t\t\"rotate\": [\n\t\t\t\t\t{ \"time\": 0, \"angle\": 0, \"curve\": \"stepped\" },\n\t\t\t\t\t{ \"time\": 0.0667, \"angle\": 0 },\n\t\t\t\t\t{ \"time\": 0.4333, \"angle\": 195.75 }\n\t\t\t\t],\n\t\t\t\t\"translate\": [\n\t\t\t\t\t{ \"time\": 0, \"x\": 1.91, \"y\": -2.55, \"curve\": \"stepped\" },\n\t\t\t\t\t{ \"time\": 0.0667, \"x\": 1.91, \"y\": -2.55 },\n\t\t\t\t\t{ \"time\": 0.4333, \"x\": 21.2, \"y\": -26.63 }\n\t\t\t\t],\n\t\t\t\t\"scale\": [\n\t\t\t\t\t{ \"time\": 0, \"x\": 1, \"y\": 1, \"curve\": \"stepped\" },\n\t\t\t\t\t{ \"time\": 0.0667, \"x\": 1, \"y\": 1 }\n\t\t\t\t]\n\t\t\t},\n\t\t\t\"gach18\": {\n\t\t\t\t\"rotate\": [\n\t\t\t\t\t{ \"time\": 0, \"angle\": 147.69, \"curve\": \"stepped\" },\n\t\t\t\t\t{ \"time\": 0.0667, \"angle\": 147.69 },\n\t\t\t\t\t{ \"time\": 0.4667, \"angle\": -51.62 }\n\t\t\t\t],\n\t\t\t\t\"translate\": [\n\t\t\t\t\t{ \"time\": 0, \"x\": 0.01, \"y\": -11.21, \"curve\": \"stepped\" },\n\t\t\t\t\t{ \"time\": 0.0667, \"x\": 0.01, \"y\": -11.21 },\n\t\t\t\t\t{ \"time\": 0.4667, \"x\": -15.83, \"y\": -62.9 }\n\t\t\t\t],\n\t\t\t\t\"scale\": [\n\t\t\t\t\t{ \"time\": 0, \"x\": 1, \"y\": 1, \"curve\": \"stepped\" },\n\t\t\t\t\t{ \"time\": 0.0667, \"x\": 1, \"y\": 1 }\n\t\t\t\t]\n\t\t\t},\n\t\t\t\"gach19\": {\n\t\t\t\t\"rotate\": [\n\t\t\t\t\t{ \"time\": 0, \"angle\": 147.69, \"curve\": \"stepped\" },\n\t\t\t\t\t{ \"time\": 0.0667, \"angle\": 147.69 },\n\t\t\t\t\t{ \"time\": 0.4333, \"angle\": -41.95 }\n\t\t\t\t],\n\t\t\t\t\"translate\": [\n\t\t\t\t\t{ \"time\": 0, \"x\": 20.67, \"y\": -14.31, \"curve\": \"stepped\" },\n\t\t\t\t\t{ \"time\": 0.0667, \"x\": 20.67, \"y\": -14.31 },\n\t\t\t\t\t{ \"time\": 0.4333, \"x\": -52.54, \"y\": -61.19 }\n\t\t\t\t],\n\t\t\t\t\"scale\": [\n\t\t\t\t\t{ \"time\": 0, \"x\": 1, \"y\": 1, \"curve\": \"stepped\" },\n\t\t\t\t\t{ \"time\": 0.0667, \"x\": 1, \"y\": 1 }\n\t\t\t\t]\n\t\t\t},\n\t\t\t\"gach20\": {\n\t\t\t\t\"rotate\": [\n\t\t\t\t\t{ \"time\": 0, \"angle\": -12.79, \"curve\": \"stepped\" },\n\t\t\t\t\t{ \"time\": 0.0667, \"angle\": -12.79 },\n\t\t\t\t\t{ \"time\": 0.4333, \"angle\": 128.12 }\n\t\t\t\t],\n\t\t\t\t\"translate\": [\n\t\t\t\t\t{ \"time\": 0, \"x\": 56.54, \"y\": -9.42, \"curve\": \"stepped\" },\n\t\t\t\t\t{ \"time\": 0.0667, \"x\": 56.54, \"y\": -9.42 },\n\t\t\t\t\t{ \"time\": 0.4333, \"x\": 71.51, \"y\": -86.79 }\n\t\t\t\t],\n\t\t\t\t\"scale\": [\n\t\t\t\t\t{ \"time\": 0, \"x\": 1, \"y\": 1, \"curve\": \"stepped\" },\n\t\t\t\t\t{ \"time\": 0.0667, \"x\": 1, \"y\": 1 }\n\t\t\t\t]\n\t\t\t},\n\t\t\t\"smokebom\": {\n\t\t\t\t\"scale\": [\n\t\t\t\t\t{ \"time\": 0, \"x\": 0.5, \"y\": 0.5 },\n\t\t\t\t\t{ \"time\": 0.5667, \"x\": 2, \"y\": 2 }\n\t\t\t\t]\n\t\t\t},\n\t\t\t\"smokebom2\": {\n\t\t\t\t\"rotate\": [\n\t\t\t\t\t{ \"time\": 0, \"angle\": -161.89 }\n\t\t\t\t],\n\t\t\t\t\"translate\": [\n\t\t\t\t\t{ \"time\": 0, \"x\": -22.12, \"y\": 18.43, \"curve\": \"stepped\" },\n\t\t\t\t\t{ \"time\": 0.0667, \"x\": -22.12, \"y\": 18.43 }\n\t\t\t\t],\n\t\t\t\t\"scale\": [\n\t\t\t\t\t{ \"time\": 0, \"x\": 0.5, \"y\": 0.5, \"curve\": \"stepped\" },\n\t\t\t\t\t{ \"time\": 0.0667, \"x\": 0.5, \"y\": 0.5 },\n\t\t\t\t\t{ \"time\": 0.6333, \"x\": 2, \"y\": 2 }\n\t\t\t\t]\n\t\t\t},\n\t\t\t\"smokebom3\": {\n\t\t\t\t\"rotate\": [\n\t\t\t\t\t{ \"time\": 0, \"angle\": -179.8, \"curve\": \"stepped\" },\n\t\t\t\t\t{ \"time\": 0.0333, \"angle\": -179.8 }\n\t\t\t\t],\n\t\t\t\t\"translate\": [\n\t\t\t\t\t{ \"time\": 0, \"x\": 7.37, \"y\": -18.44, \"curve\": \"stepped\" },\n\t\t\t\t\t{ \"time\": 0.0333, \"x\": 7.37, \"y\": -18.44 }\n\t\t\t\t],\n\t\t\t\t\"scale\": [\n\t\t\t\t\t{ \"time\": 0, \"x\": 0.5, \"y\": 0.5, \"curve\": \"stepped\" },\n\t\t\t\t\t{ \"time\": 0.0333, \"x\": 0.5, \"y\": 0.5 },\n\t\t\t\t\t{ \"time\": 0.6, \"x\": 2, \"y\": 2 }\n\t\t\t\t]\n\t\t\t},\n\t\t\t\"smokebom4\": {\n\t\t\t\t\"rotate\": [\n\t\t\t\t\t{ \"time\": 0, \"angle\": -161.89 }\n\t\t\t\t],\n\t\t\t\t\"translate\": [\n\t\t\t\t\t{ \"time\": 0, \"x\": 20.76, \"y\": 20.75 }\n\t\t\t\t],\n\t\t\t\t\"scale\": [\n\t\t\t\t\t{ \"time\": 0, \"x\": 0.5, \"y\": 0.5, \"curve\": \"stepped\" },\n\t\t\t\t\t{ \"time\": 0.1, \"x\": 0.5, \"y\": 0.5 },\n\t\t\t\t\t{ \"time\": 0.6667, \"x\": 2, \"y\": 2 }\n\t\t\t\t]\n\t\t\t}\n\t\t}\n\t},\n\t\"anim_normal\": {\n\t\t\"slots\": {\n\t\t\t\"lightitem5\": {\n\t\t\t\t\"color\": [\n\t\t\t\t\t{\n\t\t\t\t\t\t\"time\": 0,\n\t\t\t\t\t\t\"color\": \"ffffff00\",\n\t\t\t\t\t\t\"curve\": [ 0.25, 0, 0.75, 1 ]\n\t\t\t\t\t},\n\t\t\t\t\t{\n\t\t\t\t\t\t\"time\": 0.6667,\n\t\t\t\t\t\t\"color\": \"ffffffff\",\n\t\t\t\t\t\t\"curve\": [ 0.25, 0, 0.75, 1 ]\n\t\t\t\t\t},\n\t\t\t\t\t{\n\t\t\t\t\t\t\"time\": 1.3333,\n\t\t\t\t\t\t\"color\": \"ffffff00\",\n\t\t\t\t\t\t\"curve\": [ 0.25, 0, 0.75, 1 ]\n\t\t\t\t\t},\n\t\t\t\t\t{\n\t\t\t\t\t\t\"time\": 2,\n\t\t\t\t\t\t\"color\": \"ffffffff\",\n\t\t\t\t\t\t\"curve\": [ 0.25, 0, 0.75, 1 ]\n\t\t\t\t\t},\n\t\t\t\t\t{ \"time\": 2.6667, \"color\": \"ffffff00\" }\n\t\t\t\t]\n\t\t\t}\n\t\t},\n\t\t\"bones\": {\n\t\t\t\"item3\": {\n\t\t\t\t\"scale\": [\n\t\t\t\t\t{\n\t\t\t\t\t\t\"time\": 0,\n\t\t\t\t\t\t\"x\": 0.969,\n\t\t\t\t\t\t\"y\": 0.969,\n\t\t\t\t\t\t\"curve\": [ 0.25, 0, 0.75, 1 ]\n\t\t\t\t\t},\n\t\t\t\t\t{\n\t\t\t\t\t\t\"time\": 0.6667,\n\t\t\t\t\t\t\"x\": 1.01,\n\t\t\t\t\t\t\"y\": 1.01,\n\t\t\t\t\t\t\"curve\": [ 0.25, 0, 0.75, 1 ]\n\t\t\t\t\t},\n\t\t\t\t\t{\n\t\t\t\t\t\t\"time\": 1.3333,\n\t\t\t\t\t\t\"x\": 0.969,\n\t\t\t\t\t\t\"y\": 0.969,\n\t\t\t\t\t\t\"curve\": [ 0.25, 0, 0.75, 1 ]\n\t\t\t\t\t},\n\t\t\t\t\t{\n\t\t\t\t\t\t\"time\": 2,\n\t\t\t\t\t\t\"x\": 1.01,\n\t\t\t\t\t\t\"y\": 1.01,\n\t\t\t\t\t\t\"curve\": [ 0.25, 0, 0.75, 1 ]\n\t\t\t\t\t},\n\t\t\t\t\t{ \"time\": 2.6667, \"x\": 0.969, \"y\": 0.969 }\n\t\t\t\t]\n\t\t\t}\n\t\t}\n\t},\n\t\"anim_rung\": {\n\t\t\"slots\": {\n\t\t\t\"lightitem5\": {\n\t\t\t\t\"color\": [\n\t\t\t\t\t{\n\t\t\t\t\t\t\"time\": 0,\n\t\t\t\t\t\t\"color\": \"ffffff00\",\n\t\t\t\t\t\t\"curve\": [ 0.25, 0, 0.75, 1 ]\n\t\t\t\t\t},\n\t\t\t\t\t{\n\t\t\t\t\t\t\"time\": 0.6667,\n\t\t\t\t\t\t\"color\": \"ffffffff\",\n\t\t\t\t\t\t\"curve\": [ 0.25, 0, 0.75, 1 ]\n\t\t\t\t\t},\n\t\t\t\t\t{\n\t\t\t\t\t\t\"time\": 1.3333,\n\t\t\t\t\t\t\"color\": \"ffffff00\",\n\t\t\t\t\t\t\"curve\": [ 0.25, 0, 0.75, 1 ]\n\t\t\t\t\t},\n\t\t\t\t\t{\n\t\t\t\t\t\t\"time\": 2,\n\t\t\t\t\t\t\"color\": \"ffffffff\",\n\t\t\t\t\t\t\"curve\": [ 0.25, 0, 0.75, 1 ]\n\t\t\t\t\t},\n\t\t\t\t\t{ \"time\": 2.6667, \"color\": \"ffffff00\" }\n\t\t\t\t]\n\t\t\t}\n\t\t},\n\t\t\"bones\": {\n\t\t\t\"item3\": {\n\t\t\t\t\"scale\": [\n\t\t\t\t\t{\n\t\t\t\t\t\t\"time\": 0,\n\t\t\t\t\t\t\"x\": 0.969,\n\t\t\t\t\t\t\"y\": 0.969,\n\t\t\t\t\t\t\"curve\": [ 0.25, 0, 0.75, 1 ]\n\t\t\t\t\t},\n\t\t\t\t\t{\n\t\t\t\t\t\t\"time\": 0.6667,\n\t\t\t\t\t\t\"x\": 1.01,\n\t\t\t\t\t\t\"y\": 1.01,\n\t\t\t\t\t\t\"curve\": [ 0.25, 0, 0.75, 1 ]\n\t\t\t\t\t},\n\t\t\t\t\t{\n\t\t\t\t\t\t\"time\": 1.3333,\n\t\t\t\t\t\t\"x\": 0.969,\n\t\t\t\t\t\t\"y\": 0.969,\n\t\t\t\t\t\t\"curve\": [ 0.25, 0, 0.75, 1 ]\n\t\t\t\t\t},\n\t\t\t\t\t{\n\t\t\t\t\t\t\"time\": 2,\n\t\t\t\t\t\t\"x\": 1.01,\n\t\t\t\t\t\t\"y\": 1.01,\n\t\t\t\t\t\t\"curve\": [ 0.25, 0, 0.75, 1 ]\n\t\t\t\t\t},\n\t\t\t\t\t{ \"time\": 2.6667, \"x\": 0.969, \"y\": 0.969 }\n\t\t\t\t]\n\t\t\t},\n\t\t\t\"khung4\": {\n\t\t\t\t\"rotate\": [\n\t\t\t\t\t{\n\t\t\t\t\t\t\"time\": 0.0333,\n\t\t\t\t\t\t\"angle\": -1.42,\n\t\t\t\t\t\t\"curve\": [ 0.25, 0, 0.75, 1 ]\n\t\t\t\t\t},\n\t\t\t\t\t{\n\t\t\t\t\t\t\"time\": 0.1,\n\t\t\t\t\t\t\"angle\": 1.05,\n\t\t\t\t\t\t\"curve\": [ 0.25, 0, 0.75, 1 ]\n\t\t\t\t\t},\n\t\t\t\t\t{\n\t\t\t\t\t\t\"time\": 0.1667,\n\t\t\t\t\t\t\"angle\": -0.22,\n\t\t\t\t\t\t\"curve\": [ 0.25, 0, 0.75, 1 ]\n\t\t\t\t\t},\n\t\t\t\t\t{\n\t\t\t\t\t\t\"time\": 0.2333,\n\t\t\t\t\t\t\"angle\": 0.56,\n\t\t\t\t\t\t\"curve\": [ 0.25, 0, 0.75, 1 ]\n\t\t\t\t\t},\n\t\t\t\t\t{\n\t\t\t\t\t\t\"time\": 0.3,\n\t\t\t\t\t\t\"angle\": 2.85,\n\t\t\t\t\t\t\"curve\": [ 0.25, 0, 0.75, 1 ]\n\t\t\t\t\t},\n\t\t\t\t\t{\n\t\t\t\t\t\t\"time\": 0.3667,\n\t\t\t\t\t\t\"angle\": -1.55,\n\t\t\t\t\t\t\"curve\": [ 0.25, 0, 0.75, 1 ]\n\t\t\t\t\t},\n\t\t\t\t\t{\n\t\t\t\t\t\t\"time\": 0.4333,\n\t\t\t\t\t\t\"angle\": -0.13,\n\t\t\t\t\t\t\"curve\": [ 0.25, 0, 0.75, 1 ]\n\t\t\t\t\t},\n\t\t\t\t\t{\n\t\t\t\t\t\t\"time\": 0.5,\n\t\t\t\t\t\t\"angle\": 4.19,\n\t\t\t\t\t\t\"curve\": [ 0.25, 0, 0.75, 1 ]\n\t\t\t\t\t},\n\t\t\t\t\t{\n\t\t\t\t\t\t\"time\": 0.5667,\n\t\t\t\t\t\t\"angle\": -1.62,\n\t\t\t\t\t\t\"curve\": [ 0.25, 0, 0.75, 1 ]\n\t\t\t\t\t},\n\t\t\t\t\t{\n\t\t\t\t\t\t\"time\": 0.6333,\n\t\t\t\t\t\t\"angle\": 0.67,\n\t\t\t\t\t\t\"curve\": [ 0.25, 0, 0.75, 1 ]\n\t\t\t\t\t},\n\t\t\t\t\t{\n\t\t\t\t\t\t\"time\": 0.7,\n\t\t\t\t\t\t\"angle\": -1.42,\n\t\t\t\t\t\t\"curve\": [ 0.25, 0, 0.75, 1 ]\n\t\t\t\t\t},\n\t\t\t\t\t{\n\t\t\t\t\t\t\"time\": 0.7667,\n\t\t\t\t\t\t\"angle\": 1.05,\n\t\t\t\t\t\t\"curve\": [ 0.25, 0, 0.75, 1 ]\n\t\t\t\t\t},\n\t\t\t\t\t{\n\t\t\t\t\t\t\"time\": 0.8333,\n\t\t\t\t\t\t\"angle\": -0.22,\n\t\t\t\t\t\t\"curve\": [ 0.25, 0, 0.75, 1 ]\n\t\t\t\t\t},\n\t\t\t\t\t{\n\t\t\t\t\t\t\"time\": 0.9,\n\t\t\t\t\t\t\"angle\": 0.56,\n\t\t\t\t\t\t\"curve\": [ 0.25, 0, 0.75, 1 ]\n\t\t\t\t\t},\n\t\t\t\t\t{\n\t\t\t\t\t\t\"time\": 0.9667,\n\t\t\t\t\t\t\"angle\": 2.85,\n\t\t\t\t\t\t\"curve\": [ 0.25, 0, 0.75, 1 ]\n\t\t\t\t\t},\n\t\t\t\t\t{\n\t\t\t\t\t\t\"time\": 1.0333,\n\t\t\t\t\t\t\"angle\": -1.55,\n\t\t\t\t\t\t\"curve\": [ 0.25, 0, 0.75, 1 ]\n\t\t\t\t\t},\n\t\t\t\t\t{\n\t\t\t\t\t\t\"time\": 1.1,\n\t\t\t\t\t\t\"angle\": -0.13,\n\t\t\t\t\t\t\"curve\": [ 0.25, 0, 0.75, 1 ]\n\t\t\t\t\t},\n\t\t\t\t\t{\n\t\t\t\t\t\t\"time\": 1.1667,\n\t\t\t\t\t\t\"angle\": 4.19,\n\t\t\t\t\t\t\"curve\": [ 0.25, 0, 0.75, 1 ]\n\t\t\t\t\t},\n\t\t\t\t\t{\n\t\t\t\t\t\t\"time\": 1.2333,\n\t\t\t\t\t\t\"angle\": -1.62,\n\t\t\t\t\t\t\"curve\": [ 0.25, 0, 0.75, 1 ]\n\t\t\t\t\t},\n\t\t\t\t\t{\n\t\t\t\t\t\t\"time\": 1.3,\n\t\t\t\t\t\t\"angle\": 0.67,\n\t\t\t\t\t\t\"curve\": [ 0.25, 0, 0.75, 1 ]\n\t\t\t\t\t},\n\t\t\t\t\t{\n\t\t\t\t\t\t\"time\": 1.3667,\n\t\t\t\t\t\t\"angle\": -1.42,\n\t\t\t\t\t\t\"curve\": [ 0.25, 0, 0.75, 1 ]\n\t\t\t\t\t},\n\t\t\t\t\t{\n\t\t\t\t\t\t\"time\": 1.4333,\n\t\t\t\t\t\t\"angle\": 1.05,\n\t\t\t\t\t\t\"curve\": [ 0.25, 0, 0.75, 1 ]\n\t\t\t\t\t},\n\t\t\t\t\t{\n\t\t\t\t\t\t\"time\": 1.5,\n\t\t\t\t\t\t\"angle\": -0.22,\n\t\t\t\t\t\t\"curve\": [ 0.25, 0, 0.75, 1 ]\n\t\t\t\t\t},\n\t\t\t\t\t{\n\t\t\t\t\t\t\"time\": 1.5667,\n\t\t\t\t\t\t\"angle\": 0.56,\n\t\t\t\t\t\t\"curve\": [ 0.25, 0, 0.75, 1 ]\n\t\t\t\t\t},\n\t\t\t\t\t{\n\t\t\t\t\t\t\"time\": 1.6333,\n\t\t\t\t\t\t\"angle\": 2.85,\n\t\t\t\t\t\t\"curve\": [ 0.25, 0, 0.75, 1 ]\n\t\t\t\t\t},\n\t\t\t\t\t{\n\t\t\t\t\t\t\"time\": 1.7,\n\t\t\t\t\t\t\"angle\": -1.55,\n\t\t\t\t\t\t\"curve\": [ 0.25, 0, 0.75, 1 ]\n\t\t\t\t\t},\n\t\t\t\t\t{\n\t\t\t\t\t\t\"time\": 1.7667,\n\t\t\t\t\t\t\"angle\": -0.13,\n\t\t\t\t\t\t\"curve\": [ 0.25, 0, 0.75, 1 ]\n\t\t\t\t\t},\n\t\t\t\t\t{\n\t\t\t\t\t\t\"time\": 1.8333,\n\t\t\t\t\t\t\"angle\": 4.19,\n\t\t\t\t\t\t\"curve\": [ 0.25, 0, 0.75, 1 ]\n\t\t\t\t\t},\n\t\t\t\t\t{\n\t\t\t\t\t\t\"time\": 1.9,\n\t\t\t\t\t\t\"angle\": -1.62,\n\t\t\t\t\t\t\"curve\": [ 0.25, 0, 0.75, 1 ]\n\t\t\t\t\t},\n\t\t\t\t\t{\n\t\t\t\t\t\t\"time\": 1.9667,\n\t\t\t\t\t\t\"angle\": 0.67,\n\t\t\t\t\t\t\"curve\": [ 0.25, 0, 0.75, 1 ]\n\t\t\t\t\t},\n\t\t\t\t\t{\n\t\t\t\t\t\t\"time\": 2.0333,\n\t\t\t\t\t\t\"angle\": -1.55,\n\t\t\t\t\t\t\"curve\": [ 0.25, 0, 0.75, 1 ]\n\t\t\t\t\t},\n\t\t\t\t\t{\n\t\t\t\t\t\t\"time\": 2.1,\n\t\t\t\t\t\t\"angle\": -0.13,\n\t\t\t\t\t\t\"curve\": [ 0.25, 0, 0.75, 1 ]\n\t\t\t\t\t},\n\t\t\t\t\t{\n\t\t\t\t\t\t\"time\": 2.1667,\n\t\t\t\t\t\t\"angle\": 4.19,\n\t\t\t\t\t\t\"curve\": [ 0.25, 0, 0.75, 1 ]\n\t\t\t\t\t},\n\t\t\t\t\t{\n\t\t\t\t\t\t\"time\": 2.2333,\n\t\t\t\t\t\t\"angle\": -1.62,\n\t\t\t\t\t\t\"curve\": [ 0.25, 0, 0.75, 1 ]\n\t\t\t\t\t},\n\t\t\t\t\t{\n\t\t\t\t\t\t\"time\": 2.3,\n\t\t\t\t\t\t\"angle\": 0.67,\n\t\t\t\t\t\t\"curve\": [ 0.25, 0, 0.75, 1 ]\n\t\t\t\t\t},\n\t\t\t\t\t{\n\t\t\t\t\t\t\"time\": 2.3667,\n\t\t\t\t\t\t\"angle\": -1.42,\n\t\t\t\t\t\t\"curve\": [ 0.25, 0, 0.75, 1 ]\n\t\t\t\t\t},\n\t\t\t\t\t{\n\t\t\t\t\t\t\"time\": 2.4333,\n\t\t\t\t\t\t\"angle\": 1.05,\n\t\t\t\t\t\t\"curve\": [ 0.25, 0, 0.75, 1 ]\n\t\t\t\t\t},\n\t\t\t\t\t{\n\t\t\t\t\t\t\"time\": 2.5,\n\t\t\t\t\t\t\"angle\": -0.22,\n\t\t\t\t\t\t\"curve\": [ 0.25, 0, 0.75, 1 ]\n\t\t\t\t\t},\n\t\t\t\t\t{\n\t\t\t\t\t\t\"time\": 2.5667,\n\t\t\t\t\t\t\"angle\": 0.56,\n\t\t\t\t\t\t\"curve\": [ 0.25, 0, 0.75, 1 ]\n\t\t\t\t\t},\n\t\t\t\t\t{ \"time\": 2.6333, \"angle\": 2.85 }\n\t\t\t\t],\n\t\t\t\t\"translate\": [\n\t\t\t\t\t{\n\t\t\t\t\t\t\"time\": 0,\n\t\t\t\t\t\t\"x\": 0,\n\t\t\t\t\t\t\"y\": 0,\n\t\t\t\t\t\t\"curve\": [ 0.25, 0, 0.75, 1 ]\n\t\t\t\t\t},\n\t\t\t\t\t{\n\t\t\t\t\t\t\"time\": 0.0667,\n\t\t\t\t\t\t\"x\": 3.29,\n\t\t\t\t\t\t\"y\": -0.87,\n\t\t\t\t\t\t\"curve\": [ 0.25, 0, 0.75, 1 ]\n\t\t\t\t\t},\n\t\t\t\t\t{\n\t\t\t\t\t\t\"time\": 0.1333,\n\t\t\t\t\t\t\"x\": 0.93,\n\t\t\t\t\t\t\"y\": 1.45,\n\t\t\t\t\t\t\"curve\": [ 0.25, 0, 0.75, 1 ]\n\t\t\t\t\t},\n\t\t\t\t\t{\n\t\t\t\t\t\t\"time\": 0.2,\n\t\t\t\t\t\t\"x\": 2.33,\n\t\t\t\t\t\t\"y\": -3.67,\n\t\t\t\t\t\t\"curve\": [ 0.25, 0, 0.75, 1 ]\n\t\t\t\t\t},\n\t\t\t\t\t{\n\t\t\t\t\t\t\"time\": 0.2667,\n\t\t\t\t\t\t\"x\": -0.78,\n\t\t\t\t\t\t\"y\": 0.27,\n\t\t\t\t\t\t\"curve\": [ 0.25, 0, 0.75, 1 ]\n\t\t\t\t\t},\n\t\t\t\t\t{\n\t\t\t\t\t\t\"time\": 0.3333,\n\t\t\t\t\t\t\"x\": 2.56,\n\t\t\t\t\t\t\"y\": 2.81,\n\t\t\t\t\t\t\"curve\": [ 0.25, 0, 0.75, 1 ]\n\t\t\t\t\t},\n\t\t\t\t\t{\n\t\t\t\t\t\t\"time\": 0.4,\n\t\t\t\t\t\t\"x\": -0.87,\n\t\t\t\t\t\t\"y\": -4.88,\n\t\t\t\t\t\t\"curve\": [ 0.25, 0, 0.75, 1 ]\n\t\t\t\t\t},\n\t\t\t\t\t{\n\t\t\t\t\t\t\"time\": 0.4667,\n\t\t\t\t\t\t\"x\": 2.05,\n\t\t\t\t\t\t\"y\": -1.35,\n\t\t\t\t\t\t\"curve\": [ 0.25, 0, 0.75, 1 ]\n\t\t\t\t\t},\n\t\t\t\t\t{\n\t\t\t\t\t\t\"time\": 0.5333,\n\t\t\t\t\t\t\"x\": -1.26,\n\t\t\t\t\t\t\"y\": 1.42,\n\t\t\t\t\t\t\"curve\": [ 0.25, 0, 0.75, 1 ]\n\t\t\t\t\t},\n\t\t\t\t\t{\n\t\t\t\t\t\t\"time\": 0.6,\n\t\t\t\t\t\t\"x\": 1.3,\n\t\t\t\t\t\t\"y\": -5.35,\n\t\t\t\t\t\t\"curve\": [ 0.25, 0, 0.75, 1 ]\n\t\t\t\t\t},\n\t\t\t\t\t{\n\t\t\t\t\t\t\"time\": 0.6667,\n\t\t\t\t\t\t\"x\": -1.33,\n\t\t\t\t\t\t\"y\": 0,\n\t\t\t\t\t\t\"curve\": [ 0.25, 0, 0.75, 1 ]\n\t\t\t\t\t},\n\t\t\t\t\t{\n\t\t\t\t\t\t\"time\": 0.7333,\n\t\t\t\t\t\t\"x\": 2.53,\n\t\t\t\t\t\t\"y\": -0.02,\n\t\t\t\t\t\t\"curve\": [ 0.25, 0, 0.75, 1 ]\n\t\t\t\t\t},\n\t\t\t\t\t{\n\t\t\t\t\t\t\"time\": 0.8,\n\t\t\t\t\t\t\"x\": 0.23,\n\t\t\t\t\t\t\"y\": -6.65,\n\t\t\t\t\t\t\"curve\": [ 0.25, 0, 0.75, 1 ]\n\t\t\t\t\t},\n\t\t\t\t\t{\n\t\t\t\t\t\t\"time\": 0.8667,\n\t\t\t\t\t\t\"x\": 2.33,\n\t\t\t\t\t\t\"y\": -0.05,\n\t\t\t\t\t\t\"curve\": [ 0.25, 0, 0.75, 1 ]\n\t\t\t\t\t},\n\t\t\t\t\t{\n\t\t\t\t\t\t\"time\": 0.9333,\n\t\t\t\t\t\t\"x\": -2.3,\n\t\t\t\t\t\t\"y\": -0.49,\n\t\t\t\t\t\t\"curve\": [ 0.25, 0, 0.75, 1 ]\n\t\t\t\t\t},\n\t\t\t\t\t{\n\t\t\t\t\t\t\"time\": 1,\n\t\t\t\t\t\t\"x\": 0,\n\t\t\t\t\t\t\"y\": 0,\n\t\t\t\t\t\t\"curve\": [ 0.25, 0, 0.75, 1 ]\n\t\t\t\t\t},\n\t\t\t\t\t{\n\t\t\t\t\t\t\"time\": 1.0667,\n\t\t\t\t\t\t\"x\": 3.29,\n\t\t\t\t\t\t\"y\": -0.87,\n\t\t\t\t\t\t\"curve\": [ 0.25, 0, 0.75, 1 ]\n\t\t\t\t\t},\n\t\t\t\t\t{\n\t\t\t\t\t\t\"time\": 1.1333,\n\t\t\t\t\t\t\"x\": 0.93,\n\t\t\t\t\t\t\"y\": 1.45,\n\t\t\t\t\t\t\"curve\": [ 0.25, 0, 0.75, 1 ]\n\t\t\t\t\t},\n\t\t\t\t\t{\n\t\t\t\t\t\t\"time\": 1.2,\n\t\t\t\t\t\t\"x\": 2.33,\n\t\t\t\t\t\t\"y\": -3.67,\n\t\t\t\t\t\t\"curve\": [ 0.25, 0, 0.75, 1 ]\n\t\t\t\t\t},\n\t\t\t\t\t{\n\t\t\t\t\t\t\"time\": 1.2667,\n\t\t\t\t\t\t\"x\": -0.78,\n\t\t\t\t\t\t\"y\": 0.27,\n\t\t\t\t\t\t\"curve\": [ 0.25, 0, 0.75, 1 ]\n\t\t\t\t\t},\n\t\t\t\t\t{\n\t\t\t\t\t\t\"time\": 1.3333,\n\t\t\t\t\t\t\"x\": 2.56,\n\t\t\t\t\t\t\"y\": 2.81,\n\t\t\t\t\t\t\"curve\": [ 0.25, 0, 0.75, 1 ]\n\t\t\t\t\t},\n\t\t\t\t\t{\n\t\t\t\t\t\t\"time\": 1.4,\n\t\t\t\t\t\t\"x\": -0.87,\n\t\t\t\t\t\t\"y\": -4.88,\n\t\t\t\t\t\t\"curve\": [ 0.25, 0, 0.75, 1 ]\n\t\t\t\t\t},\n\t\t\t\t\t{\n\t\t\t\t\t\t\"time\": 1.4667,\n\t\t\t\t\t\t\"x\": 2.05,\n\t\t\t\t\t\t\"y\": -1.35,\n\t\t\t\t\t\t\"curve\": [ 0.25, 0, 0.75, 1 ]\n\t\t\t\t\t},\n\t\t\t\t\t{\n\t\t\t\t\t\t\"time\": 1.5333,\n\t\t\t\t\t\t\"x\": -1.26,\n\t\t\t\t\t\t\"y\": 1.42,\n\t\t\t\t\t\t\"curve\": [ 0.25, 0, 0.75, 1 ]\n\t\t\t\t\t},\n\t\t\t\t\t{\n\t\t\t\t\t\t\"time\": 1.6,\n\t\t\t\t\t\t\"x\": 1.3,\n\t\t\t\t\t\t\"y\": -5.35,\n\t\t\t\t\t\t\"curve\": [ 0.25, 0, 0.75, 1 ]\n\t\t\t\t\t},\n\t\t\t\t\t{\n\t\t\t\t\t\t\"time\": 1.6667,\n\t\t\t\t\t\t\"x\": -1.33,\n\t\t\t\t\t\t\"y\": 0,\n\t\t\t\t\t\t\"curve\": [ 0.25, 0, 0.75, 1 ]\n\t\t\t\t\t},\n\t\t\t\t\t{\n\t\t\t\t\t\t\"time\": 1.7333,\n\t\t\t\t\t\t\"x\": 2.53,\n\t\t\t\t\t\t\"y\": -0.02,\n\t\t\t\t\t\t\"curve\": [ 0.25, 0, 0.75, 1 ]\n\t\t\t\t\t},\n\t\t\t\t\t{\n\t\t\t\t\t\t\"time\": 1.8,\n\t\t\t\t\t\t\"x\": 0.23,\n\t\t\t\t\t\t\"y\": -6.65,\n\t\t\t\t\t\t\"curve\": [ 0.25, 0, 0.75, 1 ]\n\t\t\t\t\t},\n\t\t\t\t\t{\n\t\t\t\t\t\t\"time\": 1.8667,\n\t\t\t\t\t\t\"x\": 2.33,\n\t\t\t\t\t\t\"y\": -0.05,\n\t\t\t\t\t\t\"curve\": [ 0.25, 0, 0.75, 1 ]\n\t\t\t\t\t},\n\t\t\t\t\t{\n\t\t\t\t\t\t\"time\": 1.9333,\n\t\t\t\t\t\t\"x\": -2.3,\n\t\t\t\t\t\t\"y\": -0.49,\n\t\t\t\t\t\t\"curve\": [ 0.25, 0, 0.75, 1 ]\n\t\t\t\t\t},\n\t\t\t\t\t{\n\t\t\t\t\t\t\"time\": 2,\n\t\t\t\t\t\t\"x\": 0,\n\t\t\t\t\t\t\"y\": 0,\n\t\t\t\t\t\t\"curve\": [ 0.25, 0, 0.75, 1 ]\n\t\t\t\t\t},\n\t\t\t\t\t{\n\t\t\t\t\t\t\"time\": 2.0667,\n\t\t\t\t\t\t\"x\": 3.29,\n\t\t\t\t\t\t\"y\": -0.87,\n\t\t\t\t\t\t\"curve\": [ 0.25, 0, 0.75, 1 ]\n\t\t\t\t\t},\n\t\t\t\t\t{\n\t\t\t\t\t\t\"time\": 2.1333,\n\t\t\t\t\t\t\"x\": 0.93,\n\t\t\t\t\t\t\"y\": 1.45,\n\t\t\t\t\t\t\"curve\": [ 0.25, 0, 0.75, 1 ]\n\t\t\t\t\t},\n\t\t\t\t\t{\n\t\t\t\t\t\t\"time\": 2.2,\n\t\t\t\t\t\t\"x\": 2.33,\n\t\t\t\t\t\t\"y\": -3.67,\n\t\t\t\t\t\t\"curve\": [ 0.25, 0, 0.75, 1 ]\n\t\t\t\t\t},\n\t\t\t\t\t{\n\t\t\t\t\t\t\"time\": 2.2667,\n\t\t\t\t\t\t\"x\": -0.78,\n\t\t\t\t\t\t\"y\": 0.27,\n\t\t\t\t\t\t\"curve\": [ 0.25, 0, 0.75, 1 ]\n\t\t\t\t\t},\n\t\t\t\t\t{\n\t\t\t\t\t\t\"time\": 2.3333,\n\t\t\t\t\t\t\"x\": 2.56,\n\t\t\t\t\t\t\"y\": 2.81,\n\t\t\t\t\t\t\"curve\": [ 0.25, 0, 0.75, 1 ]\n\t\t\t\t\t},\n\t\t\t\t\t{\n\t\t\t\t\t\t\"time\": 2.4,\n\t\t\t\t\t\t\"x\": -0.87,\n\t\t\t\t\t\t\"y\": -4.88,\n\t\t\t\t\t\t\"curve\": [ 0.25, 0, 0.75, 1 ]\n\t\t\t\t\t},\n\t\t\t\t\t{\n\t\t\t\t\t\t\"time\": 2.4667,\n\t\t\t\t\t\t\"x\": 2.05,\n\t\t\t\t\t\t\"y\": -1.35,\n\t\t\t\t\t\t\"curve\": [ 0.25, 0, 0.75, 1 ]\n\t\t\t\t\t},\n\t\t\t\t\t{\n\t\t\t\t\t\t\"time\": 2.5333,\n\t\t\t\t\t\t\"x\": -1.26,\n\t\t\t\t\t\t\"y\": 1.42,\n\t\t\t\t\t\t\"curve\": [ 0.25, 0, 0.75, 1 ]\n\t\t\t\t\t},\n\t\t\t\t\t{\n\t\t\t\t\t\t\"time\": 2.6,\n\t\t\t\t\t\t\"x\": 1.3,\n\t\t\t\t\t\t\"y\": -5.35,\n\t\t\t\t\t\t\"curve\": [ 0.25, 0, 0.75, 1 ]\n\t\t\t\t\t},\n\t\t\t\t\t{ \"time\": 2.6667, \"x\": -1.33, \"y\": 0 }\n\t\t\t\t]\n\t\t\t}\n\t\t}\n\t}\n}\n}","_skeletonJson":{"skeleton":{"hash":"gqh6K7huG3oagiyp8QiZ4tv1acA","spine":"3.6.53","width":308,"height":303,"images":"./images/"},"bones":[{"name":"root"},{"name":"explore_all","parent":"root"},{"name":"gach_ALL","parent":"explore_all","x":1.7,"y":-12.98},{"name":"gach1","parent":"gach_ALL","x":32.27,"y":24.45},{"name":"UD","parent":"gach1"},{"name":"gach5","parent":"gach_ALL","x":-31,"y":-7.91},{"name":"UD2","parent":"gach5","x":-5.28,"y":17.61},{"name":"gach12","parent":"gach_ALL","rotation":-75.74,"x":-16.5,"y":2.06},{"name":"UD3","parent":"gach12","x":-5.28,"y":17.61},{"name":"gach16","parent":"gach_ALL","rotation":-68.7,"x":-32.96,"y":-0.92},{"name":"UD4","parent":"gach16"},{"name":"gach2","parent":"gach_ALL","x":-40.1,"y":25.43},{"name":"gach3","parent":"gach_ALL","x":-6.36,"y":42.05},{"name":"gach4","parent":"gach_ALL","x":2.93,"y":1.47},{"name":"gach6","parent":"gach_ALL","rotation":166.22,"x":5.09,"y":30.23},{"name":"gach7","parent":"gach_ALL","rotation":-143.1,"x":9.46,"y":19.76},{"name":"gach8","parent":"gach_ALL","rotation":158.71,"x":34.68,"y":33.34},{"name":"gach9","parent":"gach_ALL","rotation":16.72,"x":-1.56,"y":17.03},{"name":"gach10","parent":"gach_ALL","rotation":-23.66,"x":-31.31,"y":43.32},{"name":"gach11","parent":"gach_ALL","rotation":-143.68,"x":31.36,"y":41.1},{"name":"gach13","parent":"gach_ALL","rotation":149.95,"x":29.21,"y":12.34},{"name":"gach14","parent":"gach_ALL","rotation":161.69,"x":-0.92,"y":-15.93},{"name":"gach15","parent":"gach_ALL","rotation":53.25,"x":26.95,"y":-9},{"name":"gach17","parent":"gach_ALL","rotation":-23.66,"x":-31.31,"y":43.32},{"name":"gach18","parent":"gach_ALL","rotation":-143.68,"x":31.36,"y":41.1},{"name":"gach19","parent":"gach_ALL","rotation":149.95,"x":29.21,"y":12.34},{"name":"gach20","parent":"gach_ALL","x":-40.1,"y":25.43},{"name":"khung4","parent":"root"},{"name":"item3","parent":"khung4","x":-2.15,"y":10.8},{"name":"light_item5","parent":"item3","x":-2.23,"y":0.73,"scaleX":1.3,"scaleY":1.3},{"name":"smokebom","parent":"explore_all","x":6.08,"y":-27,"scaleX":1.5,"scaleY":1.5},{"name":"smokebom2","parent":"explore_all","x":6.08,"y":-27,"scaleX":0.8,"scaleY":0.8},{"name":"smokebom3","parent":"explore_all","x":6.08,"y":-27,"scaleX":0.7,"scaleY":0.7},{"name":"smokebom4","parent":"explore_all","x":6.08,"y":-27,"scaleX":0.8,"scaleY":0.8}],"slots":[{"name":"khung4","bone":"khung4","attachment":"khung1"},{"name":"item3","bone":"item3","attachment":"item3"},{"name":"lightitem5","bone":"light_item5","attachment":"lightitem3","blend":"additive"},{"name":"explore/special.0_0","bone":"smokebom","color":"ffffff00","attachment":"explore/special.0_0","blend":"additive"},{"name":"explore/special.0_1","bone":"smokebom2","color":"ffffff00","attachment":"explore/special.0_0","blend":"additive"},{"name":"explore/special.0_3","bone":"smokebom4","color":"ffffff00","attachment":"explore/special.0_0","blend":"additive"},{"name":"explore/special.0_2","bone":"smokebom3","color":"ffffff00","attachment":"explore/special.0_0","blend":"additive"},{"name":"explore/gach1","bone":"UD","color":"ffffff00","attachment":"explore/gach1"},{"name":"explore/gach16","bone":"UD4","color":"ffffff00","attachment":"explore/gach1"},{"name":"explore/gach5","bone":"UD2","color":"ffffff00","attachment":"explore/gach2"},{"name":"explore/gach12","bone":"UD3","color":"ffffff00","attachment":"explore/gach2"},{"name":"explore/gach2","bone":"gach2","color":"ffffff00","attachment":"explore/gach2"},{"name":"explore/gach20","bone":"gach20","color":"ffffff00","attachment":"explore/gach2"},{"name":"explore/gach15","bone":"gach15","color":"ffffff00","attachment":"explore/gach2"},{"name":"explore/gach8","bone":"gach8","color":"ffffff00","attachment":"explore/gach2"},{"name":"explore/gach9","bone":"gach9","color":"ffffff00","attachment":"explore/gach2"},{"name":"explore/gach3","bone":"gach3","color":"ffffff00","attachment":"explore/gach3"},{"name":"explore/gach14","bone":"gach14","color":"ffffff00","attachment":"explore/gach3"},{"name":"explore/gach7","bone":"gach7","color":"ffffff00","attachment":"explore/gach3"},{"name":"explore/gach10","bone":"gach10","color":"ffffff00","attachment":"explore/gach3"},{"name":"explore/gach17","bone":"gach17","color":"ffffff00","attachment":"explore/gach3"},{"name":"explore/gach4","bone":"gach4","color":"ffffff00","attachment":"explore/gach4"},{"name":"explore/gach13","bone":"gach13","color":"ffffff00","attachment":"explore/gach4"},{"name":"explore/gach19","bone":"gach19","color":"ffffff00","attachment":"explore/gach4"},{"name":"explore/gach6","bone":"gach6","color":"ffffff00","attachment":"explore/gach4"},{"name":"explore/gach11","bone":"gach11","color":"ffffff00","attachment":"explore/gach4"},{"name":"explore/gach18","bone":"gach18","color":"ffffff00","attachment":"explore/gach4"}],"skins":{"default":{"explore/gach1":{"explore/gach1":{"width":50,"height":11}},"explore/gach10":{"explore/gach3":{"width":41,"height":16}},"explore/gach11":{"explore/gach4":{"width":52,"height":17}},"explore/gach12":{"explore/gach2":{"x":0.25,"y":0.36,"rotation":-141.65,"width":38,"height":20}},"explore/gach13":{"explore/gach4":{"width":52,"height":17}},"explore/gach14":{"explore/gach3":{"width":41,"height":16}},"explore/gach15":{"explore/gach2":{"width":38,"height":20}},"explore/gach16":{"explore/gach1":{"width":50,"height":11}},"explore/gach17":{"explore/gach3":{"width":41,"height":16}},"explore/gach18":{"explore/gach4":{"width":52,"height":17}},"explore/gach19":{"explore/gach4":{"width":52,"height":17}},"explore/gach2":{"explore/gach2":{"width":38,"height":20}},"explore/gach20":{"explore/gach2":{"width":38,"height":20}},"explore/gach3":{"explore/gach3":{"width":41,"height":16}},"explore/gach4":{"explore/gach4":{"width":52,"height":17}},"explore/gach5":{"explore/gach2":{"x":0.25,"y":0.36,"rotation":-141.65,"width":38,"height":20}},"explore/gach6":{"explore/gach4":{"width":52,"height":17}},"explore/gach7":{"explore/gach3":{"width":41,"height":16}},"explore/gach8":{"explore/gach2":{"width":38,"height":20}},"explore/gach9":{"explore/gach2":{"width":38,"height":20}},"explore/special.0_0":{"explore/special.0_0":{"width":117,"height":113},"explore/special.0_1":{"width":117,"height":113},"explore/special.0_2":{"width":117,"height":113},"explore/special.0_3":{"width":117,"height":113},"explore/special.0_4":{"width":117,"height":113},"explore/special.0_5":{"width":117,"height":113},"explore/special.0_6":{"width":117,"height":113}},"explore/special.0_1":{"explore/special.0_0":{"width":117,"height":113},"explore/special.0_1":{"width":117,"height":113},"explore/special.0_2":{"width":117,"height":113},"explore/special.0_3":{"width":117,"height":113},"explore/special.0_4":{"width":117,"height":113},"explore/special.0_5":{"width":117,"height":113},"explore/special.0_6":{"width":117,"height":113}},"explore/special.0_2":{"explore/special.0_0":{"width":117,"height":113},"explore/special.0_1":{"width":117,"height":113},"explore/special.0_2":{"width":117,"height":113},"explore/special.0_3":{"width":117,"height":113},"explore/special.0_4":{"width":117,"height":113},"explore/special.0_5":{"width":117,"height":113},"explore/special.0_6":{"width":117,"height":113}},"explore/special.0_3":{"explore/special.0_0":{"width":117,"height":113},"explore/special.0_1":{"width":117,"height":113},"explore/special.0_2":{"width":117,"height":113},"explore/special.0_3":{"width":117,"height":113},"explore/special.0_4":{"width":117,"height":113},"explore/special.0_5":{"width":117,"height":113},"explore/special.0_6":{"width":117,"height":113}},"item3":{"item3":{"x":-0.47,"y":-10.3,"width":148,"height":147}},"khung4":{"khung1":{"width":185,"height":186}},"lightitem5":{"lightitem3":{"x":2.81,"y":-3.55,"width":95,"height":89}}}},"animations":{"anim_no":{"slots":{"explore/gach1":{"color":[{"time":0,"color":"ffffff00","curve":"stepped"},{"time":0.0667,"color":"ffffffff","curve":"stepped"},{"time":0.3667,"color":"ffffffff"},{"time":0.5,"color":"ffffff00"}]},"explore/gach2":{"color":[{"time":0,"color":"ffffff00","curve":"stepped"},{"time":0.0667,"color":"ffffffff","curve":"stepped"},{"time":0.3667,"color":"ffffffff"},{"time":0.5,"color":"ffffff00"}]},"explore/gach3":{"color":[{"time":0,"color":"ffffff00","curve":"stepped"},{"time":0.0667,"color":"ffffffff","curve":"stepped"},{"time":0.3667,"color":"ffffffff"},{"time":0.5,"color":"ffffff00"}]},"explore/gach4":{"color":[{"time":0,"color":"ffffff00","curve":"stepped"},{"time":0.0667,"color":"ffffffff","curve":"stepped"},{"time":0.3667,"color":"ffffffff"},{"time":0.5,"color":"ffffff00"}]},"explore/gach5":{"color":[{"time":0,"color":"ffffff00","curve":"stepped"},{"time":0.0667,"color":"ffffffff","curve":"stepped"},{"time":0.3667,"color":"ffffffff"},{"time":0.5,"color":"ffffff00"}]},"explore/gach6":{"color":[{"time":0,"color":"ffffff00","curve":"stepped"},{"time":0.0667,"color":"ffffffff","curve":"stepped"},{"time":0.3667,"color":"ffffffff"},{"time":0.5,"color":"ffffff00"}]},"explore/gach7":{"color":[{"time":0,"color":"ffffff00","curve":"stepped"},{"time":0.0667,"color":"ffffffff","curve":"stepped"},{"time":0.3667,"color":"ffffffff"},{"time":0.5,"color":"ffffff00"}]},"explore/gach8":{"color":[{"time":0,"color":"ffffff00","curve":"stepped"},{"time":0.0667,"color":"ffffffff","curve":"stepped"},{"time":0.3667,"color":"ffffffff"},{"time":0.5,"color":"ffffff00"}]},"explore/gach9":{"color":[{"time":0,"color":"ffffff00","curve":"stepped"},{"time":0.0667,"color":"ffffffff","curve":"stepped"},{"time":0.3667,"color":"ffffffff"},{"time":0.5,"color":"ffffff00"}]},"explore/gach10":{"color":[{"time":0,"color":"ffffff00","curve":"stepped"},{"time":0.0667,"color":"ffffffff","curve":"stepped"},{"time":0.3667,"color":"ffffffff"},{"time":0.5,"color":"ffffff00"}]},"explore/gach11":{"color":[{"time":0,"color":"ffffff00","curve":"stepped"},{"time":0.0667,"color":"ffffffff","curve":"stepped"},{"time":0.3667,"color":"ffffffff"},{"time":0.5,"color":"ffffff00"}]},"explore/gach12":{"color":[{"time":0,"color":"ffffff00","curve":"stepped"},{"time":0.0667,"color":"ffffffff","curve":"stepped"},{"time":0.3667,"color":"ffffffff"},{"time":0.5,"color":"ffffff00"}]},"explore/gach13":{"color":[{"time":0,"color":"ffffff00","curve":"stepped"},{"time":0.0667,"color":"ffffffff","curve":"stepped"},{"time":0.3667,"color":"ffffffff"},{"time":0.5,"color":"ffffff00"}]},"explore/gach14":{"color":[{"time":0,"color":"ffffff00","curve":"stepped"},{"time":0.0667,"color":"ffffffff","curve":"stepped"},{"time":0.3667,"color":"ffffffff"},{"time":0.5,"color":"ffffff00"}]},"explore/gach15":{"color":[{"time":0,"color":"ffffff00","curve":"stepped"},{"time":0.0667,"color":"ffffffff","curve":"stepped"},{"time":0.3667,"color":"ffffffff"},{"time":0.5,"color":"ffffff00"}]},"explore/gach16":{"color":[{"time":0,"color":"ffffff00","curve":"stepped"},{"time":0.0667,"color":"ffffffff","curve":"stepped"},{"time":0.3667,"color":"ffffffff"},{"time":0.5,"color":"ffffff00"}]},"explore/gach17":{"color":[{"time":0,"color":"ffffff00","curve":"stepped"},{"time":0.0667,"color":"ffffffff","curve":"stepped"},{"time":0.3667,"color":"ffffffff"},{"time":0.5,"color":"ffffff00"}]},"explore/gach18":{"color":[{"time":0,"color":"ffffff00","curve":"stepped"},{"time":0.0667,"color":"ffffffff","curve":"stepped"},{"time":0.3667,"color":"ffffffff"},{"time":0.5,"color":"ffffff00"}]},"explore/gach19":{"color":[{"time":0,"color":"ffffff00","curve":"stepped"},{"time":0.0667,"color":"ffffffff","curve":"stepped"},{"time":0.3667,"color":"ffffffff"},{"time":0.5,"color":"ffffff00"}]},"explore/gach20":{"color":[{"time":0,"color":"ffffff00","curve":"stepped"},{"time":0.0667,"color":"ffffffff","curve":"stepped"},{"time":0.3667,"color":"ffffffff"},{"time":0.5,"color":"ffffff00"}]},"explore/special.0_0":{"color":[{"time":0,"color":"ffffff00"},{"time":0.1,"color":"ffffffff","curve":"stepped"},{"time":0.4333,"color":"ffffffff"},{"time":0.5667,"color":"ffffff00"}],"attachment":[{"time":0.0667,"name":"explore/special.0_0"},{"time":0.1333,"name":"explore/special.0_1"},{"time":0.2,"name":"explore/special.0_2"},{"time":0.2667,"name":"explore/special.0_3"},{"time":0.3333,"name":"explore/special.0_4"},{"time":0.4,"name":"explore/special.0_5"},{"time":0.4667,"name":"explore/special.0_6"},{"time":0.5333,"name":null}]},"explore/special.0_1":{"color":[{"time":0,"color":"ffffff00","curve":"stepped"},{"time":0.0667,"color":"ffffff00"},{"time":0.1667,"color":"ffffffff","curve":"stepped"},{"time":0.5,"color":"ffffffff"},{"time":0.6333,"color":"ffffff00"}],"attachment":[{"time":0.1333,"name":"explore/special.0_0"},{"time":0.2,"name":"explore/special.0_1"},{"time":0.2667,"name":"explore/special.0_2"},{"time":0.3333,"name":"explore/special.0_3"},{"time":0.4,"name":"explore/special.0_4"},{"time":0.4667,"name":"explore/special.0_5"},{"time":0.5333,"name":"explore/special.0_6"},{"time":0.6,"name":null}]},"explore/special.0_2":{"color":[{"time":0,"color":"ffffff00","curve":"stepped"},{"time":0.0333,"color":"ffffff00"},{"time":0.1333,"color":"ffffffff","curve":"stepped"},{"time":0.4667,"color":"ffffffff"},{"time":0.6,"color":"ffffff00"}],"attachment":[{"time":0.1,"name":"explore/special.0_0"},{"time":0.1667,"name":"explore/special.0_1"},{"time":0.2333,"name":"explore/special.0_2"},{"time":0.3,"name":"explore/special.0_3"},{"time":0.3667,"name":"explore/special.0_4"},{"time":0.4333,"name":"explore/special.0_5"},{"time":0.5,"name":"explore/special.0_6"},{"time":0.5667,"name":null}]},"explore/special.0_3":{"color":[{"time":0,"color":"ffffff00","curve":"stepped"},{"time":0.1,"color":"ffffff00"},{"time":0.2,"color":"ffffffff","curve":"stepped"},{"time":0.5333,"color":"ffffffff"},{"time":0.6667,"color":"ffffff00"}],"attachment":[{"time":0.1667,"name":"explore/special.0_0"},{"time":0.2333,"name":"explore/special.0_1"},{"time":0.3,"name":"explore/special.0_2"},{"time":0.3667,"name":"explore/special.0_3"},{"time":0.4333,"name":"explore/special.0_4"},{"time":0.5,"name":"explore/special.0_5"},{"time":0.5667,"name":"explore/special.0_6"},{"time":0.6333,"name":null}]},"item3":{"color":[{"time":0,"color":"ffffff00"}]},"khung4":{"color":[{"time":0,"color":"ffffff00"}]},"lightitem5":{"color":[{"time":0,"color":"ffffff00"}]}},"bones":{"item3":{"scale":[{"time":0,"x":0.969,"y":0.969}]},"gach3":{"rotate":[{"time":0,"angle":0,"curve":"stepped"},{"time":0.0667,"angle":0},{"time":0.2333,"angle":33.98},{"time":0.4333,"angle":161.39}],"translate":[{"time":0,"x":1.91,"y":-2.55,"curve":"stepped"},{"time":0.0667,"x":1.91,"y":-2.55},{"time":0.4333,"x":-36.11,"y":-117.14}],"scale":[{"time":0,"x":1,"y":1,"curve":"stepped"},{"time":0.0667,"x":1,"y":1}]},"gach2":{"rotate":[{"time":0,"angle":-12.79,"curve":"stepped"},{"time":0.0667,"angle":-12.79},{"time":0.4333,"angle":178.81}],"translate":[{"time":0,"x":56.54,"y":-9.42,"curve":"stepped"},{"time":0.0667,"x":56.54,"y":-9.42},{"time":0.4333,"x":137.74,"y":-81.58}],"scale":[{"time":0,"x":1,"y":1,"curve":"stepped"},{"time":0.0667,"x":1,"y":1}]},"gach4":{"rotate":[{"time":0,"angle":147.69,"curve":"stepped"},{"time":0.0667,"angle":147.69},{"time":0.4333,"angle":-23.23}],"translate":[{"time":0,"x":20.67,"y":-14.31,"curve":"stepped"},{"time":0.0667,"x":20.67,"y":-14.31},{"time":0.4333,"x":17.79,"y":-105.87}],"scale":[{"time":0,"x":1,"y":1,"curve":"stepped"},{"time":0.0667,"x":1,"y":1}]},"gach1":{"translate":[{"time":0,"x":0,"y":0,"curve":[0.147,0.21,0.744,1]},{"time":0.5333,"x":106.21,"y":-1.91}],"scale":[{"time":0,"x":1,"y":1}]},"UD":{"rotate":[{"time":0,"angle":14.02,"curve":"stepped"},{"time":0.0667,"angle":14.02,"curve":[0.25,0,0.75,1]},{"time":0.5667,"angle":-23.5}],"translate":[{"time":0,"x":0,"y":0,"curve":"stepped"},{"time":0.0667,"x":0,"y":0,"curve":[0.189,0.13,0.684,1]},{"time":0.3,"x":0,"y":18.33,"curve":[0.25,0,0.849,0.65]},{"time":0.5667,"x":0,"y":-44.34}]},"UD2":{"rotate":[{"time":0,"angle":14.02,"curve":"stepped"},{"time":0.0667,"angle":14.02},{"time":0.3,"angle":119.66},{"time":0.5667,"angle":-136.3}],"translate":[{"time":0,"x":0,"y":0,"curve":"stepped"},{"time":0.0667,"x":0,"y":0},{"time":0.3,"x":8.96,"y":19.95},{"time":0.5667,"x":5.28,"y":-70.01}]},"gach5":{"translate":[{"time":0,"x":0,"y":0,"curve":[0.147,0.21,0.744,1]},{"time":0.5333,"x":-76.91,"y":-1.91}],"scale":[{"time":0,"x":1,"y":1}]},"gach6":{"rotate":[{"time":0,"angle":147.69,"curve":"stepped"},{"time":0.0667,"angle":147.69},{"time":0.4333,"angle":-51.62}],"translate":[{"time":0,"x":0.01,"y":-11.21,"curve":"stepped"},{"time":0.0667,"x":0.01,"y":-11.21},{"time":0.4333,"x":-85.41,"y":36.03}],"scale":[{"time":0,"x":1,"y":1,"curve":"stepped"},{"time":0.0667,"x":1,"y":1}]},"gach7":{"rotate":[{"time":0,"angle":0,"curve":"stepped"},{"time":0.0667,"angle":0},{"time":0.4333,"angle":195.75}],"translate":[{"time":0,"x":1.91,"y":-2.55,"curve":"stepped"},{"time":0.0667,"x":1.91,"y":-2.55},{"time":0.4333,"x":61.38,"y":23.22}],"scale":[{"time":0,"x":1,"y":1,"curve":"stepped"},{"time":0.0667,"x":1,"y":1}]},"gach8":{"rotate":[{"time":0,"angle":-12.79,"curve":"stepped"},{"time":0.0667,"angle":-12.79},{"time":0.4333,"angle":-86.42}],"translate":[{"time":0,"x":0,"y":0,"curve":"stepped"},{"time":0.0667,"x":0,"y":0},{"time":0.4333,"x":-139.46,"y":-112.35}],"scale":[{"time":0,"x":1,"y":1,"curve":"stepped"},{"time":0.0667,"x":1,"y":1}]},"gach_ALL":{"rotate":[{"time":0,"angle":0}],"translate":[{"time":0,"x":0,"y":19.21},{"time":0.4667,"x":0,"y":11.92}],"scale":[{"time":0,"x":1,"y":1},{"time":0.4667,"x":1.2,"y":1.2}]},"gach9":{"rotate":[{"time":0,"angle":-12.79,"curve":"stepped"},{"time":0.0667,"angle":-12.79},{"time":0.4333,"angle":159.22}],"translate":[{"time":0,"x":0,"y":0,"curve":"stepped"},{"time":0.0667,"x":0,"y":0},{"time":0.4333,"x":-93.36,"y":-128.59}],"scale":[{"time":0,"x":1,"y":1,"curve":"stepped"},{"time":0.0667,"x":1,"y":1}]},"gach10":{"rotate":[{"time":0,"angle":0,"curve":"stepped"},{"time":0.0667,"angle":0},{"time":0.4333,"angle":195.75}],"translate":[{"time":0,"x":1.91,"y":-2.55,"curve":"stepped"},{"time":0.0667,"x":1.91,"y":-2.55},{"time":0.4333,"x":61.38,"y":23.22}],"scale":[{"time":0,"x":1,"y":1,"curve":"stepped"},{"time":0.0667,"x":1,"y":1}]},"gach11":{"rotate":[{"time":0,"angle":147.69,"curve":"stepped"},{"time":0.0667,"angle":147.69},{"time":0.4,"angle":-51.62}],"translate":[{"time":0,"x":0.01,"y":-11.21,"curve":"stepped"},{"time":0.0667,"x":0.01,"y":-11.21},{"time":0.4,"x":-44.1,"y":36.81}],"scale":[{"time":0,"x":1,"y":1,"curve":"stepped"},{"time":0.0667,"x":1,"y":1}]},"UD3":{"rotate":[{"time":0,"angle":14.02,"curve":"stepped"},{"time":0.0667,"angle":14.02},{"time":0.3,"angle":119.66},{"time":0.5667,"angle":-136.3}],"translate":[{"time":0,"x":0,"y":0,"curve":"stepped"},{"time":0.0667,"x":0,"y":0},{"time":0.3,"x":0,"y":18.33},{"time":0.5667,"x":0,"y":-44.34}]},"gach12":{"translate":[{"time":0,"x":0,"y":0,"curve":[0.147,0.21,0.744,1]},{"time":0.5333,"x":-76.91,"y":-1.91}],"scale":[{"time":0,"x":1,"y":1}]},"gach13":{"rotate":[{"time":0,"angle":147.69,"curve":"stepped"},{"time":0.0667,"angle":147.69},{"time":0.4333,"angle":-23.23}],"translate":[{"time":0,"x":20.67,"y":-14.31,"curve":"stepped"},{"time":0.0667,"x":20.67,"y":-14.31},{"time":0.4333,"x":41.95,"y":-105.09}],"scale":[{"time":0,"x":1,"y":1,"curve":"stepped"},{"time":0.0667,"x":1,"y":1}]},"gach14":{"rotate":[{"time":0,"angle":0,"curve":"stepped"},{"time":0.0667,"angle":0},{"time":0.2333,"angle":33.98},{"time":0.4333,"angle":161.39}],"translate":[{"time":0,"x":1.91,"y":-2.55,"curve":"stepped"},{"time":0.0667,"x":1.91,"y":-2.55},{"time":0.4333,"x":-36.11,"y":-117.14}],"scale":[{"time":0,"x":1,"y":1,"curve":"stepped"},{"time":0.0667,"x":1,"y":1}]},"gach15":{"rotate":[{"time":0,"angle":-12.79,"curve":"stepped"},{"time":0.0667,"angle":-12.79},{"time":0.4333,"angle":178.81}],"translate":[{"time":0,"x":56.54,"y":-9.42,"curve":"stepped"},{"time":0.0667,"x":56.54,"y":-9.42},{"time":0.4333,"x":137.74,"y":-81.58}],"scale":[{"time":0,"x":1,"y":1,"curve":"stepped"},{"time":0.0667,"x":1,"y":1}]},"UD4":{"rotate":[{"time":0,"angle":14.02,"curve":"stepped"},{"time":0.0667,"angle":14.02,"curve":[0.252,0,0.622,0.48]},{"time":0.3,"angle":161.05,"curve":[0.372,0.48,0.752,1]},{"time":0.5667,"angle":-23.5}],"translate":[{"time":0,"x":0,"y":0,"curve":"stepped"},{"time":0.0667,"x":0,"y":0,"curve":[0.189,0.13,0.684,1]},{"time":0.3,"x":0,"y":18.33,"curve":[0.25,0,0.849,0.65]},{"time":0.5667,"x":83.74,"y":-19.2}]},"gach16":{"translate":[{"time":0,"x":0,"y":0,"curve":[0.147,0.21,0.744,1]},{"time":0.6,"x":106.21,"y":-1.91}],"scale":[{"time":0,"x":1,"y":1}]},"gach17":{"rotate":[{"time":0,"angle":0,"curve":"stepped"},{"time":0.0667,"angle":0},{"time":0.4333,"angle":195.75}],"translate":[{"time":0,"x":1.91,"y":-2.55,"curve":"stepped"},{"time":0.0667,"x":1.91,"y":-2.55},{"time":0.4333,"x":21.2,"y":-26.63}],"scale":[{"time":0,"x":1,"y":1,"curve":"stepped"},{"time":0.0667,"x":1,"y":1}]},"gach18":{"rotate":[{"time":0,"angle":147.69,"curve":"stepped"},{"time":0.0667,"angle":147.69},{"time":0.4667,"angle":-51.62}],"translate":[{"time":0,"x":0.01,"y":-11.21,"curve":"stepped"},{"time":0.0667,"x":0.01,"y":-11.21},{"time":0.4667,"x":-15.83,"y":-62.9}],"scale":[{"time":0,"x":1,"y":1,"curve":"stepped"},{"time":0.0667,"x":1,"y":1}]},"gach19":{"rotate":[{"time":0,"angle":147.69,"curve":"stepped"},{"time":0.0667,"angle":147.69},{"time":0.4333,"angle":-41.95}],"translate":[{"time":0,"x":20.67,"y":-14.31,"curve":"stepped"},{"time":0.0667,"x":20.67,"y":-14.31},{"time":0.4333,"x":-52.54,"y":-61.19}],"scale":[{"time":0,"x":1,"y":1,"curve":"stepped"},{"time":0.0667,"x":1,"y":1}]},"gach20":{"rotate":[{"time":0,"angle":-12.79,"curve":"stepped"},{"time":0.0667,"angle":-12.79},{"time":0.4333,"angle":128.12}],"translate":[{"time":0,"x":56.54,"y":-9.42,"curve":"stepped"},{"time":0.0667,"x":56.54,"y":-9.42},{"time":0.4333,"x":71.51,"y":-86.79}],"scale":[{"time":0,"x":1,"y":1,"curve":"stepped"},{"time":0.0667,"x":1,"y":1}]},"smokebom":{"scale":[{"time":0,"x":0.5,"y":0.5},{"time":0.5667,"x":2,"y":2}]},"smokebom2":{"rotate":[{"time":0,"angle":-161.89}],"translate":[{"time":0,"x":-22.12,"y":18.43,"curve":"stepped"},{"time":0.0667,"x":-22.12,"y":18.43}],"scale":[{"time":0,"x":0.5,"y":0.5,"curve":"stepped"},{"time":0.0667,"x":0.5,"y":0.5},{"time":0.6333,"x":2,"y":2}]},"smokebom3":{"rotate":[{"time":0,"angle":-179.8,"curve":"stepped"},{"time":0.0333,"angle":-179.8}],"translate":[{"time":0,"x":7.37,"y":-18.44,"curve":"stepped"},{"time":0.0333,"x":7.37,"y":-18.44}],"scale":[{"time":0,"x":0.5,"y":0.5,"curve":"stepped"},{"time":0.0333,"x":0.5,"y":0.5},{"time":0.6,"x":2,"y":2}]},"smokebom4":{"rotate":[{"time":0,"angle":-161.89}],"translate":[{"time":0,"x":20.76,"y":20.75}],"scale":[{"time":0,"x":0.5,"y":0.5,"curve":"stepped"},{"time":0.1,"x":0.5,"y":0.5},{"time":0.6667,"x":2,"y":2}]}}},"anim_normal":{"slots":{"lightitem5":{"color":[{"time":0,"color":"ffffff00","curve":[0.25,0,0.75,1]},{"time":0.6667,"color":"ffffffff","curve":[0.25,0,0.75,1]},{"time":1.3333,"color":"ffffff00","curve":[0.25,0,0.75,1]},{"time":2,"color":"ffffffff","curve":[0.25,0,0.75,1]},{"time":2.6667,"color":"ffffff00"}]}},"bones":{"item3":{"scale":[{"time":0,"x":0.969,"y":0.969,"curve":[0.25,0,0.75,1]},{"time":0.6667,"x":1.01,"y":1.01,"curve":[0.25,0,0.75,1]},{"time":1.3333,"x":0.969,"y":0.969,"curve":[0.25,0,0.75,1]},{"time":2,"x":1.01,"y":1.01,"curve":[0.25,0,0.75,1]},{"time":2.6667,"x":0.969,"y":0.969}]}}},"anim_rung":{"slots":{"lightitem5":{"color":[{"time":0,"color":"ffffff00","curve":[0.25,0,0.75,1]},{"time":0.6667,"color":"ffffffff","curve":[0.25,0,0.75,1]},{"time":1.3333,"color":"ffffff00","curve":[0.25,0,0.75,1]},{"time":2,"color":"ffffffff","curve":[0.25,0,0.75,1]},{"time":2.6667,"color":"ffffff00"}]}},"bones":{"item3":{"scale":[{"time":0,"x":0.969,"y":0.969,"curve":[0.25,0,0.75,1]},{"time":0.6667,"x":1.01,"y":1.01,"curve":[0.25,0,0.75,1]},{"time":1.3333,"x":0.969,"y":0.969,"curve":[0.25,0,0.75,1]},{"time":2,"x":1.01,"y":1.01,"curve":[0.25,0,0.75,1]},{"time":2.6667,"x":0.969,"y":0.969}]},"khung4":{"rotate":[{"time":0.0333,"angle":-1.42,"curve":[0.25,0,0.75,1]},{"time":0.1,"angle":1.05,"curve":[0.25,0,0.75,1]},{"time":0.1667,"angle":-0.22,"curve":[0.25,0,0.75,1]},{"time":0.2333,"angle":0.56,"curve":[0.25,0,0.75,1]},{"time":0.3,"angle":2.85,"curve":[0.25,0,0.75,1]},{"time":0.3667,"angle":-1.55,"curve":[0.25,0,0.75,1]},{"time":0.4333,"angle":-0.13,"curve":[0.25,0,0.75,1]},{"time":0.5,"angle":4.19,"curve":[0.25,0,0.75,1]},{"time":0.5667,"angle":-1.62,"curve":[0.25,0,0.75,1]},{"time":0.6333,"angle":0.67,"curve":[0.25,0,0.75,1]},{"time":0.7,"angle":-1.42,"curve":[0.25,0,0.75,1]},{"time":0.7667,"angle":1.05,"curve":[0.25,0,0.75,1]},{"time":0.8333,"angle":-0.22,"curve":[0.25,0,0.75,1]},{"time":0.9,"angle":0.56,"curve":[0.25,0,0.75,1]},{"time":0.9667,"angle":2.85,"curve":[0.25,0,0.75,1]},{"time":1.0333,"angle":-1.55,"curve":[0.25,0,0.75,1]},{"time":1.1,"angle":-0.13,"curve":[0.25,0,0.75,1]},{"time":1.1667,"angle":4.19,"curve":[0.25,0,0.75,1]},{"time":1.2333,"angle":-1.62,"curve":[0.25,0,0.75,1]},{"time":1.3,"angle":0.67,"curve":[0.25,0,0.75,1]},{"time":1.3667,"angle":-1.42,"curve":[0.25,0,0.75,1]},{"time":1.4333,"angle":1.05,"curve":[0.25,0,0.75,1]},{"time":1.5,"angle":-0.22,"curve":[0.25,0,0.75,1]},{"time":1.5667,"angle":0.56,"curve":[0.25,0,0.75,1]},{"time":1.6333,"angle":2.85,"curve":[0.25,0,0.75,1]},{"time":1.7,"angle":-1.55,"curve":[0.25,0,0.75,1]},{"time":1.7667,"angle":-0.13,"curve":[0.25,0,0.75,1]},{"time":1.8333,"angle":4.19,"curve":[0.25,0,0.75,1]},{"time":1.9,"angle":-1.62,"curve":[0.25,0,0.75,1]},{"time":1.9667,"angle":0.67,"curve":[0.25,0,0.75,1]},{"time":2.0333,"angle":-1.55,"curve":[0.25,0,0.75,1]},{"time":2.1,"angle":-0.13,"curve":[0.25,0,0.75,1]},{"time":2.1667,"angle":4.19,"curve":[0.25,0,0.75,1]},{"time":2.2333,"angle":-1.62,"curve":[0.25,0,0.75,1]},{"time":2.3,"angle":0.67,"curve":[0.25,0,0.75,1]},{"time":2.3667,"angle":-1.42,"curve":[0.25,0,0.75,1]},{"time":2.4333,"angle":1.05,"curve":[0.25,0,0.75,1]},{"time":2.5,"angle":-0.22,"curve":[0.25,0,0.75,1]},{"time":2.5667,"angle":0.56,"curve":[0.25,0,0.75,1]},{"time":2.6333,"angle":2.85}],"translate":[{"time":0,"x":0,"y":0,"curve":[0.25,0,0.75,1]},{"time":0.0667,"x":3.29,"y":-0.87,"curve":[0.25,0,0.75,1]},{"time":0.1333,"x":0.93,"y":1.45,"curve":[0.25,0,0.75,1]},{"time":0.2,"x":2.33,"y":-3.67,"curve":[0.25,0,0.75,1]},{"time":0.2667,"x":-0.78,"y":0.27,"curve":[0.25,0,0.75,1]},{"time":0.3333,"x":2.56,"y":2.81,"curve":[0.25,0,0.75,1]},{"time":0.4,"x":-0.87,"y":-4.88,"curve":[0.25,0,0.75,1]},{"time":0.4667,"x":2.05,"y":-1.35,"curve":[0.25,0,0.75,1]},{"time":0.5333,"x":-1.26,"y":1.42,"curve":[0.25,0,0.75,1]},{"time":0.6,"x":1.3,"y":-5.35,"curve":[0.25,0,0.75,1]},{"time":0.6667,"x":-1.33,"y":0,"curve":[0.25,0,0.75,1]},{"time":0.7333,"x":2.53,"y":-0.02,"curve":[0.25,0,0.75,1]},{"time":0.8,"x":0.23,"y":-6.65,"curve":[0.25,0,0.75,1]},{"time":0.8667,"x":2.33,"y":-0.05,"curve":[0.25,0,0.75,1]},{"time":0.9333,"x":-2.3,"y":-0.49,"curve":[0.25,0,0.75,1]},{"time":1,"x":0,"y":0,"curve":[0.25,0,0.75,1]},{"time":1.0667,"x":3.29,"y":-0.87,"curve":[0.25,0,0.75,1]},{"time":1.1333,"x":0.93,"y":1.45,"curve":[0.25,0,0.75,1]},{"time":1.2,"x":2.33,"y":-3.67,"curve":[0.25,0,0.75,1]},{"time":1.2667,"x":-0.78,"y":0.27,"curve":[0.25,0,0.75,1]},{"time":1.3333,"x":2.56,"y":2.81,"curve":[0.25,0,0.75,1]},{"time":1.4,"x":-0.87,"y":-4.88,"curve":[0.25,0,0.75,1]},{"time":1.4667,"x":2.05,"y":-1.35,"curve":[0.25,0,0.75,1]},{"time":1.5333,"x":-1.26,"y":1.42,"curve":[0.25,0,0.75,1]},{"time":1.6,"x":1.3,"y":-5.35,"curve":[0.25,0,0.75,1]},{"time":1.6667,"x":-1.33,"y":0,"curve":[0.25,0,0.75,1]},{"time":1.7333,"x":2.53,"y":-0.02,"curve":[0.25,0,0.75,1]},{"time":1.8,"x":0.23,"y":-6.65,"curve":[0.25,0,0.75,1]},{"time":1.8667,"x":2.33,"y":-0.05,"curve":[0.25,0,0.75,1]},{"time":1.9333,"x":-2.3,"y":-0.49,"curve":[0.25,0,0.75,1]},{"time":2,"x":0,"y":0,"curve":[0.25,0,0.75,1]},{"time":2.0667,"x":3.29,"y":-0.87,"curve":[0.25,0,0.75,1]},{"time":2.1333,"x":0.93,"y":1.45,"curve":[0.25,0,0.75,1]},{"time":2.2,"x":2.33,"y":-3.67,"curve":[0.25,0,0.75,1]},{"time":2.2667,"x":-0.78,"y":0.27,"curve":[0.25,0,0.75,1]},{"time":2.3333,"x":2.56,"y":2.81,"curve":[0.25,0,0.75,1]},{"time":2.4,"x":-0.87,"y":-4.88,"curve":[0.25,0,0.75,1]},{"time":2.4667,"x":2.05,"y":-1.35,"curve":[0.25,0,0.75,1]},{"time":2.5333,"x":-1.26,"y":1.42,"curve":[0.25,0,0.75,1]},{"time":2.6,"x":1.3,"y":-5.35,"curve":[0.25,0,0.75,1]},{"time":2.6667,"x":-1.33,"y":0}]}}}}},"_atlasText":"\nitem3.png\nsize: 1024,256\nformat: RGBA8888\nfilter: Linear,Linear\nrepeat: none\nexplore/gach1\n  rotate: false\n  xy: 2, 31\n  size: 50, 11\n  orig: 50, 11\n  offset: 0, 0\n  index: -1\nexplore/gach2\n  rotate: false\n  xy: 189, 61\n  size: 38, 20\n  orig: 38, 20\n  offset: 0, 0\n  index: -1\nexplore/gach3\n  rotate: false\n  xy: 577, 8\n  size: 41, 16\n  orig: 41, 16\n  offset: 0, 0\n  index: -1\nexplore/gach4\n  rotate: false\n  xy: 934, 213\n  size: 52, 17\n  orig: 52, 17\n  offset: 0, 0\n  index: -1\nexplore/special.0_0\n  rotate: false\n  xy: 339, 117\n  size: 117, 113\n  orig: 117, 113\n  offset: 0, 0\n  index: -1\nexplore/special.0_1\n  rotate: false\n  xy: 458, 117\n  size: 117, 113\n  orig: 117, 113\n  offset: 0, 0\n  index: -1\nexplore/special.0_2\n  rotate: false\n  xy: 577, 117\n  size: 117, 113\n  orig: 117, 113\n  offset: 0, 0\n  index: -1\nexplore/special.0_3\n  rotate: false\n  xy: 696, 117\n  size: 117, 113\n  orig: 117, 113\n  offset: 0, 0\n  index: -1\nexplore/special.0_4\n  rotate: false\n  xy: 815, 117\n  size: 117, 113\n  orig: 117, 113\n  offset: 0, 0\n  index: -1\nexplore/special.0_5\n  rotate: false\n  xy: 339, 2\n  size: 117, 113\n  orig: 117, 113\n  offset: 0, 0\n  index: -1\nexplore/special.0_6\n  rotate: false\n  xy: 458, 2\n  size: 117, 113\n  orig: 117, 113\n  offset: 0, 0\n  index: -1\nitem3\n  rotate: false\n  xy: 189, 83\n  size: 148, 147\n  orig: 148, 147\n  offset: 0, 0\n  index: -1\nkhung1\n  rotate: false\n  xy: 2, 44\n  size: 185, 186\n  orig: 185, 186\n  offset: 0, 0\n  index: -1\nlightitem3\n  rotate: false\n  xy: 577, 26\n  size: 95, 89\n  orig: 95, 89\n  offset: 0, 0\n  index: -1\n","textures":[{"__uuid__":"fbAdlMBx5JnpE+geRQFEyM"}],"textureNames":["item3.png"]}